Workbook

Sheet Report
A1: GITHUB Issues Tracker | M1: Open Issues - Type | S1: Open Issues - Assignee
A2: Date: 17Dec25 @ 10 AM EST | S2: Date: 17Dec25 @ 10 AM EST
A3: Repository | B3: App Name | C3: Open | D3: Closed | E3: Total | F3: % Complete | G3: Change | M3: P1: Task | N3: P2:Bug | O3: P3: Features | P3: Not Specified | S3: Name | T3: Task Count | U3: Tes-BE | V3: Tes-FE | W3: Tes-Pl | X3: Rap | Y3: RapFE | Z3: PSO | AA3: ZWar | AB3: GIT | AC3: ProPul | AD3: AS | AE3: ZWor | AF3: Git RB | AG3: Notes
A4: cloudwarriors-ai/Tesseract | B4: Tesseract - Backend | C4: =COUNTIFS('All Issues'!B:B, "*Tesseract - Backend*", 'All Issues'!E:E, "open") -> 14 | D4: =COUNTIFS('All Issues'!B:B, "*Tesseract - Backend*", 'All Issues'!E:E, "closed") -> 66 | E4: =COUNTIF('All Issues'!B:B, "*Tesseract - Backend*") -> 80 | F4: =D4/$E$4 -> 0.825 | G4: ↔️ | M4: =COUNTIFS('All Issues'!B:B, "*Tesseract - Backend*", 'All Issues'!E:E, "open", 'All Issues'!M:M, "Task") -> 13 | N4: =COUNTIFS('All Issues'!B:B, "*Tesseract - Backend*", 'All Issues'!E:E, "open", 'All Issues'!M:M, "Bug") -> 1 | O4: =COUNTIFS('All Issues'!B:B, "*Tesseract - Backend*", 'All Issues'!E:E, "open", 'All Issues'!M:M, "Feature") -> 0 | P4: =COUNTIFS('All Issues'!B:B, "*Tesseract - Backend*", 'All Issues'!E:E, "open", 'All Issues'!M:M, "Not Specified") -> 0 | S4: Voipin | T4: =COUNTIFS('All Issues'!E:E, "open", 'All Issues'!O:O, "*voipin*") -> 0
A5: cloudwarriors-ai/tesseract-frontend | B5: Tesseract - Frontend | C5: =COUNTIFS('All Issues'!B:B, "*Tesseract - Frontend*", 'All Issues'!E:E, "open") -> 4 | D5: =COUNTIFS('All Issues'!B:B, "*Tesseract - Frontend*", 'All Issues'!E:E, "closed") -> 58 | E5: =COUNTIF('All Issues'!B:B, "*Tesseract - Frontend*") -> 62 | F5: =D5/$E$5 -> 0.93548387 | G5: ↔️ | M5: =COUNTIFS('All Issues'!B:B, "*Tesseract - Frontend*", 'All Issues'!E:E, "open", 'All Issues'!M:M, "Task") -> 1 | N5: =COUNTIFS('All Issues'!B:B, "*Tesseract - Frontend*", 'All Issues'!E:E, "open", 'All Issues'!M:M, "Bug") -> 2 | O5: =COUNTIFS('All Issues'!B:B, "*Tesseract - Frontend*", 'All Issues'!E:E, "open", 'All Issues'!M:M, "Feature") -> 1 | P5: =COUNTIFS('All Issues'!B:B, "*Tesseract - Frontend*", 'All Issues'!E:E, "open", 'All Issues'!M:M, "Not Specified") -> 0 | S5: Chaddacus | T5: =COUNTIFS('All Issues'!E:E, "open", 'All Issues'!O:O, "*Chaddacus*") -> 13 | X5: 1 | Y5: 10 | AD5: 2
A6: cloudwarriors-ai/tesseract-platform | B6: Tessereact Platform | C6: =COUNTIFS('All Issues'!B:B, "*Tesseract Platform*", 'All Issues'!E:E, "open") -> 2 | D6: =COUNTIFS('All Issues'!B:B, "*Tesseract Platform*", 'All Issues'!E:E, "closed") -> 1 | E6: =COUNTIF('All Issues'!B:B, "*Tesseract Platform*") -> 3 | F6: =D6/$E$5 -> 0.016129032 | G6: ⬆️ | M6: =COUNTIFS('All Issues'!B:B, "*Tesseract Platform*", 'All Issues'!E:E, "open", 'All Issues'!M:M, "Task") -> 1 | N6: =COUNTIFS('All Issues'!B:B, "*Tesseract Platform*", 'All Issues'!E:E, "open", 'All Issues'!M:M, "Bug") -> 0 | O6: =COUNTIFS('All Issues'!B:B, "*Tesseract Platform*", 'All Issues'!E:E, "open", 'All Issues'!M:M, "Feature") -> 0 | P6: =COUNTIFS('All Issues'!B:B, "*Tesseract Platform*", 'All Issues'!E:E, "open", 'All Issues'!M:M, "Not Specified") -> 1 | S6: trentcharlton | T6: =COUNTIFS('All Issues'!E:E, "open", 'All Issues'!O:O, "*trentcharlton*") -> 14 | U6: 4 | V6: 1 | W6: 2 | Y6: 7
A7: cloudwarriors-ai/rapture | B7: MACD - Rapture | C7: =COUNTIFS('All Issues'!B:B, "*MACD - Rapture*", 'All Issues'!E:E, "open") -> 2 | D7: =COUNTIFS('All Issues'!B:B, "*MACD - Rapture*", 'All Issues'!E:E, "closed") -> 28 | E7: =COUNTIF('All Issues'!B:B, "*MACD - Rapture*") -> 30 | F7: =D7/E7 -> 0.93333333 | G7: ↔️ | M7: =COUNTIFS('All Issues'!B:B, "*MACD - Rapture*", 'All Issues'!E:E, "open", 'All Issues'!M:M, "Task") -> 0 | N7: =COUNTIFS('All Issues'!B:B, "*MACD - Rapture*", 'All Issues'!E:E, "open", 'All Issues'!M:M, "Bug") -> 1 | O7: =COUNTIFS('All Issues'!B:B, "*MACD - Rapture*", 'All Issues'!E:E, "open", 'All Issues'!M:M, "Feature") -> 1 | P7: =COUNTIFS('All Issues'!B:B, "*MACD - Rapture*", 'All Issues'!E:E, "open", 'All Issues'!M:M, "Not Specified") -> 0 | S7: Jeffrey-Searcy | T7: =COUNTIFS('All Issues'!E:E, "open", 'All Issues'!O:O, "*Jeffrey-Searcy*") -> 6 | U7: 6
A8: cloudwarriors-ai/rapture-frontend | B8: MACD - PSCX Frontend | C8: =COUNTIFS('All Issues'!B:B, "*MACD - PSCX Frontend*", 'All Issues'!E:E, "open") -> 19 | D8: =COUNTIFS('All Issues'!B:B, "*MACD - PSCX Frontend*", 'All Issues'!E:E, "closed") -> 86 | E8: =COUNTIF('All Issues'!B:B, "*MACD - PSCX Frontend*") -> 105 | F8: =D8/E8 -> 0.81904762 | G8: ↔️ | M8: =COUNTIFS('All Issues'!B:B, "*MACD - PSCX Frontend*", 'All Issues'!E:E, "open", 'All Issues'!M:M, "Task") -> 5 | N8: =COUNTIFS('All Issues'!B:B, "*MACD - PSCX Frontend*", 'All Issues'!E:E, "open", 'All Issues'!M:M, "Bug") -> 3 | O8: =COUNTIFS('All Issues'!B:B, "*MACD - PSCX Frontend*", 'All Issues'!E:E, "open", 'All Issues'!M:M, "Feature") -> 11 | P8: =COUNTIFS('All Issues'!B:B, "*MACD - PSCX Frontend*", 'All Issues'!E:E, "open", 'All Issues'!M:M, "Not Specified") -> 0 | S8: jvitato1 | T8: =COUNTIFS('All Issues'!E:E, "open", 'All Issues'!O:O, "*jvitato1*") -> 4 | V8: 1 | W8: 1 | AB8: 2
A9: cloudwarriors-ai/PSO-Quoting-Tool | B9: PSO Tool | C9: =COUNTIFS('All Issues'!B:B, "*PSO Tool*", 'All Issues'!E:E, "open") -> 2 | D9: =COUNTIFS('All Issues'!B:B, "*PSO Tool*", 'All Issues'!E:E, "closed") -> 17 | E9: =COUNTIF('All Issues'!B:B, "*PSO Tool*") -> 19 | F9: =D9/E9 -> 0.89473684 | G9: ⬇️ | M9: =COUNTIFS('All Issues'!B:B, "*PSO Tool*", 'All Issues'!E:E, "open", 'All Issues'!M:M, "Task") -> 1 | N9: =COUNTIFS('All Issues'!B:B, "*PSO Tool*", 'All Issues'!E:E, "open", 'All Issues'!M:M, "Bug") -> 0 | O9: =COUNTIFS('All Issues'!B:B, "*PSO Tool*", 'All Issues'!E:E, "open", 'All Issues'!M:M, "Feature") -> 1 | P9: =COUNTIFS('All Issues'!B:B, "*PSO Tool*", 'All Issues'!E:E, "open", 'All Issues'!M:M, "Not Specified") -> 0 | S9: Matt-Keuning | T9: =COUNTIFS('All Issues'!E:E, "open", 'All Issues'!O:O, "*Matt-Keuning*") -> 14 | U9: 7 | V9: 1 | AA9: 6
A10: cloudwarriors-ai/zoomwarriors_2 | B10: Zoom Warriors | C10: =COUNTIFS('All Issues'!B:B, "*Zoom Warriors*", 'All Issues'!E:E, "open") -> 6 | D10: =COUNTIFS('All Issues'!B:B, "*Zoom Warriors*", 'All Issues'!E:E, "closed") -> 100 | E10: =COUNTIF('All Issues'!B:B, "*Zoom Warriors*") -> 106 | F10: =D10/E10 -> 0.94339623 | G10: ⬆️ | M10: =COUNTIFS('All Issues'!B:B, "*Zoom Warriors*", 'All Issues'!E:E, "open", 'All Issues'!M:M, "Task") -> 1 | N10: =COUNTIFS('All Issues'!B:B, "*Zoom Warriors*", 'All Issues'!E:E, "open", 'All Issues'!M:M, "Bug") -> 0 | O10: =COUNTIFS('All Issues'!B:B, "*Zoom Warriors*", 'All Issues'!E:E, "open", 'All Issues'!M:M, "Feature") -> 5 | P10: =COUNTIFS('All Issues'!B:B, "*Zoom Warriors*", 'All Issues'!E:E, "open", 'All Issues'!M:M, "Not Specified") -> 0 | S10: campbellayers | T10: =COUNTIFS('All Issues'!E:E, "open", 'All Issues'!O:O, "*campbellayers*") -> 4 | Z10: 2 | AB10: 2
A11: cloudwarriors-ai/github_issues_tracker | B11: GitHub Issues Tracker | C11: =COUNTIFS('All Issues'!B:B, "*GitHub Issues Tracker*", 'All Issues'!E:E, "open") -> 2 | D11: =COUNTIFS('All Issues'!B:B, "*GitHub Issues Tracker*", 'All Issues'!E:E, "closed") -> 1 | E11: =COUNTIF('All Issues'!B:B, "*GitHub Issues Tracker*") -> 3 | F11: =D11/E11 -> 0.33333333 | G11: ↔️ | M11: =COUNTIFS('All Issues'!B:B, "*GitHub Issues Tracker*", 'All Issues'!E:E, "open", 'All Issues'!M:M, "Task") -> 0 | N11: =COUNTIFS('All Issues'!B:B, "*GitHub Issues Tracker*", 'All Issues'!E:E, "open", 'All Issues'!M:M, "Bug") -> 0 | O11: =COUNTIFS('All Issues'!B:B, "*GitHub Issues Tracker*", 'All Issues'!E:E, "open", 'All Issues'!M:M, "Feature") -> 2 | P11: =COUNTIFS('All Issues'!B:B, "*GitHub Issues Tracker*", 'All Issues'!E:E, "open", 'All Issues'!M:M, "Not Specified") -> 0 | S11: rebecca-cichy | T11: =COUNTIFS('All Issues'!E:E, "open", 'All Issues'!O:O, "*rebecca-cichy*") -> 7 | V11: 1 | W11: 1 | X11: 2 | Y11: 2 | AC11: 1
A12: cloudwarriors-ai/Project-Pulse | B12: Project Pulse | C12: =COUNTIFS('All Issues'!B:B, "*Project Pulse*", 'All Issues'!E:E, "open") -> 2 | D12: =COUNTIFS('All Issues'!B:B, "*Project Pulse*", 'All Issues'!E:E, "closed") -> 0 | E12: =COUNTIF('All Issues'!B:B, "*Project Pulse*") -> 2 | F12: =D12/E12 -> 0 | G12: ↔️ | M12: =COUNTIFS('All Issues'!B:B, "*Project Pulse*", 'All Issues'!E:E, "open", 'All Issues'!M:M, "Task") -> 1 | N12: =COUNTIFS('All Issues'!B:B, "*Project Pulse*", 'All Issues'!E:E, "open", 'All Issues'!M:M, "Bug") -> 0 | O12: =COUNTIFS('All Issues'!B:B, "*Project Pulse*", 'All Issues'!E:E, "open", 'All Issues'!M:M, "Feature") -> 1 | P12: =COUNTIFS('All Issues'!B:B, "*Project Pulse*", 'All Issues'!E:E, "open", 'All Issues'!M:M, "Not Specified") -> 0 | S12: DsuarezCW | T12: =COUNTIFS('All Issues'!E:E, "open", 'All Issues'!O:O, "*DsuarezCW*") -> 2 | AA12: 2
A13: cloudwarriors-ai/automation-station | B13: Automation Station | C13: =COUNTIFS('All Issues'!B:B, "*Automation Station*", 'All Issues'!E:E, "open") -> 2 | D13: =COUNTIFS('All Issues'!B:B, "*Automation Station*", 'All Issues'!E:E, "closed") -> 18 | E13: =COUNTIF('All Issues'!B:B, "*Automation Station*") -> 20 | F13: =D13/E13 -> 0.9 | G13: ↔️ | M13: =COUNTIFS('All Issues'!B:B, "*Automation Station*", 'All Issues'!E:E, "open", 'All Issues'!M:M, "Task") -> 0 | N13: =COUNTIFS('All Issues'!B:B, "*Automation Station*", 'All Issues'!E:E, "open", 'All Issues'!M:M, "Bug") -> 0 | O13: =COUNTIFS('All Issues'!B:B, "*Automation Station*", 'All Issues'!E:E, "open", 'All Issues'!M:M, "Feature") -> 2 | P13: =COUNTIFS('All Issues'!B:B, "*Automation Station*", 'All Issues'!E:E, "open", 'All Issues'!M:M, "Not Specified") -> 0 | S13: JStab7 | T13: =COUNTIFS('All Issues'!E:E, "open", 'All Issues'!O:O, "*JStab7*") -> 1 | AC13: 1
A14: cloudwarriors-ai/codename_wad | B14: Zoom Workbook | C14: =COUNTIFS('All Issues'!B:B, "*Zoom Workbook*", 'All Issues'!E:E, "open") -> 12 | D14: =COUNTIFS('All Issues'!B:B, "*Zoom Workbook*", 'All Issues'!E:E, "closed") -> 58 | E14: =COUNTIF('All Issues'!B:B, "*Zoom Workbook*") -> 70 | F14: =D14/E14 -> 0.82857143 | G14: ↔️ | M14: =COUNTIFS('All Issues'!B:B, "*Zoom Workbook*", 'All Issues'!E:E, "open", 'All Issues'!M:M, "Task") -> 5 | N14: =COUNTIFS('All Issues'!B:B, "*Zoom Workbook*", 'All Issues'!E:E, "open", 'All Issues'!M:M, "Bug") -> 0 | O14: =COUNTIFS('All Issues'!B:B, "*Zoom Workbook*", 'All Issues'!E:E, "open", 'All Issues'!M:M, "Feature") -> 7 | P14: =COUNTIFS('All Issues'!B:B, "*Zoom Workbook*", 'All Issues'!E:E, "open", 'All Issues'!M:M, "Not Specified") -> 0
A15: cloudwarriors-ai/github_review_build_test | B15: GitHub Review Build | C15: =COUNTIFS('All Issues'!B:B, "*GitHub Review Build*", 'All Issues'!E:E, "open") -> 16 | D15: =COUNTIFS('All Issues'!B:B, "*GitHub Review Build*", 'All Issues'!E:E, "closed") -> 0 | E15: =COUNTIF('All Issues'!B:B, "*GitHub Review Build*") -> 16 | F15: =D15/E15 -> 0 | G15: ↔️ | M15: =COUNTIFS('All Issues'!B:B, "*GitHub Review Build*", 'All Issues'!E:E, "open", 'All Issues'!M:M, "Task") -> 0 | N15: =COUNTIFS('All Issues'!B:B, "*GitHub Review Build*", 'All Issues'!E:E, "open", 'All Issues'!M:M, "Bug") -> 0 | O15: =COUNTIFS('All Issues'!B:B, "*GitHub Review Build*", 'All Issues'!E:E, "open", 'All Issues'!M:M, "Feature") -> 0 | P15: =COUNTIFS('All Issues'!B:B, "*GitHub Review Build*", 'All Issues'!E:E, "open", 'All Issues'!M:M, "Not Specified") -> 16 | S15: TOTALS | T15: =SUM(T4:T14) -> 65 | U15: =SUM(U4:U14) -> 17 | V15: =SUM(V4:V14) -> 4 | W15: =SUM(W4:W14) -> 4 | X15: =SUM(X4:X14) -> 3 | Y15: =SUM(Y4:Y14) -> 19 | Z15: =SUM(Z4:Z14) -> 2 | AA15: =SUM(AA4:AA14) -> 8 | ... AF15: =SUM(AF4:AF14) -> 0
C19: ⬆️ | D19: ↔️ | E19: ⬇️ | F19: FILL IN
C20: *Red Items require Manual Changes
A23: Date: 10Dec25 @ 6 AM EST | S23: Date: 10Dec25 @ 6 AM EST
A24: Repository | B24: App Name | C24: Open | D24: Closed | E24: Total | F24: % Complete | G24: Change | M24: P1: Task | N24: P2:Bug | O24: P3: Features | P24: Not Specified | S24: Name | T24: Task Count | U24: Tes-BE | V24: Tes-FE | W24: Tes-Pl | X24: Rap | Y24: RapFE | Z24: PSO | AA24: ZWar | AB24: GIT | AC24: AS | AD24: ZWor | AE24: Git RB | AF24: Chad | AG24: Supp | AH24: Notes
A25: cloudwarriors-ai/Tesseract | B25: Tesseract - Backend | C25: 14 | D25: 66 | E25: 80 | F25: 0.825 | G25: ↔️ | M25: 13 | N25: 1 | O25: 0 | P25: 0 | S25: Voipin | T25: 0
A26: cloudwarriors-ai/tesseract-frontend | B26: Tesseract - Frontend | C26: 4 | D26: 58 | E26: 62 | F26: 0.93548387 | G26: ↔️ | M26: 1 | N26: 2 | O26: 1 | P26: 0 | S26: Chaddacus | T26: 13 | X26: 1 | Y26: 10 | AC26: 2
A27: cloudwarriors-ai/tesseract-platform | B27: Tessereact Platform | C27: 2 | D27: 0 | E27: 2 | F27: 0 | G27: ↔️ | M27: 1 | N27: 1 | O27: 0 | P27: 0 | S27: trentcharlton | T27: 13 | U27: 4 | V27: 1 | W27: 1 | Y27: 7
A28: cloudwarriors-ai/rapture | B28: MACD - Rapture | C28: 2 | D28: 28 | E28: 30 | F28: 0.93333333 | G28: ↔️ | M28: 0 | N28: 1 | O28: 1 | P28: 0 | S28: Jeffrey-Searcy | T28: 7 | U28: 6 | W28: 1
A29: cloudwarriors-ai/rapture-frontend | B29: MACD - PSCX Frontend | C29: 19 | D29: 86 | E29: 105 | F29: 0.81904762 | G29: ↔️ | M29: 5 | N29: 3 | O29: 11 | P29: 0 | S29: jvitato1 | T29: 3 | V29: 1 | AB29: 2
A30: cloudwarriors-ai/PSO-Quoting-Tool | B30: PSO Tool | C30: 2 | D30: 16 | E30: 18 | F30: 0.88888889 | G30: ↔️ | M30: 2 | N30: 0 | O30: 0 | P30: 0 | S30: Matt-Keuning | T30: 14 | U30: 7 | V30: 1 | AA30: 6
A31: cloudwarriors-ai/zoomwarriors_2 | B31: Zoom Warriors | C31: 6 | D31: 100 | E31: 106 | F31: 0.94339623 | G31: ⬆️ | M31: 1 | N31: 0 | O31: 5 | P31: 0 | S31: campbellayers | T31: 2 | Z31: 2
A32: cloudwarriors-ai/github_issues_tracker | B32: GitHub Issues Tracker | C32: 2 | D32: 1 | E32: 3 | F32: 0.33333333 | G32: ↔️ | M32: 0 | N32: 0 | O32: 2 | P32: 0 | S32: rebecca-cichy | T32: 6 | V32: 1 | W32: 1 | X32: 2 | Y32: 2
A33: cloudwarriors-ai/automation-station | B33: Automation Station | C33: 2 | D33: 18 | E33: 20 | F33: 0.9 | G33: ↔️ | M33: 0 | N33: 0 | O33: 2 | P33: 0 | S33: DsuarezCW | T33: 2 | AA33: 2
A34: cloudwarriors-ai/codename_wad | B34: Zoom Workbook | C34: 12 | D34: 58 | E34: 70 | F34: 0.82857143 | G34: ↔️ | M34: 5 | N34: 0 | O34: 7 | P34: 0
A35: cloudwarriors-ai/github_review_build_test | B35: GitHub Review Build | C35: 16 | D35: 0 | E35: 16 | F35: 0 | G35: ↔️ | M35: 0 | N35: 0 | O35: 3 | P35: 13
A36: cloudwarriors-ai/chadwick | B36: Chadwick | C36: 1 | D36: 0 | E36: 1 | F36: 0 | G36: ↔️ | M36: 0 | N36: 1 | O36: 0 | P36: 0 | S36: TOTALS | T36: 60 | U36: 17 | V36: 4 | W36: 3 | X36: 3 | Y36: 19 | Z36: 2 | AA36: 8 | AB36: 2 | AC36: 2 | AD36: 0 | AE36: 0 | AF36: 0 | AG36: 0
A37: cloudwarriors-ai/support | B37: Support | C37: 1 | D37: 0 | E37: 1 | F37: 0 | G37: ↔️ | M37: 0 | N37: 0 | O37: 0 | P37: 1
A40: Date: 3Dec25 @ 6 AM EST | S40: Date: 3Dec25 @ 6 AM EST
A41: Repository | B41: App Name | C41: Open | D41: Closed | E41: Total | F41: % Complete | G41: Change | M41: P1: Task | N41: P2:Bug | O41: P3: Features | P41: Not Specified | S41: Name | T41: Task Count | U41: Tes-BE | V41: Tes-FE | X41: Rap | Y41: RapFE | Z41: PSO | AA41: ZWar | AB41: GIT | AC41: AS | AD41: ZWor | AE41: Git RB | AF41: Chad | AG41: Supp | AH41: TesPl | AI41: Notes
A42: cloudwarriors-ai/Tesseract | B42: Tesseract - Backend | C42: 14 | D42: 66 | E42: 80 | F42: 0.825 | G42: ⬆️ | M42: 13 | N42: 1 | O42: 0 | P42: 0 | S42: Voipin | T42: 0
A43: cloudwarriors-ai/tesseract-frontend | B43: Tesseract - Frontend | C43: 4 | D43: 58 | E43: 62 | F43: 0.93548387 | G43: ↔️ | M43: 1 | N43: 2 | O43: 1 | P43: 0 | S43: Chaddacus | T43: 13 | X43: 1 | Y43: 10 | AC43: 2
A44: cloudwarriors-ai/rapture | B44: MACD - Rapture | C44: 2 | D44: 28 | E44: 30 | F44: 0.93333333 | G44: ↔️ | M44: 0 | N44: 1 | O44: 1 | P44: 0 | S44: trentcharlton | T44: 12 | U44: 4 | V44: 1 | Y44: 7
A45: cloudwarriors-ai/rapture-frontend | B45: MACD - PSCX Frontend | C45: 19 | D45: 86 | E45: 105 | F45: 0.81904762 | G45: ↔️ | M45: 5 | N45: 3 | O45: 11 | P45: 0 | S45: Jeffrey-Searcy | T45: 6 | U45: 6
A46: cloudwarriors-ai/PSO-Quoting-Tool | B46: PSO Tool | C46: 2 | D46: 16 | E46: 18 | F46: 0.88888889 | G46: ↔️ | M46: 2 | N46: 0 | O46: 0 | P46: 0 | S46: jvitato1 | T46: 3 | V46: 1 | AB46: 2
A47: cloudwarriors-ai/zoom_presales_django | B47: Zoom Warriors | C47: 11 | D47: 94 | E47: 105 | F47: 0.8952381 | G47: ⬆️ | M47: 3 | N47: 0 | O47: 8 | P47: 0 | S47: Matt-Keuning | T47: 19 | U47: 7 | V47: 1 | AA47: 11
A48: cloudwarriors-ai/github_issues_tracker | B48: GitHub Issues Tracker | C48: 2 | D48: 1 | E48: 3 | F48: 0.33333333 | G48: ↔️ | M48: 0 | N48: 0 | O48: 2 | P48: 0 | S48: campbellayers | T48: 2 | Z48: 2
A49: cloudwarriors-ai/automation-station | B49: Automation Station | C49: 2 | D49: 18 | E49: 20 | F49: 0.9 | G49: ↔️ | M49: 0 | N49: 0 | O49: 2 | P49: 0 | S49: rebecca-cichy | T49: 6 | V49: 1 | X49: 2 | Y49: 2 | AA49: 1
A50: cloudwarriors-ai/codename_wad | B50: Zoom Workbook | C50: 12 | D50: 58 | E50: 70 | F50: 0.82857143 | G50: ↔️ | M50: 5 | N50: 0 | O50: 7 | P50: 0 | S50: sophiahooley-CW | T50: 0
A51: cloudwarriors-ai/github_review_build_test | B51: GitHub Review Build | C51: 16 | D51: 0 | E51: 16 | F51: 0 | G51: ↔️ | M51: 0 | N51: 0 | O51: 0 | P51: 16 | S51: sara-ota-cw | T51: 0
A52: cloudwarriors-ai/chadwick | B52: Chadwick | C52: 1 | D52: 0 | E52: 1 | F52: 0 | G52: ↔️ | M52: 0 | N52: 0 | O52: 0 | P52: 1 | S52: DsuarezCW | T52: 5 | AA52: 5
A53: cloudwarriors-ai/support | B53: Support | C53: 1 | D53: 0 | E53: 1 | F53: 0 | G53: ↔️ | M53: 0 | N53: 0 | O53: 0 | P53: 1
A54: cloudwarriors-ai/tesseract-platform | B54: Tesseract Platform | C54: 1 | D54: 0 | E54: 1 | F54: 0 | G54: ↔️ | M54: 0 | N54: 0 | O54: 0 | P54: 0
S55: TOTALS | T55: 66 | U55: 17 | V55: 4 | X55: 3 | Y55: 19 | Z55: 2 | AA55: 17 | AB55: 2 | AC55: 2 | AD55: 0 | AE55: 0 | AF55: 0 | AG55: 0 | AH55: 0
A58: Date: 26Nov25 @ 7 AM EST | S58: Date: 26Nov25 @ 7 AM EST
A59: Repository | B59: App Name | C59: Open | D59: Closed | E59: Total | F59: % Complete | G59: Change | M59: P1: Task | N59: P2:Bug | O59: P3: Features | P59: Not Specified | S59: Name | T59: Task Count | U59: Tes-BE | V59: Tes-FE | X59: Rap | Y59: RapFE | Z59: PSO | AA59: ZWar | AB59: GIT | AC59: Notes
A60: cloudwarriors-ai/Tesseract | B60: Tesseract - Backend | C60: 14 | D60: 67 | E60: 81 | F60: 0.82716049 | G60: ⬇️ | M60: 13 | N60: 1 | O60: 0 | P60: 0 | S60: Voipin | T60: 0
A61: cloudwarriors-ai/tesseract-frontend | B61: Tesseract - Frontend | C61: 4 | D61: 58 | E61: 62 | F61: 0.93548387 | G61: ↔️ | M61: 1 | N61: 2 | O61: 1 | P61: 0 | S61: Chaddacus | T61: 11 | X61: 1 | Y61: 10
A62: cloudwarriors-ai/rapture | B62: MACD - Rapture | C62: 2 | D62: 28 | E62: 30 | F62: 0.93333333 | G62: ↔️ | M62: 0 | N62: 1 | O62: 1 | P62: 0 | S62: trentcharlton | T62: 10 | U62: 4 | V62: 1 | Y62: 5
A63: cloudwarriors-ai/rapture-frontend | B63: MACD - PSCX Frontend | C63: 19 | D63: 86 | E63: 105 | F63: 0.81904762 | G63: ↔️ | M63: 5 | N63: 3 | O63: 11 | P63: 0 | S63: Jeffrey-Searcy | T63: 6 | U63: 6
A64: cloudwarriors-ai/PSO-Quoting-Tool | B64: PSO Tool | C64: 2 | D64: 16 | E64: 18 | F64: 0.88888889 | G64: ⬇️ | M64: 2 | N64: 0 | O64: 0 | P64: 0 | S64: jvitato1 | T64: 3 | V64: 1 | AB64: 2
A65: cloudwarriors-ai/zoom_presales_django | B65: Zoom Warriors | C65: 10 | D65: 94 | E65: 104 | F65: 0.90384615 | G65: ⬇️ | M65: 2 | N65: 0 | O65: 8 | P65: 0 | S65: Matt-Keuning | T65: 18 | U65: 7 | V65: 1 | AA65: 10
A66: cloudwarriors-ai/github_issues_tracker | B66: GitHub Issues Tracker | C66: 2 | D66: 1 | E66: 3 | F66: 0.33333333 | G66: ⬆️ | M66: 0 | N66: 0 | O66: 2 | P66: 0 | S66: campbellayers | T66: 2 | Z66: 2
S67: rebecca-cichy | T67: 5 | V67: 1 | X67: 2 | Y67: 2
S68: sophiahooley-CW | T68: 0
S69: sara-ota-cw | T69: 2 | Y69: 2
S70: DsuarezCW | T70: 4 | AA70: 4
S71: TOTALS | T71: 61 | U71: 17 | V71: 4 | X71: 3 | Y71: 19 | Z71: 2 | AA71: 14
A74: Date: 19Nov25 @ 10 PM EST | S74: Date: 19Nov25 @ 10 PM EST
A75: Repository | B75: App Name | C75: Open | D75: Closed | E75: Total | F75: % Complete | G75: Change | M75: P1: Task | N75: P2:Bug | O75: P3: Features | P75: Not Specified | S75: Name | T75: Task Count | U75: Tes-BE | V75: Tes-FE | X75: Rap | Y75: RapFE | Z75: PSO | AA75: ZWar | AB75: GIT | AC75: Notes
A76: cloudwarriors-ai/Tesseract | B76: Tesseract - Backend | C76: 18 | D76: 62 | E76: 80 | F76: 0.775 | G76: ⬇️ | M76: 17 | N76: 1 | O76: 0 | P76: 0 | S76: Voipin | T76: 0
A77: cloudwarriors-ai/tesseract-frontend | B77: Tesseract - Frontend | C77: 4 | D77: 58 | E77: 62 | F77: 0.93548387 | G77: ⬇️ | M77: 1 | N77: 2 | O77: 1 | P77: 0 | S77: Chaddacus | T77: 15 | X77: 1 | Y77: 10 | Z77: 4
A78: cloudwarriors-ai/rapture | B78: MACD - Rapture | C78: 2 | D78: 28 | E78: 30 | F78: 0.93333333 | G78: ↔️ | M78: 0 | N78: 1 | O78: 1 | P78: 0 | S78: trentcharlton | T78: 14 | U78: 8 | V78: 1 | Y78: 5
A79: cloudwarriors-ai/rapture-frontend | B79: MACD - PSCX Frontend | C79: 19 | D79: 86 | E79: 105 | F79: 0.81904762 | G79: ↔️ | M79: 5 | N79: 3 | O79: 11 | P79: 0 | S79: Jeffrey-Searcy | T79: 10 | U79: 10
A80: cloudwarriors-ai/PSO-Quoting-Tool | B80: PSO Tool | C80: 12 | D80: 6 | E80: 18 | F80: 0.33333333 | G80: ↔️ | M80: 4 | N80: 6 | O80: 2 | P80: 0 | S80: jvitato1 | T80: 2 | V80: 1 | AB80: 1
A81: cloudwarriors-ai/zoom_presales_django | B81: Zoom Warriors | C81: 15 | D81: 87 | E81: 102 | F81: 0.85294118 | G81: ⬇️ | M81: 4 | N81: 4 | O81: 7 | P81: 0 | S81: Matt-Keuning | T81: 22 | U81: 7 | V81: 1 | AA81: 14
A82: cloudwarriors-ai/github_issues_tracker | B82: GitHub Issues Tracker | C82: 1 | D82: 0 | E82: 1 | F82: 0 | G82: ⬆️ | M82: 0 | N82: 1 | O82: 0 | P82: 0 | S82: campbellayers | T82: 15 | Z82: 12 | AA82: 3
C83: 0 | D83: 0 | E83: 0 | F83: #DIV/0! | M83: 0 | N83: 0 | O83: 0 | P83: 0 | S83: rebecca-cichy | T83: 9 | V83: 1 | X83: 2 | Y83: 2 | AA83: 4
S84: sophiahooley-CW | T84: 1 | AA84: 1
S85: sara-ota-cw | T85: 2 | Y85: 2
S86: DsuarezCW | T86: 2 | AA86: 2
S87: TOTALS | T87: 92 | U87: 25 | V87: 4 | X87: 3 | Y87: 19 | Z87: 16 | AA87: 24
A90: Date: 15Oct25 @ 7 AM EST | S90: Date: 15Oct25 @ 7 AM EST
A91: Repository | B91: App Name | C91: Open | D91: Closed | E91: Total | F91: % Complete | G91: Change | M91: P1: Task | N91: P2:Bug | O91: P3: Features | P91: Not Specified | S91: Name | T91: Task Count | U91: Tes-BE | V91: Tes-FE | X91: Rap | Y91: RapFE | Z91: PSO | AA91: ZWar | AC91: Notes
A92: cloudwarriors-ai/Tesseract | B92: Tesseract - Backend | C92: 35 | D92: 44 | E92: 79 | F92: 0.55696203 | G92: ⬇️ | M92: 30 | N92: 0 | O92: 4 | P92: 1 | S92: Voipin | T92: 2 | U92: 2
A93: cloudwarriors-ai/tesseract-frontend | B93: Tesseract - Frontend | C93: 5 | D93: 56 | E93: 61 | F93: 0.91803279 | G93: ⬆️ | M93: 2 | N93: 2 | O93: 1 | P93: 0 | S93: Chaddacus | T93: 17 | U93: 2 | X93: 1 | Y93: 10 | Z93: 4
A94: cloudwarriors-ai/rapture | B94: MACD - Rapture | C94: 2 | D94: 28 | E94: 30 | F94: 0.93333333 | G94: ↔️ | M94: 0 | N94: 1 | O94: 1 | P94: 0 | S94: trentcharlton | T94: 15 | U94: 12 | Y94: 3
A95: cloudwarriors-ai/rapture-frontend | B95: MACD - PSCX Frontend | C95: 19 | D95: 86 | E95: 105 | F95: 0.81904762 | G95: ↔️ | M95: 5 | N95: 3 | O95: 11 | P95: 0 | S95: Jeffrey-Searcy | T95: 20 | U95: 20
A96: cloudwarriors-ai/PSO-Quoting-Tool | B96: PSO Tool | C96: 12 | D96: 6 | E96: 18 | F96: 0.33333333 | G96: ↔️ | M96: 4 | N96: 6 | O96: 2 | P96: 0 | S96: jvitato1 | T96: 3 | U96: 2 | V96: 1
A97: cloudwarriors-ai/zoom_presales_django | B97: Zoom Warriors | C97: 21 | D97: 66 | E97: 87 | F97: 0.75862069 | G97: ⬇️ | M97: 1 | N97: 6 | O97: 14 | P97: 0 | S97: adamarnold-cpu | T97: 0
C98: 0 | D98: 0 | E98: 0 | F98: #DIV/0! | M98: 0 | N98: 0 | O98: 0 | P98: 0 | S98: Matt-Keuning | T98: 24 | U98: 10 | V98: 3 | AA98: 11
C99: 0 | D99: 0 | E99: 0 | F99: #DIV/0! | M99: 0 | N99: 0 | O99: 0 | P99: 0 | S99: campbellayers | T99: 18 | Z99: 12 | AA99: 6
S100: rebecca-cichy | T100: 9 | U100: 3 | V100: 1 | X100: 2 | Y100: 2 | AA100: 1
S101: sophiahooley-CW | T101: 8 | AA101: 8
S102: sara-ota-cw | T102: 3 | Y102: 2 | AA102: 1
S103: TOTALS | T103: 119 | U103: 51 | V103: 5 | X103: 3 | Y103: 17 | Z103: 16 | AA103: 27
A106: Date: 24Sep25 @ 7 AM EST | S106: Date: 24Sep25 @ 7 AM EST
A107: Repository | B107: App Name | C107: Open | D107: Closed | E107: Total | F107: % Complete | G107: Change | M107: P1: Task | N107: P2:Bug | O107: P3: Features | P107: Not Specified | S107: Name | T107: Task Count | U107: Tes-BE | V107: Tes-FE | X107: Rap | Y107: RapFE | Z107: PSO | AA107: ZWar | AC107: Notes
A108: cloudwarriors-ai/Tesseract | B108: Tesseract - Backend | C108: 57 | D108: 20 | E108: 77 | F108: 0.25974026 | G108: ⬆️ | M108: 52 | N108: 1 | O108: 4 | P108: 0 | S108: Voipin | T108: 2 | U108: 2
A109: cloudwarriors-ai/tesseract-frontend | B109: Tesseract - Frontend | C109: 4 | D109: 48 | E109: 52 | F109: 0.92307692 | G109: ⬆️ | M109: 2 | N109: 1 | O109: 1 | P109: 0 | S109: Chaddacus | T109: 17 | U109: 2 | X109: 1 | Y109: 10 | Z109: 4
A110: cloudwarriors-ai/rapture | B110: MACD - Rapture | C110: 2 | D110: 28 | E110: 30 | F110: 0.93333333 | G110: ↔️ | M110: 0 | N110: 1 | O110: 1 | P110: 0 | S110: trentcharlton | T110: 11 | U110: 7 | Y110: 3
A111: cloudwarriors-ai/rapture-frontend | B111: MACD - PSCX Frontend | C111: 19 | D111: 85 | E111: 104 | F111: 0.81730769 | G111: ⬇️ | M111: 5 | N111: 3 | O111: 11 | P111: 0 | S111: Jeffrey-Searcy | T111: 29 | U111: 29
A112: cloudwarriors-ai/PSO-Quoting-Tool | B112: PSO Tool | C112: 12 | D112: 6 | E112: 18 | F112: 0.33333333 | G112: ↔️ | M112: 4 | N112: 6 | O112: 2 | P112: 0 | S112: jvitato1 | T112: 3 | U112: 2 | V112: 1
A113: cloudwarriors-ai/zoom_presales_django | B113: Zoom Warriors | C113: 24 | D113: 57 | E113: 81 | F113: 0.7037037 | G113: ⬇️ | M113: 3 | N113: 8 | O113: 13 | P113: 0 | S113: Waterboy-TH | T113: 7 | AA113: 7
C114: 0 | D114: 0 | E114: 0 | F114: #DIV/0! | M114: 0 | N114: 0 | O114: 0 | P114: 0 | S114: adamarnold-cpu | T114: 0
C115: 0 | D115: 0 | E115: 0 | F115: #DIV/0! | M115: 0 | N115: 0 | O115: 0 | P115: 0 | S115: Matt-Keuning | T115: 35 | U115: 19 | V115: 3 | AA115: 13
...

Sheet All Issues
A1: Repository | B1: System | C1: Issue Number | D1: Title | E1: State | F1: Created At | G1: Created At | H1: Created By | I1: Last Updated At | J1: Last Updated At | K1: Closed At | L1: Closed At | M1: Type | N1: Labels | O1: Assignees | P1: Comments Count | Q1: URL | R1: Priority | S1: Skill | T1: Status
A2: cloudwarriors-ai/cw-automation-station | B2: CW Automation Station | C2: 26 | D2: Feature Request - new V1 Common Area user setting modifications | E2: closed | F2: 2024-04-19T19:37:01Z | G2: =IF(I2="", "", TEXT(DATEVALUE(LEFT(F2, 10)), "dd-mmm-yyyy")) -> 19-Apr-2024 | H2: jondejonghcw | I2: 2025-06-12T15:34:16Z | J2: =IF(I2="", "", TEXT(DATEVALUE(LEFT(I2, 10)), "dd-mmm-yyyy")) -> 12-Jun-2025 | K2: 2025-06-12T15:34:16Z | L2: =IF(K2="", "", TEXT(DATEVALUE(LEFT(K2, 10)), "dd-mmm-yyyy")) -> 12-Jun-2025 | M2: Not Specified | N2: None | P2: 1 | Q2: https://github.com/cloudwarriors-ai/cw-automation-station/issues/26 | R2: =IFERROR(__xludf.DUMMYFUNCTION("IF(REGEXMATCH(N2, ""PRIORITY: Low""), ""Low"", IF(REGEXMATCH(N2, ""PRIORITY: Medium""), ""Medium"", IF(REGEXMATCH(N2, ""PRIORITY: High""), ""High"", """"))) "),"") | S2: =IFERROR(__xludf.DUMMYFUNCTION("IF(REGEXMATCH(N2, ""SKILL: Low""), ""Low"", IF(REGEXMATCH(N2, ""SKILL: Medium""), ""Medium"", IF(REGEXMATCH(N2, ""SKILL: High""), ""High"", """")))"),"") | T2: =IFERROR(__xludf.DUMMYFUNCTION("IF(REGEXMATCH(N2, ""STATUS: Dev Complete - Awaiting QA""), ""Dev Complete - Awaiting QA"", IF(REGEXMATCH(N2, ""STATUS: Follow-Up Required""), ""Follow-Up Required"", IF(REGEXMATCH(N2, ""STATUS: In Progress""), ""In Progress"", IF(REGEXMATCH(N2, ""STATUS: "&"In QA""), ""In QA"", IF(REGEXMATCH(N2, ""STATUS: Needs Customer Feedback""), ""Needs Customer Feedback"", IF(REGEXMATCH(N2, ""STATUS: QA Passed - Awaiting Release""), ""QA Passed - Awaiting Release"", IF(REGEXMATCH(N2, ""STATUS: Release to Prod""), ""Rele"&"ase to Prod"", """")))))))"),"")
A3: cloudwarriors-ai/cw-automation-station | B3: CW Automation Station | C3: 25 | D3: Feature Request - Enhance v1 Call Queue Overflow to include other destinations | E3: closed | F3: 2024-04-19T19:34:00Z | G3: =IF(I3="", "", TEXT(DATEVALUE(LEFT(F3, 10)), "dd-mmm-yyyy")) -> 19-Apr-2024 | H3: jondejonghcw | I3: 2025-06-12T15:34:24Z | J3: =IF(I3="", "", TEXT(DATEVALUE(LEFT(I3, 10)), "dd-mmm-yyyy")) -> 12-Jun-2025 | K3: 2025-06-12T15:34:24Z | L3: =IF(K3="", "", TEXT(DATEVALUE(LEFT(K3, 10)), "dd-mmm-yyyy")) -> 12-Jun-2025 | M3: Not Specified | N3: None | P3: 1 | Q3: https://github.com/cloudwarriors-ai/cw-automation-station/issues/25 | R3: =IFERROR(__xludf.DUMMYFUNCTION("IF(REGEXMATCH(N3, ""PRIORITY: Low""), ""Low"", IF(REGEXMATCH(N3, ""PRIORITY: Medium""), ""Medium"", IF(REGEXMATCH(N3, ""PRIORITY: High""), ""High"", """"))) "),"") | S3: =IFERROR(__xludf.DUMMYFUNCTION("IF(REGEXMATCH(N3, ""SKILL: Low""), ""Low"", IF(REGEXMATCH(N3, ""SKILL: Medium""), ""Medium"", IF(REGEXMATCH(N3, ""SKILL: High""), ""High"", """")))"),"") | T3: =IFERROR(__xludf.DUMMYFUNCTION("IF(REGEXMATCH(N3, ""STATUS: Dev Complete - Awaiting QA""), ""Dev Complete - Awaiting QA"", IF(REGEXMATCH(N3, ""STATUS: Follow-Up Required""), ""Follow-Up Required"", IF(REGEXMATCH(N3, ""STATUS: In Progress""), ""In Progress"", IF(REGEXMATCH(N3, ""STATUS: "&"In QA""), ""In QA"", IF(REGEXMATCH(N3, ""STATUS: Needs Customer Feedback""), ""Needs Customer Feedback"", IF(REGEXMATCH(N3, ""STATUS: QA Passed - Awaiting Release""), ""QA Passed - Awaiting Release"", IF(REGEXMATCH(N3, ""STATUS: Release to Prod""), ""Rele"&"ase to Prod"", """")))))))"),"")
A4: cloudwarriors-ai/cw-automation-station | B4: CW Automation Station | C4: 24 | D4: Feature Request - Add Description Field in CSV files | E4: closed | F4: 2024-04-19T19:31:25Z | G4: =IF(I4="", "", TEXT(DATEVALUE(LEFT(F4, 10)), "dd-mmm-yyyy")) -> 19-Apr-2024 | H4: jondejonghcw | I4: 2025-06-12T15:34:30Z | J4: =IF(I4="", "", TEXT(DATEVALUE(LEFT(I4, 10)), "dd-mmm-yyyy")) -> 12-Jun-2025 | K4: 2025-06-12T15:34:30Z | L4: =IF(K4="", "", TEXT(DATEVALUE(LEFT(K4, 10)), "dd-mmm-yyyy")) -> 12-Jun-2025 | M4: Not Specified | N4: None | P4: 1 | Q4: https://github.com/cloudwarriors-ai/cw-automation-station/issues/24 | R4: =IFERROR(__xludf.DUMMYFUNCTION("IF(REGEXMATCH(N4, ""PRIORITY: Low""), ""Low"", IF(REGEXMATCH(N4, ""PRIORITY: Medium""), ""Medium"", IF(REGEXMATCH(N4, ""PRIORITY: High""), ""High"", """"))) "),"") | S4: =IFERROR(__xludf.DUMMYFUNCTION("IF(REGEXMATCH(N4, ""SKILL: Low""), ""Low"", IF(REGEXMATCH(N4, ""SKILL: Medium""), ""Medium"", IF(REGEXMATCH(N4, ""SKILL: High""), ""High"", """")))"),"") | T4: =IFERROR(__xludf.DUMMYFUNCTION("IF(REGEXMATCH(N4, ""STATUS: Dev Complete - Awaiting QA""), ""Dev Complete - Awaiting QA"", IF(REGEXMATCH(N4, ""STATUS: Follow-Up Required""), ""Follow-Up Required"", IF(REGEXMATCH(N4, ""STATUS: In Progress""), ""In Progress"", IF(REGEXMATCH(N4, ""STATUS: "&"In QA""), ""In QA"", IF(REGEXMATCH(N4, ""STATUS: Needs Customer Feedback""), ""Needs Customer Feedback"", IF(REGEXMATCH(N4, ""STATUS: QA Passed - Awaiting Release""), ""QA Passed - Awaiting Release"", IF(REGEXMATCH(N4, ""STATUS: Release to Prod""), ""Rele"&"ase to Prod"", """")))))))"),"")
A5: cloudwarriors-ai/cw-automation-station | B5: CW Automation Station | C5: 15 | D5: Feature Request: Test Zoom generated SDK for Contact Center | E5: closed | F5: 2024-02-12T17:13:38Z | G5: =IF(I5="", "", TEXT(DATEVALUE(LEFT(F5, 10)), "dd-mmm-yyyy")) -> 12-Feb-2024 | H5: CkirkCW | I5: 2025-06-12T15:35:05Z | J5: =IF(I5="", "", TEXT(DATEVALUE(LEFT(I5, 10)), "dd-mmm-yyyy")) -> 12-Jun-2025 | K5: 2025-06-12T15:35:05Z | L5: =IF(K5="", "", TEXT(DATEVALUE(LEFT(K5, 10)), "dd-mmm-yyyy")) -> 12-Jun-2025 | M5: Not Specified | N5: None | P5: 1 | Q5: https://github.com/cloudwarriors-ai/cw-automation-station/issues/15 | R5: =IFERROR(__xludf.DUMMYFUNCTION("IF(REGEXMATCH(N5, ""PRIORITY: Low""), ""Low"", IF(REGEXMATCH(N5, ""PRIORITY: Medium""), ""Medium"", IF(REGEXMATCH(N5, ""PRIORITY: High""), ""High"", """"))) "),"") | S5: =IFERROR(__xludf.DUMMYFUNCTION("IF(REGEXMATCH(N5, ""SKILL: Low""), ""Low"", IF(REGEXMATCH(N5, ""SKILL: Medium""), ""Medium"", IF(REGEXMATCH(N5, ""SKILL: High""), ""High"", """")))"),"") | T5: =IFERROR(__xludf.DUMMYFUNCTION("IF(REGEXMATCH(N5, ""STATUS: Dev Complete - Awaiting QA""), ""Dev Complete - Awaiting QA"", IF(REGEXMATCH(N5, ""STATUS: Follow-Up Required""), ""Follow-Up Required"", IF(REGEXMATCH(N5, ""STATUS: In Progress""), ""In Progress"", IF(REGEXMATCH(N5, ""STATUS: "&"In QA""), ""In QA"", IF(REGEXMATCH(N5, ""STATUS: Needs Customer Feedback""), ""Needs Customer Feedback"", IF(REGEXMATCH(N5, ""STATUS: QA Passed - Awaiting Release""), ""QA Passed - Awaiting Release"", IF(REGEXMATCH(N5, ""STATUS: Release to Prod""), ""Rele"&"ase to Prod"", """")))))))"),"")
A6: cloudwarriors-ai/cw-automation-station | B6: CW Automation Station | C6: 11 | D6: Login Redirect Issue | E6: closed | F6: 2024-01-31T14:54:44Z | G6: =IF(I6="", "", TEXT(DATEVALUE(LEFT(F6, 10)), "dd-mmm-yyyy")) -> 31-Jan-2024 | H6: CkirkCW | I6: 2024-02-12T21:29:16Z | J6: =IF(I6="", "", TEXT(DATEVALUE(LEFT(I6, 10)), "dd-mmm-yyyy")) -> 12-Feb-2024 | K6: 2024-02-12T21:29:16Z | L6: =IF(K6="", "", TEXT(DATEVALUE(LEFT(K6, 10)), "dd-mmm-yyyy")) -> 12-Feb-2024 | M6: Not Specified | N6: None | P6: 1 | Q6: https://github.com/cloudwarriors-ai/cw-automation-station/issues/11 | R6: =IFERROR(__xludf.DUMMYFUNCTION("IF(REGEXMATCH(N6, ""PRIORITY: Low""), ""Low"", IF(REGEXMATCH(N6, ""PRIORITY: Medium""), ""Medium"", IF(REGEXMATCH(N6, ""PRIORITY: High""), ""High"", """"))) "),"") | S6: =IFERROR(__xludf.DUMMYFUNCTION("IF(REGEXMATCH(N6, ""SKILL: Low""), ""Low"", IF(REGEXMATCH(N6, ""SKILL: Medium""), ""Medium"", IF(REGEXMATCH(N6, ""SKILL: High""), ""High"", """")))"),"") | T6: =IFERROR(__xludf.DUMMYFUNCTION("IF(REGEXMATCH(N6, ""STATUS: Dev Complete - Awaiting QA""), ""Dev Complete - Awaiting QA"", IF(REGEXMATCH(N6, ""STATUS: Follow-Up Required""), ""Follow-Up Required"", IF(REGEXMATCH(N6, ""STATUS: In Progress""), ""In Progress"", IF(REGEXMATCH(N6, ""STATUS: "&"In QA""), ""In QA"", IF(REGEXMATCH(N6, ""STATUS: Needs Customer Feedback""), ""Needs Customer Feedback"", IF(REGEXMATCH(N6, ""STATUS: QA Passed - Awaiting Release""), ""QA Passed - Awaiting Release"", IF(REGEXMATCH(N6, ""STATUS: Release to Prod""), ""Rele"&"ase to Prod"", """")))))))"),"")
A7: cloudwarriors-ai/cw-automation-station | B7: CW Automation Station | C7: 8 | D7: Remote DB not adding new users to database at insert_into_database | E7: closed | F7: 2024-01-30T17:30:00Z | G7: =IF(I7="", "", TEXT(DATEVALUE(LEFT(F7, 10)), "dd-mmm-yyyy")) -> 30-Jan-2024 | H7: trentcharlton | I7: 2025-06-12T15:34:58Z | J7: =IF(I7="", "", TEXT(DATEVALUE(LEFT(I7, 10)), "dd-mmm-yyyy")) -> 12-Jun-2025 | K7: 2025-06-12T15:34:58Z | L7: =IF(K7="", "", TEXT(DATEVALUE(LEFT(K7, 10)), "dd-mmm-yyyy")) -> 12-Jun-2025 | M7: Not Specified | N7: None | P7: 1 | Q7: https://github.com/cloudwarriors-ai/cw-automation-station/issues/8 | R7: =IFERROR(__xludf.DUMMYFUNCTION("IF(REGEXMATCH(N7, ""PRIORITY: Low""), ""Low"", IF(REGEXMATCH(N7, ""PRIORITY: Medium""), ""Medium"", IF(REGEXMATCH(N7, ""PRIORITY: High""), ""High"", """"))) "),"") | S7: =IFERROR(__xludf.DUMMYFUNCTION("IF(REGEXMATCH(N7, ""SKILL: Low""), ""Low"", IF(REGEXMATCH(N7, ""SKILL: Medium""), ""Medium"", IF(REGEXMATCH(N7, ""SKILL: High""), ""High"", """")))"),"") | T7: =IFERROR(__xludf.DUMMYFUNCTION("IF(REGEXMATCH(N7, ""STATUS: Dev Complete - Awaiting QA""), ""Dev Complete - Awaiting QA"", IF(REGEXMATCH(N7, ""STATUS: Follow-Up Required""), ""Follow-Up Required"", IF(REGEXMATCH(N7, ""STATUS: In Progress""), ""In Progress"", IF(REGEXMATCH(N7, ""STATUS: "&"In QA""), ""In QA"", IF(REGEXMATCH(N7, ""STATUS: Needs Customer Feedback""), ""Needs Customer Feedback"", IF(REGEXMATCH(N7, ""STATUS: QA Passed - Awaiting Release""), ""QA Passed - Awaiting Release"", IF(REGEXMATCH(N7, ""STATUS: Release to Prod""), ""Rele"&"ase to Prod"", """")))))))"),"")
A8: cloudwarriors-ai/cw-automation-station | B8: CW Automation Station | C8: 7 | D8: Process_user_data possible infinite loop | E8: closed | F8: 2024-01-30T17:27:06Z | G8: =IF(I8="", "", TEXT(DATEVALUE(LEFT(F8, 10)), "dd-mmm-yyyy")) -> 30-Jan-2024 | H8: trentcharlton | I8: 2024-05-07T20:53:49Z | J8: =IF(I8="", "", TEXT(DATEVALUE(LEFT(I8, 10)), "dd-mmm-yyyy")) -> 07-May-2024 | K8: 2024-01-30T20:57:01Z | L8: =IF(K8="", "", TEXT(DATEVALUE(LEFT(K8, 10)), "dd-mmm-yyyy")) -> 30-Jan-2024 | M8: Not Specified | N8: None | P8: 0 | Q8: https://github.com/cloudwarriors-ai/cw-automation-station/issues/7 | R8: =IFERROR(__xludf.DUMMYFUNCTION("IF(REGEXMATCH(N8, ""PRIORITY: Low""), ""Low"", IF(REGEXMATCH(N8, ""PRIORITY: Medium""), ""Medium"", IF(REGEXMATCH(N8, ""PRIORITY: High""), ""High"", """"))) "),"") | S8: =IFERROR(__xludf.DUMMYFUNCTION("IF(REGEXMATCH(N8, ""SKILL: Low""), ""Low"", IF(REGEXMATCH(N8, ""SKILL: Medium""), ""Medium"", IF(REGEXMATCH(N8, ""SKILL: High""), ""High"", """")))"),"") | T8: =IFERROR(__xludf.DUMMYFUNCTION("IF(REGEXMATCH(N8, ""STATUS: Dev Complete - Awaiting QA""), ""Dev Complete - Awaiting QA"", IF(REGEXMATCH(N8, ""STATUS: Follow-Up Required""), ""Follow-Up Required"", IF(REGEXMATCH(N8, ""STATUS: In Progress""), ""In Progress"", IF(REGEXMATCH(N8, ""STATUS: "&"In QA""), ""In QA"", IF(REGEXMATCH(N8, ""STATUS: Needs Customer Feedback""), ""Needs Customer Feedback"", IF(REGEXMATCH(N8, ""STATUS: QA Passed - Awaiting Release""), ""QA Passed - Awaiting Release"", IF(REGEXMATCH(N8, ""STATUS: Release to Prod""), ""Rele"&"ase to Prod"", """")))))))"),"")
A9: cloudwarriors-ai/cw-automation-station | B9: CW Automation Station | C9: 5 | D9: phone call queue manager needs to get the manger ID to insert | E9: closed | F9: 2024-01-23T20:58:08Z | G9: =IF(I9="", "", TEXT(DATEVALUE(LEFT(F9, 10)), "dd-mmm-yyyy")) -> 23-Jan-2024 | H9: voipin | I9: 2025-06-12T15:34:52Z | J9: =IF(I9="", "", TEXT(DATEVALUE(LEFT(I9, 10)), "dd-mmm-yyyy")) -> 12-Jun-2025 | K9: 2025-06-12T15:34:52Z | L9: =IF(K9="", "", TEXT(DATEVALUE(LEFT(K9, 10)), "dd-mmm-yyyy")) -> 12-Jun-2025 | M9: Not Specified | N9: None | P9: 1 | Q9: https://github.com/cloudwarriors-ai/cw-automation-station/issues/5 | R9: =IFERROR(__xludf.DUMMYFUNCTION("IF(REGEXMATCH(N9, ""PRIORITY: Low""), ""Low"", IF(REGEXMATCH(N9, ""PRIORITY: Medium""), ""Medium"", IF(REGEXMATCH(N9, ""PRIORITY: High""), ""High"", """"))) "),"") | S9: =IFERROR(__xludf.DUMMYFUNCTION("IF(REGEXMATCH(N9, ""SKILL: Low""), ""Low"", IF(REGEXMATCH(N9, ""SKILL: Medium""), ""Medium"", IF(REGEXMATCH(N9, ""SKILL: High""), ""High"", """")))"),"") | T9: =IFERROR(__xludf.DUMMYFUNCTION("IF(REGEXMATCH(N9, ""STATUS: Dev Complete - Awaiting QA""), ""Dev Complete - Awaiting QA"", IF(REGEXMATCH(N9, ""STATUS: Follow-Up Required""), ""Follow-Up Required"", IF(REGEXMATCH(N9, ""STATUS: In Progress""), ""In Progress"", IF(REGEXMATCH(N9, ""STATUS: "&"In QA""), ""In QA"", IF(REGEXMATCH(N9, ""STATUS: Needs Customer Feedback""), ""Needs Customer Feedback"", IF(REGEXMATCH(N9, ""STATUS: QA Passed - Awaiting Release""), ""QA Passed - Awaiting Release"", IF(REGEXMATCH(N9, ""STATUS: Release to Prod""), ""Rele"&"ase to Prod"", """")))))))"),"")
A10: cloudwarriors-ai/cw-automation-station | B10: CW Automation Station | C10: 4 | D10: call_queue member doesn't work , missing data | E10: closed | F10: 2024-01-23T20:57:19Z | G10: =IF(I10="", "", TEXT(DATEVALUE(LEFT(F10, 10)), "dd-mmm-yyyy")) -> 23-Jan-2024 | H10: voipin | I10: 2025-06-12T15:34:46Z | J10: =IF(I10="", "", TEXT(DATEVALUE(LEFT(I10, 10)), "dd-mmm-yyyy")) -> 12-Jun-2025 | K10: 2025-06-12T15:34:46Z | L10: =IF(K10="", "", TEXT(DATEVALUE(LEFT(K10, 10)), "dd-mmm-yyyy")) -> 12-Jun-2025 | M10: Not Specified | N10: None | P10: 1 | Q10: https://github.com/cloudwarriors-ai/cw-automation-station/issues/4 | R10: =IFERROR(__xludf.DUMMYFUNCTION("IF(REGEXMATCH(N10, ""PRIORITY: Low""), ""Low"", IF(REGEXMATCH(N10, ""PRIORITY: Medium""), ""Medium"", IF(REGEXMATCH(N10, ""PRIORITY: High""), ""High"", """"))) "),"") | S10: =IFERROR(__xludf.DUMMYFUNCTION("IF(REGEXMATCH(N10, ""SKILL: Low""), ""Low"", IF(REGEXMATCH(N10, ""SKILL: Medium""), ""Medium"", IF(REGEXMATCH(N10, ""SKILL: High""), ""High"", """")))"),"") | T10: =IFERROR(__xludf.DUMMYFUNCTION("IF(REGEXMATCH(N10, ""STATUS: Dev Complete - Awaiting QA""), ""Dev Complete - Awaiting QA"", IF(REGEXMATCH(N10, ""STATUS: Follow-Up Required""), ""Follow-Up Required"", IF(REGEXMATCH(N10, ""STATUS: In Progress""), ""In Progress"", IF(REGEXMATCH(N10, ""STAT"&"US: In QA""), ""In QA"", IF(REGEXMATCH(N10, ""STATUS: Needs Customer Feedback""), ""Needs Customer Feedback"", IF(REGEXMATCH(N10, ""STATUS: QA Passed - Awaiting Release""), ""QA Passed - Awaiting Release"", IF(REGEXMATCH(N10, ""STATUS: Release to Prod""),"&" ""Release to Prod"", """")))))))"),"")
A11: cloudwarriors-ai/cw-automation-station | B11: CW Automation Station | C11: 3 | D11: Validation button/alerts | E11: closed | F11: 2024-01-22T20:00:06Z | G11: =IF(I11="", "", TEXT(DATEVALUE(LEFT(F11, 10)), "dd-mmm-yyyy")) -> 22-Jan-2024 | H11: CkirkCW | I11: 2025-06-12T15:34:39Z | J11: =IF(I11="", "", TEXT(DATEVALUE(LEFT(I11, 10)), "dd-mmm-yyyy")) -> 12-Jun-2025 | K11: 2025-06-12T15:34:39Z | L11: =IF(K11="", "", TEXT(DATEVALUE(LEFT(K11, 10)), "dd-mmm-yyyy")) -> 12-Jun-2025 | M11: Not Specified | N11: None | P11: 3 | Q11: https://github.com/cloudwarriors-ai/cw-automation-station/issues/3 | R11: =IFERROR(__xludf.DUMMYFUNCTION("IF(REGEXMATCH(N11, ""PRIORITY: Low""), ""Low"", IF(REGEXMATCH(N11, ""PRIORITY: Medium""), ""Medium"", IF(REGEXMATCH(N11, ""PRIORITY: High""), ""High"", """"))) "),"") | S11: =IFERROR(__xludf.DUMMYFUNCTION("IF(REGEXMATCH(N11, ""SKILL: Low""), ""Low"", IF(REGEXMATCH(N11, ""SKILL: Medium""), ""Medium"", IF(REGEXMATCH(N11, ""SKILL: High""), ""High"", """")))"),"") | T11: =IFERROR(__xludf.DUMMYFUNCTION("IF(REGEXMATCH(N11, ""STATUS: Dev Complete - Awaiting QA""), ""Dev Complete - Awaiting QA"", IF(REGEXMATCH(N11, ""STATUS: Follow-Up Required""), ""Follow-Up Required"", IF(REGEXMATCH(N11, ""STATUS: In Progress""), ""In Progress"", IF(REGEXMATCH(N11, ""STAT"&"US: In QA""), ""In QA"", IF(REGEXMATCH(N11, ""STATUS: Needs Customer Feedback""), ""Needs Customer Feedback"", IF(REGEXMATCH(N11, ""STATUS: QA Passed - Awaiting Release""), ""QA Passed - Awaiting Release"", IF(REGEXMATCH(N11, ""STATUS: Release to Prod""),"&" ""Release to Prod"", """")))))))"),"")
A12: cloudwarriors-ai/cw-automation-station | B12: CW Automation Station | C12: 2 | D12: User email redirection - update zoom OAUTH not redirecting to index | E12: closed | F12: 2024-01-19T22:15:23Z | G12: =IF(I12="", "", TEXT(DATEVALUE(LEFT(F12, 10)), "dd-mmm-yyyy")) -> 19-Jan-2024 | H12: CkirkCW | I12: 2024-01-19T22:22:10Z | J12: =IF(I12="", "", TEXT(DATEVALUE(LEFT(I12, 10)), "dd-mmm-yyyy")) -> 19-Jan-2024 | K12: 2024-01-19T22:22:10Z | L12: =IF(K12="", "", TEXT(DATEVALUE(LEFT(K12, 10)), "dd-mmm-yyyy")) -> 19-Jan-2024 | M12: Not Specified | N12: None | P12: 0 | Q12: https://github.com/cloudwarriors-ai/cw-automation-station/issues/2 | R12: =IFERROR(__xludf.DUMMYFUNCTION("IF(REGEXMATCH(N12, ""PRIORITY: Low""), ""Low"", IF(REGEXMATCH(N12, ""PRIORITY: Medium""), ""Medium"", IF(REGEXMATCH(N12, ""PRIORITY: High""), ""High"", """"))) "),"") | S12: =IFERROR(__xludf.DUMMYFUNCTION("IF(REGEXMATCH(N12, ""SKILL: Low""), ""Low"", IF(REGEXMATCH(N12, ""SKILL: Medium""), ""Medium"", IF(REGEXMATCH(N12, ""SKILL: High""), ""High"", """")))"),"") | T12: =IFERROR(__xludf.DUMMYFUNCTION("IF(REGEXMATCH(N12, ""STATUS: Dev Complete - Awaiting QA""), ""Dev Complete - Awaiting QA"", IF(REGEXMATCH(N12, ""STATUS: Follow-Up Required""), ""Follow-Up Required"", IF(REGEXMATCH(N12, ""STATUS: In Progress""), ""In Progress"", IF(REGEXMATCH(N12, ""STAT"&"US: In QA""), ""In QA"", IF(REGEXMATCH(N12, ""STATUS: Needs Customer Feedback""), ""Needs Customer Feedback"", IF(REGEXMATCH(N12, ""STATUS: QA Passed - Awaiting Release""), ""QA Passed - Awaiting Release"", IF(REGEXMATCH(N12, ""STATUS: Release to Prod""),"&" ""Release to Prod"", """")))))))"),"")
A13: cloudwarriors-ai/cw-automation-station | B13: CW Automation Station | C13: 1 | D13: Check for file before upload button is functional | E13: closed | F13: 2024-01-17T18:45:10Z | G13: =IF(I13="", "", TEXT(DATEVALUE(LEFT(F13, 10)), "dd-mmm-yyyy")) -> 17-Jan-2024 | H13: voipin | I13: 2024-01-30T20:57:16Z | J13: =IF(I13="", "", TEXT(DATEVALUE(LEFT(I13, 10)), "dd-mmm-yyyy")) -> 30-Jan-2024 | K13: 2024-01-30T20:57:15Z | L13: =IF(K13="", "", TEXT(DATEVALUE(LEFT(K13, 10)), "dd-mmm-yyyy")) -> 30-Jan-2024 | M13: Not Specified | N13: None | P13: 0 | Q13: https://github.com/cloudwarriors-ai/cw-automation-station/issues/1 | R13: =IFERROR(__xludf.DUMMYFUNCTION("IF(REGEXMATCH(N13, ""PRIORITY: Low""), ""Low"", IF(REGEXMATCH(N13, ""PRIORITY: Medium""), ""Medium"", IF(REGEXMATCH(N13, ""PRIORITY: High""), ""High"", """"))) "),"") | S13: =IFERROR(__xludf.DUMMYFUNCTION("IF(REGEXMATCH(N13, ""SKILL: Low""), ""Low"", IF(REGEXMATCH(N13, ""SKILL: Medium""), ""Medium"", IF(REGEXMATCH(N13, ""SKILL: High""), ""High"", """")))"),"") | T13: =IFERROR(__xludf.DUMMYFUNCTION("IF(REGEXMATCH(N13, ""STATUS: Dev Complete - Awaiting QA""), ""Dev Complete - Awaiting QA"", IF(REGEXMATCH(N13, ""STATUS: Follow-Up Required""), ""Follow-Up Required"", IF(REGEXMATCH(N13, ""STATUS: In Progress""), ""In Progress"", IF(REGEXMATCH(N13, ""STAT"&"US: In QA""), ""In QA"", IF(REGEXMATCH(N13, ""STATUS: Needs Customer Feedback""), ""Needs Customer Feedback"", IF(REGEXMATCH(N13, ""STATUS: QA Passed - Awaiting Release""), ""QA Passed - Awaiting Release"", IF(REGEXMATCH(N13, ""STATUS: Release to Prod""),"&" ""Release to Prod"", """")))))))"),"")
A14: cloudwarriors-ai/automation-station | B14: Automation Station | C14: 58 | D14: Zoom Phone - Need to have the option to add extra e911 zones | E14: closed | F14: 2025-04-08T18:50:21Z | G14: =IF(I14="", "", TEXT(DATEVALUE(LEFT(F14, 10)), "dd-mmm-yyyy")) -> 08-Apr-2025 | H14: rebecca-cichy | I14: 2025-07-11T21:07:52Z | J14: =IF(I14="", "", TEXT(DATEVALUE(LEFT(I14, 10)), "dd-mmm-yyyy")) -> 11-Jul-2025 | K14: 2025-04-08T18:55:46Z | L14: =IF(K14="", "", TEXT(DATEVALUE(LEFT(K14, 10)), "dd-mmm-yyyy")) -> 08-Apr-2025 | M14: Not Specified | N14: None | P14: 0 | Q14: https://github.com/cloudwarriors-ai/automation-station/issues/58 | R14: =IFERROR(__xludf.DUMMYFUNCTION("IF(REGEXMATCH(N14, ""PRIORITY: Low""), ""Low"", IF(REGEXMATCH(N14, ""PRIORITY: Medium""), ""Medium"", IF(REGEXMATCH(N14, ""PRIORITY: High""), ""High"", """"))) "),"") | S14: =IFERROR(__xludf.DUMMYFUNCTION("IF(REGEXMATCH(N14, ""SKILL: Low""), ""Low"", IF(REGEXMATCH(N14, ""SKILL: Medium""), ""Medium"", IF(REGEXMATCH(N14, ""SKILL: High""), ""High"", """")))"),"") | T14: =IFERROR(__xludf.DUMMYFUNCTION("IF(REGEXMATCH(N14, ""STATUS: Dev Complete - Awaiting QA""), ""Dev Complete - Awaiting QA"", IF(REGEXMATCH(N14, ""STATUS: Follow-Up Required""), ""Follow-Up Required"", IF(REGEXMATCH(N14, ""STATUS: In Progress""), ""In Progress"", IF(REGEXMATCH(N14, ""STAT"&"US: In QA""), ""In QA"", IF(REGEXMATCH(N14, ""STATUS: Needs Customer Feedback""), ""Needs Customer Feedback"", IF(REGEXMATCH(N14, ""STATUS: QA Passed - Awaiting Release""), ""QA Passed - Awaiting Release"", IF(REGEXMATCH(N14, ""STATUS: Release to Prod""),"&" ""Release to Prod"", """")))))))"),"")
A15: cloudwarriors-ai/automation-station | B15: Automation Station | C15: 55 | D15: SLA not being correctly pulled when job is created | E15: closed | F15: 2025-02-26T14:00:38Z | G15: =IF(I15="", "", TEXT(DATEVALUE(LEFT(F15, 10)), "dd-mmm-yyyy")) -> 26-Feb-2025 | H15: Chaddacus | I15: 2025-07-11T21:07:54Z | J15: =IF(I15="", "", TEXT(DATEVALUE(LEFT(I15, 10)), "dd-mmm-yyyy")) -> 11-Jul-2025 | K15: 2025-06-12T15:13:33Z | L15: =IF(K15="", "", TEXT(DATEVALUE(LEFT(K15, 10)), "dd-mmm-yyyy")) -> 12-Jun-2025 | M15: Not Specified | N15: None | P15: 1 | Q15: https://github.com/cloudwarriors-ai/automation-station/issues/55 | R15: =IFERROR(__xludf.DUMMYFUNCTION("IF(REGEXMATCH(N15, ""PRIORITY: Low""), ""Low"", IF(REGEXMATCH(N15, ""PRIORITY: Medium""), ""Medium"", IF(REGEXMATCH(N15, ""PRIORITY: High""), ""High"", """"))) "),"") | S15: =IFERROR(__xludf.DUMMYFUNCTION("IF(REGEXMATCH(N15, ""SKILL: Low""), ""Low"", IF(REGEXMATCH(N15, ""SKILL: Medium""), ""Medium"", IF(REGEXMATCH(N15, ""SKILL: High""), ""High"", """")))"),"") | T15: =IFERROR(__xludf.DUMMYFUNCTION("IF(REGEXMATCH(N15, ""STATUS: Dev Complete - Awaiting QA""), ""Dev Complete - Awaiting QA"", IF(REGEXMATCH(N15, ""STATUS: Follow-Up Required""), ""Follow-Up Required"", IF(REGEXMATCH(N15, ""STATUS: In Progress""), ""In Progress"", IF(REGEXMATCH(N15, ""STAT"&"US: In QA""), ""In QA"", IF(REGEXMATCH(N15, ""STATUS: Needs Customer Feedback""), ""Needs Customer Feedback"", IF(REGEXMATCH(N15, ""STATUS: QA Passed - Awaiting Release""), ""QA Passed - Awaiting Release"", IF(REGEXMATCH(N15, ""STATUS: Release to Prod""),"&" ""Release to Prod"", """")))))))"),"")
A16: cloudwarriors-ai/automation-station | B16: Automation Station | C16: 54 | D16: List jobs need to be exempt from SLA | E16: closed | F16: 2025-02-26T13:59:26Z | G16: =IF(I16="", "", TEXT(DATEVALUE(LEFT(F16, 10)), "dd-mmm-yyyy")) -> 26-Feb-2025 | H16: Chaddacus | I16: 2025-07-11T21:07:55Z | J16: =IF(I16="", "", TEXT(DATEVALUE(LEFT(I16, 10)), "dd-mmm-yyyy")) -> 11-Jul-2025 | K16: 2025-06-12T15:14:11Z | L16: =IF(K16="", "", TEXT(DATEVALUE(LEFT(K16, 10)), "dd-mmm-yyyy")) -> 12-Jun-2025 | M16: Not Specified | N16: None | P16: 1 | Q16: https://github.com/cloudwarriors-ai/automation-station/issues/54 | R16: =IFERROR(__xludf.DUMMYFUNCTION("IF(REGEXMATCH(N16, ""PRIORITY: Low""), ""Low"", IF(REGEXMATCH(N16, ""PRIORITY: Medium""), ""Medium"", IF(REGEXMATCH(N16, ""PRIORITY: High""), ""High"", """"))) "),"") | S16: =IFERROR(__xludf.DUMMYFUNCTION("IF(REGEXMATCH(N16, ""SKILL: Low""), ""Low"", IF(REGEXMATCH(N16, ""SKILL: Medium""), ""Medium"", IF(REGEXMATCH(N16, ""SKILL: High""), ""High"", """")))"),"") | T16: =IFERROR(__xludf.DUMMYFUNCTION("IF(REGEXMATCH(N16, ""STATUS: Dev Complete - Awaiting QA""), ""Dev Complete - Awaiting QA"", IF(REGEXMATCH(N16, ""STATUS: Follow-Up Required""), ""Follow-Up Required"", IF(REGEXMATCH(N16, ""STATUS: In Progress""), ""In Progress"", IF(REGEXMATCH(N16, ""STAT"&"US: In QA""), ""In QA"", IF(REGEXMATCH(N16, ""STATUS: Needs Customer Feedback""), ""Needs Customer Feedback"", IF(REGEXMATCH(N16, ""STATUS: QA Passed - Awaiting Release""), ""QA Passed - Awaiting Release"", IF(REGEXMATCH(N16, ""STATUS: Release to Prod""),"&" ""Release to Prod"", """")))))))"),"")
A17: cloudwarriors-ai/automation-station | B17: Automation Station | C17: 53 | D17: Jobs not properly moving between tables based on status | E17: closed | F17: 2025-02-26T13:58:07Z | G17: =IF(I17="", "", TEXT(DATEVALUE(LEFT(F17, 10)), "dd-mmm-yyyy")) -> 26-Feb-2025 | H17: Chaddacus | I17: 2025-07-11T21:07:55Z | J17: =IF(I17="", "", TEXT(DATEVALUE(LEFT(I17, 10)), "dd-mmm-yyyy")) -> 11-Jul-2025 | K17: 2025-06-12T15:19:19Z | L17: =IF(K17="", "", TEXT(DATEVALUE(LEFT(K17, 10)), "dd-mmm-yyyy")) -> 12-Jun-2025 | M17: Not Specified | N17: None | P17: 1 | Q17: https://github.com/cloudwarriors-ai/automation-station/issues/53 | R17: =IFERROR(__xludf.DUMMYFUNCTION("IF(REGEXMATCH(N17, ""PRIORITY: Low""), ""Low"", IF(REGEXMATCH(N17, ""PRIORITY: Medium""), ""Medium"", IF(REGEXMATCH(N17, ""PRIORITY: High""), ""High"", """"))) "),"") | S17: =IFERROR(__xludf.DUMMYFUNCTION("IF(REGEXMATCH(N17, ""SKILL: Low""), ""Low"", IF(REGEXMATCH(N17, ""SKILL: Medium""), ""Medium"", IF(REGEXMATCH(N17, ""SKILL: High""), ""High"", """")))"),"") | T17: =IFERROR(__xludf.DUMMYFUNCTION("IF(REGEXMATCH(N17, ""STATUS: Dev Complete - Awaiting QA""), ""Dev Complete - Awaiting QA"", IF(REGEXMATCH(N17, ""STATUS: Follow-Up Required""), ""Follow-Up Required"", IF(REGEXMATCH(N17, ""STATUS: In Progress""), ""In Progress"", IF(REGEXMATCH(N17, ""STAT"&"US: In QA""), ""In QA"", IF(REGEXMATCH(N17, ""STATUS: Needs Customer Feedback""), ""Needs Customer Feedback"", IF(REGEXMATCH(N17, ""STATUS: QA Passed - Awaiting Release""), ""QA Passed - Awaiting Release"", IF(REGEXMATCH(N17, ""STATUS: Release to Prod""),"&" ""Release to Prod"", """")))))))"),"")
A18: cloudwarriors-ai/automation-station | B18: Automation Station | C18: 52 | D18: Job Page - Rework/Touch Up | E18: open | F18: 2025-02-26T13:56:48Z | G18: =IF(I18="", "", TEXT(DATEVALUE(LEFT(F18, 10)), "dd-mmm-yyyy")) -> 26-Feb-2025 | H18: Chaddacus | I18: 2025-12-03T11:34:20Z | J18: =IF(I18="", "", TEXT(DATEVALUE(LEFT(I18, 10)), "dd-mmm-yyyy")) -> 03-Dec-2025 | L18: =IF(K18="", "", TEXT(DATEVALUE(LEFT(K18, 10)), "dd-mmm-yyyy")) | M18: Feature | N18: PRIORITY: Low, SKILL: Low, STATUS: In Progress | O18: Chaddacus | P18: 0 | Q18: https://github.com/cloudwarriors-ai/automation-station/issues/52 | R18: =IFERROR(__xludf.DUMMYFUNCTION("IF(REGEXMATCH(N18, ""PRIORITY: Low""), ""Low"", IF(REGEXMATCH(N18, ""PRIORITY: Medium""), ""Medium"", IF(REGEXMATCH(N18, ""PRIORITY: High""), ""High"", """"))) "),"Low") -> Low | S18: =IFERROR(__xludf.DUMMYFUNCTION("IF(REGEXMATCH(N18, ""SKILL: Low""), ""Low"", IF(REGEXMATCH(N18, ""SKILL: Medium""), ""Medium"", IF(REGEXMATCH(N18, ""SKILL: High""), ""High"", """")))"),"Low") -> Low | T18: =IFERROR(__xludf.DUMMYFUNCTION("IF(REGEXMATCH(N18, ""STATUS: Dev Complete - Awaiting QA""), ""Dev Complete - Awaiting QA"", IF(REGEXMATCH(N18, ""STATUS: Follow-Up Required""), ""Follow-Up Required"", IF(REGEXMATCH(N18, ""STATUS: In Progress""), ""In Progress"", IF(REGEXMATCH(N18, ""STAT"&"US: In QA""), ""In QA"", IF(REGEXMATCH(N18, ""STATUS: Needs Customer Feedback""), ""Needs Customer Feedback"", IF(REGEXMATCH(N18, ""STATUS: QA Passed - Awaiting Release""), ""QA Passed - Awaiting Release"", IF(REGEXMATCH(N18, ""STATUS: Release to Prod""),"&" ""Release to Prod"", """")))))))"),"In Progress") -> In Progress
A19: cloudwarriors-ai/automation-station | B19: Automation Station | C19: 38 | D19: Logging | E19: closed | F19: 2025-01-21T21:17:10Z | G19: =IF(I19="", "", TEXT(DATEVALUE(LEFT(F19, 10)), "dd-mmm-yyyy")) -> 21-Jan-2025 | H19: PittyG | I19: 2025-07-11T21:08:06Z | J19: =IF(I19="", "", TEXT(DATEVALUE(LEFT(I19, 10)), "dd-mmm-yyyy")) -> 11-Jul-2025 | K19: 2025-02-07T15:45:49Z | L19: =IF(K19="", "", TEXT(DATEVALUE(LEFT(K19, 10)), "dd-mmm-yyyy")) -> 07-Feb-2025 | M19: Not Specified | N19: None | P19: 0 | Q19: https://github.com/cloudwarriors-ai/automation-station/issues/38 | R19: =IFERROR(__xludf.DUMMYFUNCTION("IF(REGEXMATCH(N19, ""PRIORITY: Low""), ""Low"", IF(REGEXMATCH(N19, ""PRIORITY: Medium""), ""Medium"", IF(REGEXMATCH(N19, ""PRIORITY: High""), ""High"", """"))) "),"") | S19: =IFERROR(__xludf.DUMMYFUNCTION("IF(REGEXMATCH(N19, ""SKILL: Low""), ""Low"", IF(REGEXMATCH(N19, ""SKILL: Medium""), ""Medium"", IF(REGEXMATCH(N19, ""SKILL: High""), ""High"", """")))"),"") | T19: =IFERROR(__xludf.DUMMYFUNCTION("IF(REGEXMATCH(N19, ""STATUS: Dev Complete - Awaiting QA""), ""Dev Complete - Awaiting QA"", IF(REGEXMATCH(N19, ""STATUS: Follow-Up Required""), ""Follow-Up Required"", IF(REGEXMATCH(N19, ""STATUS: In Progress""), ""In Progress"", IF(REGEXMATCH(N19, ""STAT"&"US: In QA""), ""In QA"", IF(REGEXMATCH(N19, ""STATUS: Needs Customer Feedback""), ""Needs Customer Feedback"", IF(REGEXMATCH(N19, ""STATUS: QA Passed - Awaiting Release""), ""QA Passed - Awaiting Release"", IF(REGEXMATCH(N19, ""STATUS: Release to Prod""),"&" ""Release to Prod"", """")))))))"),"")
A20: cloudwarriors-ai/automation-station | B20: Automation Station | C20: 37 | D20: Add a send function after celery has completed a job that routes the results to the frontend | E20: closed | F20: 2025-01-21T16:37:37Z | G20: =IF(I20="", "", TEXT(DATEVALUE(LEFT(F20, 10)), "dd-mmm-yyyy")) -> 21-Jan-2025 | H20: Chaddacus | I20: 2025-07-11T21:08:07Z | J20: =IF(I20="", "", TEXT(DATEVALUE(LEFT(I20, 10)), "dd-mmm-yyyy")) -> 11-Jul-2025 | K20: 2025-02-07T15:45:49Z | L20: =IF(K20="", "", TEXT(DATEVALUE(LEFT(K20, 10)), "dd-mmm-yyyy")) -> 07-Feb-2025 | M20: Not Specified | N20: None | P20: 0 | Q20: https://github.com/cloudwarriors-ai/automation-station/issues/37 | R20: =IFERROR(__xludf.DUMMYFUNCTION("IF(REGEXMATCH(N20, ""PRIORITY: Low""), ""Low"", IF(REGEXMATCH(N20, ""PRIORITY: Medium""), ""Medium"", IF(REGEXMATCH(N20, ""PRIORITY: High""), ""High"", """"))) "),"") | S20: =IFERROR(__xludf.DUMMYFUNCTION("IF(REGEXMATCH(N20, ""SKILL: Low""), ""Low"", IF(REGEXMATCH(N20, ""SKILL: Medium""), ""Medium"", IF(REGEXMATCH(N20, ""SKILL: High""), ""High"", """")))"),"") | T20: =IFERROR(__xludf.DUMMYFUNCTION("IF(REGEXMATCH(N20, ""STATUS: Dev Complete - Awaiting QA""), ""Dev Complete - Awaiting QA"", IF(REGEXMATCH(N20, ""STATUS: Follow-Up Required""), ""Follow-Up Required"", IF(REGEXMATCH(N20, ""STATUS: In Progress""), ""In Progress"", IF(REGEXMATCH(N20, ""STAT"&"US: In QA""), ""In QA"", IF(REGEXMATCH(N20, ""STATUS: Needs Customer Feedback""), ""Needs Customer Feedback"", IF(REGEXMATCH(N20, ""STATUS: QA Passed - Awaiting Release""), ""QA Passed - Awaiting Release"", IF(REGEXMATCH(N20, ""STATUS: Release to Prod""),"&" ""Release to Prod"", """")))))))"),"")
A21: cloudwarriors-ai/automation-station | B21: Automation Station | C21: 36 | D21: Fix the CSRF Token Authentication to a True Token Authentication System | E21: open | F21: 2025-01-21T16:34:03Z | G21: =IF(I21="", "", TEXT(DATEVALUE(LEFT(F21, 10)), "dd-mmm-yyyy")) -> 21-Jan-2025 | H21: Chaddacus | I21: 2025-07-16T16:18:24Z | J21: =IF(I21="", "", TEXT(DATEVALUE(LEFT(I21, 10)), "dd-mmm-yyyy")) -> 16-Jul-2025 | L21: =IF(K21="", "", TEXT(DATEVALUE(LEFT(K21, 10)), "dd-mmm-yyyy")) | M21: Feature | N21: PRIORITY: Medium, SKILL: Medium, STATUS: In Progress | O21: Chaddacus | P21: 1 | Q21: https://github.com/cloudwarriors-ai/automation-station/issues/36 | R21: =IFERROR(__xludf.DUMMYFUNCTION("IF(REGEXMATCH(N21, ""PRIORITY: Low""), ""Low"", IF(REGEXMATCH(N21, ""PRIORITY: Medium""), ""Medium"", IF(REGEXMATCH(N21, ""PRIORITY: High""), ""High"", """"))) "),"Medium") -> Medium | S21: =IFERROR(__xludf.DUMMYFUNCTION("IF(REGEXMATCH(N21, ""SKILL: Low""), ""Low"", IF(REGEXMATCH(N21, ""SKILL: Medium""), ""Medium"", IF(REGEXMATCH(N21, ""SKILL: High""), ""High"", """")))"),"Medium") -> Medium | T21: =IFERROR(__xludf.DUMMYFUNCTION("IF(REGEXMATCH(N21, ""STATUS: Dev Complete - Awaiting QA""), ""Dev Complete - Awaiting QA"", IF(REGEXMATCH(N21, ""STATUS: Follow-Up Required""), ""Follow-Up Required"", IF(REGEXMATCH(N21, ""STATUS: In Progress""), ""In Progress"", IF(REGEXMATCH(N21, ""STAT"&"US: In QA""), ""In QA"", IF(REGEXMATCH(N21, ""STATUS: Needs Customer Feedback""), ""Needs Customer Feedback"", IF(REGEXMATCH(N21, ""STATUS: QA Passed - Awaiting Release""), ""QA Passed - Awaiting Release"", IF(REGEXMATCH(N21, ""STATUS: Release to Prod""),"&" ""Release to Prod"", """")))))))"),"In Progress") -> In Progress
A22: cloudwarriors-ai/zoom_presales_django | B22: ZoomWarriors v1 | C22: 432 | D22: [CAB] Data Cleanup Refactor - Comprehensive Reset Approach | E22: closed | F22: 2025-08-25T13:54:11Z | G22: =IF(I22="", "", TEXT(DATEVALUE(LEFT(F22, 10)), "dd-mmm-yyyy")) -> 25-Aug-2025 | H22: Matt-Keuning | I22: 2025-09-05T18:42:53Z | J22: =IF(I22="", "", TEXT(DATEVALUE(LEFT(I22, 10)), "dd-mmm-yyyy")) -> 05-Sep-2025 | K22: 2025-09-05T18:42:53Z | L22: =IF(K22="", "", TEXT(DATEVALUE(LEFT(K22, 10)), "dd-mmm-yyyy")) -> 05-Sep-2025 | M22: Not Specified | N22: None | P22: 1 | Q22: https://github.com/cloudwarriors-ai/zoom_presales_django/issues/432 | R22: =IFERROR(__xludf.DUMMYFUNCTION("IF(REGEXMATCH(N22, ""PRIORITY: Low""), ""Low"", IF(REGEXMATCH(N22, ""PRIORITY: Medium""), ""Medium"", IF(REGEXMATCH(N22, ""PRIORITY: High""), ""High"", """"))) "),"") | S22: =IFERROR(__xludf.DUMMYFUNCTION("IF(REGEXMATCH(N22, ""SKILL: Low""), ""Low"", IF(REGEXMATCH(N22, ""SKILL: Medium""), ""Medium"", IF(REGEXMATCH(N22, ""SKILL: High""), ""High"", """")))"),"") | T22: =IFERROR(__xludf.DUMMYFUNCTION("IF(REGEXMATCH(N22, ""STATUS: Dev Complete - Awaiting QA""), ""Dev Complete - Awaiting QA"", IF(REGEXMATCH(N22, ""STATUS: Follow-Up Required""), ""Follow-Up Required"", IF(REGEXMATCH(N22, ""STATUS: In Progress""), ""In Progress"", IF(REGEXMATCH(N22, ""STAT"&"US: In QA""), ""In QA"", IF(REGEXMATCH(N22, ""STATUS: Needs Customer Feedback""), ""Needs Customer Feedback"", IF(REGEXMATCH(N22, ""STATUS: QA Passed - Awaiting Release""), ""QA Passed - Awaiting Release"", IF(REGEXMATCH(N22, ""STATUS: Release to Prod""),"&" ""Release to Prod"", """")))))))"),"")
A23: cloudwarriors-ai/zoom_presales_django | B23: ZoomWarriors v1 | C23: 431 | D23: [CAB] UI Bundle Fix For CAB - Multiple UI Improvements | E23: closed | F23: 2025-08-22T18:49:09Z | G23: =IF(I23="", "", TEXT(DATEVALUE(LEFT(F23, 10)), "dd-mmm-yyyy")) -> 22-Aug-2025 | H23: Matt-Keuning | I23: 2025-09-05T18:42:39Z | J23: =IF(I23="", "", TEXT(DATEVALUE(LEFT(I23, 10)), "dd-mmm-yyyy")) -> 05-Sep-2025 | K23: 2025-09-05T18:42:39Z | L23: =IF(K23="", "", TEXT(DATEVALUE(LEFT(K23, 10)), "dd-mmm-yyyy")) -> 05-Sep-2025 | M23: Not Specified | N23: None | O23: voipin, Chaddacus, trentcharlton | P23: 1 | Q23: https://github.com/cloudwarriors-ai/zoom_presales_django/issues/431 | R23: =IFERROR(__xludf.DUMMYFUNCTION("IF(REGEXMATCH(N23, ""PRIORITY: Low""), ""Low"", IF(REGEXMATCH(N23, ""PRIORITY: Medium""), ""Medium"", IF(REGEXMATCH(N23, ""PRIORITY: High""), ""High"", """"))) "),"") | S23: =IFERROR(__xludf.DUMMYFUNCTION("IF(REGEXMATCH(N23, ""SKILL: Low""), ""Low"", IF(REGEXMATCH(N23, ""SKILL: Medium""), ""Medium"", IF(REGEXMATCH(N23, ""SKILL: High""), ""High"", """")))"),"") | T23: =IFERROR(__xludf.DUMMYFUNCTION("IF(REGEXMATCH(N23, ""STATUS: Dev Complete - Awaiting QA""), ""Dev Complete - Awaiting QA"", IF(REGEXMATCH(N23, ""STATUS: Follow-Up Required""), ""Follow-Up Required"", IF(REGEXMATCH(N23, ""STATUS: In Progress""), ""In Progress"", IF(REGEXMATCH(N23, ""STAT"&"US: In QA""), ""In QA"", IF(REGEXMATCH(N23, ""STATUS: Needs Customer Feedback""), ""Needs Customer Feedback"", IF(REGEXMATCH(N23, ""STATUS: QA Passed - Awaiting Release""), ""QA Passed - Awaiting Release"", IF(REGEXMATCH(N23, ""STATUS: Release to Prod""),"&" ""Release to Prod"", """")))))))"),"")
A24: cloudwarriors-ai/zoom_presales_django | B24: ZoomWarriors v1 | C24: 427 | D24: [CAB] zoom_presales_django – Form logic + data-cleanup fixes | E24: closed | F24: 2025-08-17T18:41:57Z | G24: =IF(I24="", "", TEXT(DATEVALUE(LEFT(F24, 10)), "dd-mmm-yyyy")) -> 17-Aug-2025 | H24: Jeffrey-Searcy | I24: 2025-09-19T03:29:21Z | J24: =IF(I24="", "", TEXT(DATEVALUE(LEFT(I24, 10)), "dd-mmm-yyyy")) -> 19-Sep-2025 | K24: 2025-09-05T18:42:30Z | L24: =IF(K24="", "", TEXT(DATEVALUE(LEFT(K24, 10)), "dd-mmm-yyyy")) -> 05-Sep-2025 | M24: Not Specified | N24: None | O24: voipin, Chaddacus, trentcharlton | P24: 1 | Q24: https://github.com/cloudwarriors-ai/zoom_presales_django/issues/427 | R24: =IFERROR(__xludf.DUMMYFUNCTION("IF(REGEXMATCH(N24, ""PRIORITY: Low""), ""Low"", IF(REGEXMATCH(N24, ""PRIORITY: Medium""), ""Medium"", IF(REGEXMATCH(N24, ""PRIORITY: High""), ""High"", """"))) "),"") | S24: =IFERROR(__xludf.DUMMYFUNCTION("IF(REGEXMATCH(N24, ""SKILL: Low""), ""Low"", IF(REGEXMATCH(N24, ""SKILL: Medium""), ""Medium"", IF(REGEXMATCH(N24, ""SKILL: High""), ""High"", """")))"),"") | T24: =IFERROR(__xludf.DUMMYFUNCTION("IF(REGEXMATCH(N24, ""STATUS: Dev Complete - Awaiting QA""), ""Dev Complete - Awaiting QA"", IF(REGEXMATCH(N24, ""STATUS: Follow-Up Required""), ""Follow-Up Required"", IF(REGEXMATCH(N24, ""STATUS: In Progress""), ""In Progress"", IF(REGEXMATCH(N24, ""STAT"&"US: In QA""), ""In QA"", IF(REGEXMATCH(N24, ""STATUS: Needs Customer Feedback""), ""Needs Customer Feedback"", IF(REGEXMATCH(N24, ""STATUS: QA Passed - Awaiting Release""), ""QA Passed - Awaiting Release"", IF(REGEXMATCH(N24, ""STATUS: Release to Prod""),"&" ""Release to Prod"", """")))))))"),"")
A25: cloudwarriors-ai/zoom_presales_django | B25: ZoomWarriors v1 | C25: 424 | D25: Zoom Phone Paging - Page Separation Appearance | E25: closed | F25: 2025-08-13T18:05:04Z | G25: =IF(I25="", "", TEXT(DATEVALUE(LEFT(F25, 10)), "dd-mmm-yyyy")) -> 13-Aug-2025 | H25: rebecca-cichy | I25: 2025-09-05T18:42:06Z | J25: =IF(I25="", "", TEXT(DATEVALUE(LEFT(I25, 10)), "dd-mmm-yyyy")) -> 05-Sep-2025 | K25: 2025-09-05T18:42:06Z | L25: =IF(K25="", "", TEXT(DATEVALUE(LEFT(K25, 10)), "dd-mmm-yyyy")) -> 05-Sep-2025 | M25: Bug | N25: PRIORITY: Low, SKILL: Low, STATUS: QA Passed - Awaiting Release | O25: Matt-Keuning | P25: 3 | Q25: https://github.com/cloudwarriors-ai/zoom_presales_django/issues/424 | R25: =IFERROR(__xludf.DUMMYFUNCTION("IF(REGEXMATCH(N25, ""PRIORITY: Low""), ""Low"", IF(REGEXMATCH(N25, ""PRIORITY: Medium""), ""Medium"", IF(REGEXMATCH(N25, ""PRIORITY: High""), ""High"", """"))) "),"Low") -> Low | S25: =IFERROR(__xludf.DUMMYFUNCTION("IF(REGEXMATCH(N25, ""SKILL: Low""), ""Low"", IF(REGEXMATCH(N25, ""SKILL: Medium""), ""Medium"", IF(REGEXMATCH(N25, ""SKILL: High""), ""High"", """")))"),"Low") -> Low | T25: =IFERROR(__xludf.DUMMYFUNCTION("IF(REGEXMATCH(N25, ""STATUS: Dev Complete - Awaiting QA""), ""Dev Complete - Awaiting QA"", IF(REGEXMATCH(N25, ""STATUS: Follow-Up Required""), ""Follow-Up Required"", IF(REGEXMATCH(N25, ""STATUS: In Progress""), ""In Progress"", IF(REGEXMATCH(N25, ""STAT"&"US: In QA""), ""In QA"", IF(REGEXMATCH(N25, ""STATUS: Needs Customer Feedback""), ""Needs Customer Feedback"", IF(REGEXMATCH(N25, ""STATUS: QA Passed - Awaiting Release""), ""QA Passed - Awaiting Release"", IF(REGEXMATCH(N25, ""STATUS: Release to Prod""),"&" ""Release to Prod"", """")))))))"),"QA Passed - Awaiting Release") -> QA Passed - Awaiting Release
A26: cloudwarriors-ai/zoom_presales_django | B26: ZoomWarriors v1 | C26: 422 | D26: Zoom Phone Harware Page - Remove Baseline Slider | E26: closed | F26: 2025-08-06T19:08:37Z | G26: =IF(I26="", "", TEXT(DATEVALUE(LEFT(F26, 10)), "dd-mmm-yyyy")) -> 06-Aug-2025 | H26: rebecca-cichy | I26: 2025-09-05T18:41:59Z | J26: =IF(I26="", "", TEXT(DATEVALUE(LEFT(I26, 10)), "dd-mmm-yyyy")) -> 05-Sep-2025 | K26: 2025-09-05T18:41:59Z | L26: =IF(K26="", "", TEXT(DATEVALUE(LEFT(K26, 10)), "dd-mmm-yyyy")) -> 05-Sep-2025 | M26: Task | N26: PRIORITY: Low, SKILL: Low, STATUS: Released to Prod | O26: Matt-Keuning | P26: 3 | Q26: https://github.com/cloudwarriors-ai/zoom_presales_django/issues/422 | R26: =IFERROR(__xludf.DUMMYFUNCTION("IF(REGEXMATCH(N26, ""PRIORITY: Low""), ""Low"", IF(REGEXMATCH(N26, ""PRIORITY: Medium""), ""Medium"", IF(REGEXMATCH(N26, ""PRIORITY: High""), ""High"", """"))) "),"Low") -> Low | S26: =IFERROR(__xludf.DUMMYFUNCTION("IF(REGEXMATCH(N26, ""SKILL: Low""), ""Low"", IF(REGEXMATCH(N26, ""SKILL: Medium""), ""Medium"", IF(REGEXMATCH(N26, ""SKILL: High""), ""High"", """")))"),"Low") -> Low | T26: =IFERROR(__xludf.DUMMYFUNCTION("IF(REGEXMATCH(N26, ""STATUS: Dev Complete - Awaiting QA""), ""Dev Complete - Awaiting QA"", IF(REGEXMATCH(N26, ""STATUS: Follow-Up Required""), ""Follow-Up Required"", IF(REGEXMATCH(N26, ""STATUS: In Progress""), ""In Progress"", IF(REGEXMATCH(N26, ""STAT"&"US: In QA""), ""In QA"", IF(REGEXMATCH(N26, ""STATUS: Needs Customer Feedback""), ""Needs Customer Feedback"", IF(REGEXMATCH(N26, ""STATUS: QA Passed - Awaiting Release""), ""QA Passed - Awaiting Release"", IF(REGEXMATCH(N26, ""STATUS: Release to Prod""),"&" ""Release to Prod"", """")))))))"),"")
A27: cloudwarriors-ai/zoom_presales_django | B27: ZoomWarriors v1 | C27: 418 | D27: Edit Previous Customer Quote Functionality - Saving Previously Entered Data | E27: closed | F27: 2025-08-05T16:40:25Z | G27: =IF(I27="", "", TEXT(DATEVALUE(LEFT(F27, 10)), "dd-mmm-yyyy")) -> 05-Aug-2025 | H27: rebecca-cichy | I27: 2025-09-05T18:41:50Z | J27: =IF(I27="", "", TEXT(DATEVALUE(LEFT(I27, 10)), "dd-mmm-yyyy")) -> 05-Sep-2025 | K27: 2025-09-05T18:41:50Z | L27: =IF(K27="", "", TEXT(DATEVALUE(LEFT(K27, 10)), "dd-mmm-yyyy")) -> 05-Sep-2025 | M27: Bug | N27: PRIORITY: High, SKILL: Medium, STATUS: Released to Prod | O27: Matt-Keuning | P27: 4 | Q27: https://github.com/cloudwarriors-ai/zoom_presales_django/issues/418 | R27: =IFERROR(__xludf.DUMMYFUNCTION("IF(REGEXMATCH(N27, ""PRIORITY: Low""), ""Low"", IF(REGEXMATCH(N27, ""PRIORITY: Medium""), ""Medium"", IF(REGEXMATCH(N27, ""PRIORITY: High""), ""High"", """"))) "),"High") -> High | S27: =IFERROR(__xludf.DUMMYFUNCTION("IF(REGEXMATCH(N27, ""SKILL: Low""), ""Low"", IF(REGEXMATCH(N27, ""SKILL: Medium""), ""Medium"", IF(REGEXMATCH(N27, ""SKILL: High""), ""High"", """")))"),"Medium") -> Medium | T27: =IFERROR(__xludf.DUMMYFUNCTION("IF(REGEXMATCH(N27, ""STATUS: Dev Complete - Awaiting QA""), ""Dev Complete - Awaiting QA"", IF(REGEXMATCH(N27, ""STATUS: Follow-Up Required""), ""Follow-Up Required"", IF(REGEXMATCH(N27, ""STATUS: In Progress""), ""In Progress"", IF(REGEXMATCH(N27, ""STAT"&"US: In QA""), ""In QA"", IF(REGEXMATCH(N27, ""STATUS: Needs Customer Feedback""), ""Needs Customer Feedback"", IF(REGEXMATCH(N27, ""STATUS: QA Passed - Awaiting Release""), ""QA Passed - Awaiting Release"", IF(REGEXMATCH(N27, ""STATUS: Release to Prod""),"&" ""Release to Prod"", """")))))))"),"")
A28: cloudwarriors-ai/zoom_presales_django | B28: ZoomWarriors v1 | C28: 407 | D28: Align Toggle Buttons - Zoom Phone SBC & PBX - ZW Dev | E28: closed | F28: 2025-07-14T16:50:52Z | G28: =IF(I28="", "", TEXT(DATEVALUE(LEFT(F28, 10)), "dd-mmm-yyyy")) -> 14-Jul-2025 | H28: Matt-Keuning | I28: 2025-07-31T21:29:51Z | J28: =IF(I28="", "", TEXT(DATEVALUE(LEFT(I28, 10)), "dd-mmm-yyyy")) -> 31-Jul-2025 | K28: 2025-07-31T21:29:51Z | L28: =IF(K28="", "", TEXT(DATEVALUE(LEFT(K28, 10)), "dd-mmm-yyyy")) -> 31-Jul-2025 | M28: Feature | N28: PRIORITY: Low, SKILL: Low, STATUS: Update in v2.0 | O28: jvitato1 | P28: 2 | Q28: https://github.com/cloudwarriors-ai/zoom_presales_django/issues/407 | R28: =IFERROR(__xludf.DUMMYFUNCTION("IF(REGEXMATCH(N28, ""PRIORITY: Low""), ""Low"", IF(REGEXMATCH(N28, ""PRIORITY: Medium""), ""Medium"", IF(REGEXMATCH(N28, ""PRIORITY: High""), ""High"", """"))) "),"Low") -> Low | S28: =IFERROR(__xludf.DUMMYFUNCTION("IF(REGEXMATCH(N28, ""SKILL: Low""), ""Low"", IF(REGEXMATCH(N28, ""SKILL: Medium""), ""Medium"", IF(REGEXMATCH(N28, ""SKILL: High""), ""High"", """")))"),"Low") -> Low | T28: =IFERROR(__xludf.DUMMYFUNCTION("IF(REGEXMATCH(N28, ""STATUS: Dev Complete - Awaiting QA""), ""Dev Complete - Awaiting QA"", IF(REGEXMATCH(N28, ""STATUS: Follow-Up Required""), ""Follow-Up Required"", IF(REGEXMATCH(N28, ""STATUS: In Progress""), ""In Progress"", IF(REGEXMATCH(N28, ""STAT"&"US: In QA""), ""In QA"", IF(REGEXMATCH(N28, ""STATUS: Needs Customer Feedback""), ""Needs Customer Feedback"", IF(REGEXMATCH(N28, ""STATUS: QA Passed - Awaiting Release""), ""QA Passed - Awaiting Release"", IF(REGEXMATCH(N28, ""STATUS: Release to Prod""),"&" ""Release to Prod"", """")))))))"),"")
A29: cloudwarriors-ai/zoom_presales_django | B29: ZoomWarriors v1 | C29: 406 | D29: Zoom Contact Center Page - Social Media (Flows, Queues, Surveys, Database Dips) Not Saving - ZW Dev | E29: closed | F29: 2025-07-14T13:16:46Z | G29: =IF(I29="", "", TEXT(DATEVALUE(LEFT(F29, 10)), "dd-mmm-yyyy")) -> 14-Jul-2025 | H29: Matt-Keuning | I29: 2025-08-22T00:37:50Z | J29: =IF(I29="", "", TEXT(DATEVALUE(LEFT(I29, 10)), "dd-mmm-yyyy")) -> 22-Aug-2025 | K29: 2025-08-11T20:45:47Z | L29: =IF(K29="", "", TEXT(DATEVALUE(LEFT(K29, 10)), "dd-mmm-yyyy")) -> 11-Aug-2025 | M29: Bug | N29: PRIORITY: High, SKILL: Medium, STATUS: Released to Prod | O29: campbellayers | P29: 6 | Q29: https://github.com/cloudwarriors-ai/zoom_presales_django/issues/406 | R29: =IFERROR(__xludf.DUMMYFUNCTION("IF(REGEXMATCH(N29, ""PRIORITY: Low""), ""Low"", IF(REGEXMATCH(N29, ""PRIORITY: Medium""), ""Medium"", IF(REGEXMATCH(N29, ""PRIORITY: High""), ""High"", """"))) "),"High") -> High | S29: =IFERROR(__xludf.DUMMYFUNCTION("IF(REGEXMATCH(N29, ""SKILL: Low""), ""Low"", IF(REGEXMATCH(N29, ""SKILL: Medium""), ""Medium"", IF(REGEXMATCH(N29, ""SKILL: High""), ""High"", """")))"),"Medium") -> Medium | T29: =IFERROR(__xludf.DUMMYFUNCTION("IF(REGEXMATCH(N29, ""STATUS: Dev Complete - Awaiting QA""), ""Dev Complete - Awaiting QA"", IF(REGEXMATCH(N29, ""STATUS: Follow-Up Required""), ""Follow-Up Required"", IF(REGEXMATCH(N29, ""STATUS: In Progress""), ""In Progress"", IF(REGEXMATCH(N29, ""STAT"&"US: In QA""), ""In QA"", IF(REGEXMATCH(N29, ""STATUS: Needs Customer Feedback""), ""Needs Customer Feedback"", IF(REGEXMATCH(N29, ""STATUS: QA Passed - Awaiting Release""), ""QA Passed - Awaiting Release"", IF(REGEXMATCH(N29, ""STATUS: Release to Prod""),"&" ""Release to Prod"", """")))))))"),"")
A30: cloudwarriors-ai/zoom_presales_django | B30: ZoomWarriors v1 | C30: 405 | D30: Remove Drop Down Arrow (SSO Type, SSO Authentication Method) - Zoom Phone & Contact Center Custom Additions Page - ZW Dev | E30: closed | F30: 2025-07-14T12:56:09Z | G30: =IF(I30="", "", TEXT(DATEVALUE(LEFT(F30, 10)), "dd-mmm-yyyy")) -> 14-Jul-2025 | H30: Matt-Keuning | I30: 2025-08-18T19:55:38Z | J30: =IF(I30="", "", TEXT(DATEVALUE(LEFT(I30, 10)), "dd-mmm-yyyy")) -> 18-Aug-2025 | K30: 2025-08-18T19:55:38Z | L30: =IF(K30="", "", TEXT(DATEVALUE(LEFT(K30, 10)), "dd-mmm-yyyy")) -> 18-Aug-2025 | M30: Feature | N30: PRIORITY: Low, SKILL: Low, STATUS: QA Passed - Awaiting Release | O30: Matt-Keuning | P30: 1 | Q30: https://github.com/cloudwarriors-ai/zoom_presales_django/issues/405 | R30: =IFERROR(__xludf.DUMMYFUNCTION("IF(REGEXMATCH(N30, ""PRIORITY: Low""), ""Low"", IF(REGEXMATCH(N30, ""PRIORITY: Medium""), ""Medium"", IF(REGEXMATCH(N30, ""PRIORITY: High""), ""High"", """"))) "),"Low") -> Low | S30: =IFERROR(__xludf.DUMMYFUNCTION("IF(REGEXMATCH(N30, ""SKILL: Low""), ""Low"", IF(REGEXMATCH(N30, ""SKILL: Medium""), ""Medium"", IF(REGEXMATCH(N30, ""SKILL: High""), ""High"", """")))"),"Low") -> Low | T30: =IFERROR(__xludf.DUMMYFUNCTION("IF(REGEXMATCH(N30, ""STATUS: Dev Complete - Awaiting QA""), ""Dev Complete - Awaiting QA"", IF(REGEXMATCH(N30, ""STATUS: Follow-Up Required""), ""Follow-Up Required"", IF(REGEXMATCH(N30, ""STATUS: In Progress""), ""In Progress"", IF(REGEXMATCH(N30, ""STAT"&"US: In QA""), ""In QA"", IF(REGEXMATCH(N30, ""STATUS: Needs Customer Feedback""), ""Needs Customer Feedback"", IF(REGEXMATCH(N30, ""STATUS: QA Passed - Awaiting Release""), ""QA Passed - Awaiting Release"", IF(REGEXMATCH(N30, ""STATUS: Release to Prod""),"&" ""Release to Prod"", """")))))))"),"QA Passed - Awaiting Release") -> QA Passed - Awaiting Release
A31: cloudwarriors-ai/zoom_presales_django | B31: ZoomWarriors v1 | C31: 404 | D31: Trivial Horizontal Scroll Bar - Zoom Phone Hardware Page - Zoom Warriors (DEV) | E31: closed | F31: 2025-07-14T12:18:24Z | G31: =IF(I31="", "", TEXT(DATEVALUE(LEFT(F31, 10)), "dd-mmm-yyyy")) -> 14-Jul-2025 | H31: Matt-Keuning | I31: 2025-07-31T22:39:09Z | J31: =IF(I31="", "", TEXT(DATEVALUE(LEFT(I31, 10)), "dd-mmm-yyyy")) -> 31-Jul-2025 | K31: 2025-07-14T16:56:20Z | L31: =IF(K31="", "", TEXT(DATEVALUE(LEFT(K31, 10)), "dd-mmm-yyyy")) -> 14-Jul-2025 | M31: Task | N31: None | O31: rebecca-cichy | P31: 1 | Q31: https://github.com/cloudwarriors-ai/zoom_presales_django/issues/404 | R31: =IFERROR(__xludf.DUMMYFUNCTION("IF(REGEXMATCH(N31, ""PRIORITY: Low""), ""Low"", IF(REGEXMATCH(N31, ""PRIORITY: Medium""), ""Medium"", IF(REGEXMATCH(N31, ""PRIORITY: High""), ""High"", """"))) "),"") | S31: =IFERROR(__xludf.DUMMYFUNCTION("IF(REGEXMATCH(N31, ""SKILL: Low""), ""Low"", IF(REGEXMATCH(N31, ""SKILL: Medium""), ""Medium"", IF(REGEXMATCH(N31, ""SKILL: High""), ""High"", """")))"),"") | T31: =IFERROR(__xludf.DUMMYFUNCTION("IF(REGEXMATCH(N31, ""STATUS: Dev Complete - Awaiting QA""), ""Dev Complete - Awaiting QA"", IF(REGEXMATCH(N31, ""STATUS: Follow-Up Required""), ""Follow-Up Required"", IF(REGEXMATCH(N31, ""STATUS: In Progress""), ""In Progress"", IF(REGEXMATCH(N31, ""STAT"&"US: In QA""), ""In QA"", IF(REGEXMATCH(N31, ""STATUS: Needs Customer Feedback""), ""Needs Customer Feedback"", IF(REGEXMATCH(N31, ""STATUS: QA Passed - Awaiting Release""), ""QA Passed - Awaiting Release"", IF(REGEXMATCH(N31, ""STATUS: Release to Prod""),"&" ""Release to Prod"", """")))))))"),"")
A32: cloudwarriors-ai/zoom_presales_django | B32: ZoomWarriors v1 | C32: 403 | D32: Zoom Warriors Production site: Paging Configuration page split up | E32: closed | F32: 2025-07-11T20:08:59Z | G32: =IF(I32="", "", TEXT(DATEVALUE(LEFT(F32, 10)), "dd-mmm-yyyy")) -> 11-Jul-2025 | H32: Matt-Keuning | I32: 2025-09-05T18:41:39Z | K32: 2025-09-05T18:41:39Z | M32: Bug | N32: PRIORITY: Low, SKILL: Low, STATUS: QA Passed - Awaiting Release | O32: jvitato1 | P32: 5 | Q32: https://github.com/cloudwarriors-ai/zoom_presales_django/issues/403
A33: cloudwarriors-ai/zoom_presales_django | B33: ZoomWarriors v1 | C33: 401 | D33: Missing Drop Down Fields in Paging Configuration (DEV) | E33: closed | F33: 2025-07-11T18:58:06Z | G33: =IF(I33="", "", TEXT(DATEVALUE(LEFT(F33, 10)), "dd-mmm-yyyy")) -> 11-Jul-2025 | H33: Matt-Keuning | I33: 2025-07-31T22:39:09Z | K33: 2025-07-15T17:03:47Z | M33: Bug | N33: PRIORITY: High, STATUS: Dev Complete - Awaiting QA | P33: 3 | Q33: https://github.com/cloudwarriors-ai/zoom_presales_django/issues/401
A34: cloudwarriors-ai/zoom_presales_django | B34: ZoomWarriors v1 | C34: 400 | D34: Phone Number Validation on Company Order page - BUG | E34: closed | F34: 2025-07-11T15:27:52Z | G34: =IF(I34="", "", TEXT(DATEVALUE(LEFT(F34, 10)), "dd-mmm-yyyy")) -> 11-Jul-2025 | H34: Waterboy-TH | I34: 2025-07-31T22:39:08Z | K34: 2025-07-15T17:05:30Z | M34: Bug | N34: STATUS: Dev Complete - Awaiting QA | P34: 4 | Q34: https://github.com/cloudwarriors-ai/zoom_presales_django/issues/400
A35: cloudwarriors-ai/zoom_presales_django | B35: ZoomWarriors v1 | C35: 398 | D35: Deployment Overview - 'Go-Live Date' goes back in time | E35: closed | F35: 2025-07-10T06:33:32Z | G35: =IF(I35="", "", TEXT(DATEVALUE(LEFT(F35, 10)), "dd-mmm-yyyy")) -> 10-Jul-2025 | H35: abbyrien | I35: 2025-09-05T18:41:29Z | J35: =IF(I35="", "", TEXT(DATEVALUE(LEFT(I35, 10)), "dd-mmm-yyyy")) -> 05-Sep-2025 | K35: 2025-09-05T18:41:29Z | L35: =IF(K35="", "", TEXT(DATEVALUE(LEFT(K35, 10)), "dd-mmm-yyyy")) -> 05-Sep-2025 | M35: Task | N35: PRIORITY: Low, SKILL: Low, STATUS: Released to Prod | O35: Matt-Keuning | P35: 4 | Q35: https://github.com/cloudwarriors-ai/zoom_presales_django/issues/398 | R35: =IFERROR(__xludf.DUMMYFUNCTION("IF(REGEXMATCH(N35, ""PRIORITY: Low""), ""Low"", IF(REGEXMATCH(N35, ""PRIORITY: Medium""), ""Medium"", IF(REGEXMATCH(N35, ""PRIORITY: High""), ""High"", """"))) "),"Low") -> Low | S35: =IFERROR(__xludf.DUMMYFUNCTION("IF(REGEXMATCH(N35, ""SKILL: Low""), ""Low"", IF(REGEXMATCH(N35, ""SKILL: Medium""), ""Medium"", IF(REGEXMATCH(N35, ""SKILL: High""), ""High"", """")))"),"Low") -> Low | T35: =IFERROR(__xludf.DUMMYFUNCTION("IF(REGEXMATCH(N35, ""STATUS: Dev Complete - Awaiting QA""), ""Dev Complete - Awaiting QA"", IF(REGEXMATCH(N35, ""STATUS: Follow-Up Required""), ""Follow-Up Required"", IF(REGEXMATCH(N35, ""STATUS: In Progress""), ""In Progress"", IF(REGEXMATCH(N35, ""STAT"&"US: In QA""), ""In QA"", IF(REGEXMATCH(N35, ""STATUS: Needs Customer Feedback""), ""Needs Customer Feedback"", IF(REGEXMATCH(N35, ""STATUS: QA Passed - Awaiting Release""), ""QA Passed - Awaiting Release"", IF(REGEXMATCH(N35, ""STATUS: Release to Prod""),"&" ""Release to Prod"", """")))))))"),"")
A36: cloudwarriors-ai/zoom_presales_django | B36: ZoomWarriors v1 | C36: 397 | D36: Zoom Contact Center Page - Channel Toggles NOT Working (on Mac) | E36: closed | F36: 2025-07-10T06:29:22Z | G36: =IF(I36="", "", TEXT(DATEVALUE(LEFT(F36, 10)), "dd-mmm-yyyy")) -> 10-Jul-2025 | H36: abbyrien | I36: 2025-07-31T22:39:08Z | J36: =IF(I36="", "", TEXT(DATEVALUE(LEFT(I36, 10)), "dd-mmm-yyyy")) -> 31-Jul-2025 | K36: 2025-07-15T17:43:02Z | L36: =IF(K36="", "", TEXT(DATEVALUE(LEFT(K36, 10)), "dd-mmm-yyyy")) -> 15-Jul-2025 | M36: Bug | N36: STATUS: Dev Complete - Awaiting QA | P36: 3 | Q36: https://github.com/cloudwarriors-ai/zoom_presales_django/issues/397 | R36: =IFERROR(__xludf.DUMMYFUNCTION("IF(REGEXMATCH(N36, ""PRIORITY: Low""), ""Low"", IF(REGEXMATCH(N36, ""PRIORITY: Medium""), ""Medium"", IF(REGEXMATCH(N36, ""PRIORITY: High""), ""High"", """"))) "),"") | S36: =IFERROR(__xludf.DUMMYFUNCTION("IF(REGEXMATCH(N36, ""SKILL: Low""), ""Low"", IF(REGEXMATCH(N36, ""SKILL: Medium""), ""Medium"", IF(REGEXMATCH(N36, ""SKILL: High""), ""High"", """")))"),"") | T36: =IFERROR(__xludf.DUMMYFUNCTION("IF(REGEXMATCH(N36, ""STATUS: Dev Complete - Awaiting QA""), ""Dev Complete - Awaiting QA"", IF(REGEXMATCH(N36, ""STATUS: Follow-Up Required""), ""Follow-Up Required"", IF(REGEXMATCH(N36, ""STATUS: In Progress""), ""In Progress"", IF(REGEXMATCH(N36, ""STAT"&"US: In QA""), ""In QA"", IF(REGEXMATCH(N36, ""STATUS: Needs Customer Feedback""), ""Needs Customer Feedback"", IF(REGEXMATCH(N36, ""STATUS: QA Passed - Awaiting Release""), ""QA Passed - Awaiting Release"", IF(REGEXMATCH(N36, ""STATUS: Release to Prod""),"&" ""Release to Prod"", """")))))))"),"Dev Complete - Awaiting QA") -> Dev Complete - Awaiting QA
A37: cloudwarriors-ai/zoom_presales_django | B37: ZoomWarriors v1 | C37: 396 | D37: Zoom Phone Locations Page - Capping Total Countries | E37: closed | F37: 2025-07-10T06:10:15Z | G37: =IF(I37="", "", TEXT(DATEVALUE(LEFT(F37, 10)), "dd-mmm-yyyy")) -> 10-Jul-2025 | H37: abbyrien | I37: 2025-09-05T18:41:17Z | J37: =IF(I37="", "", TEXT(DATEVALUE(LEFT(I37, 10)), "dd-mmm-yyyy")) -> 05-Sep-2025 | K37: 2025-09-05T18:41:17Z | L37: =IF(K37="", "", TEXT(DATEVALUE(LEFT(K37, 10)), "dd-mmm-yyyy")) -> 05-Sep-2025 | M37: Bug | N37: PRIORITY: Low, SKILL: Low, STATUS: Update in v2.0 | O37: jvitato1 | P37: 2 | Q37: https://github.com/cloudwarriors-ai/zoom_presales_django/issues/396 | R37: =IFERROR(__xludf.DUMMYFUNCTION("IF(REGEXMATCH(N37, ""PRIORITY: Low""), ""Low"", IF(REGEXMATCH(N37, ""PRIORITY: Medium""), ""Medium"", IF(REGEXMATCH(N37, ""PRIORITY: High""), ""High"", """"))) "),"Low") -> Low | S37: =IFERROR(__xludf.DUMMYFUNCTION("IF(REGEXMATCH(N37, ""SKILL: Low""), ""Low"", IF(REGEXMATCH(N37, ""SKILL: Medium""), ""Medium"", IF(REGEXMATCH(N37, ""SKILL: High""), ""High"", """")))"),"Low") -> Low | T37: =IFERROR(__xludf.DUMMYFUNCTION("IF(REGEXMATCH(N37, ""STATUS: Dev Complete - Awaiting QA""), ""Dev Complete - Awaiting QA"", IF(REGEXMATCH(N37, ""STATUS: Follow-Up Required""), ""Follow-Up Required"", IF(REGEXMATCH(N37, ""STATUS: In Progress""), ""In Progress"", IF(REGEXMATCH(N37, ""STAT"&"US: In QA""), ""In QA"", IF(REGEXMATCH(N37, ""STATUS: Needs Customer Feedback""), ""Needs Customer Feedback"", IF(REGEXMATCH(N37, ""STATUS: QA Passed - Awaiting Release""), ""QA Passed - Awaiting Release"", IF(REGEXMATCH(N37, ""STATUS: Release to Prod""),"&" ""Release to Prod"", """")))))))"),"")
A38: cloudwarriors-ai/zoom_presales_django | B38: ZoomWarriors v1 | C38: 395 | D38: Zoom Phone Licenses - Duplicate Fields Allowed | E38: closed | F38: 2025-07-10T06:05:39Z | G38: =IF(I38="", "", TEXT(DATEVALUE(LEFT(F38, 10)), "dd-mmm-yyyy")) -> 10-Jul-2025 | H38: abbyrien | I38: 2025-09-05T18:40:49Z | J38: =IF(I38="", "", TEXT(DATEVALUE(LEFT(I38, 10)), "dd-mmm-yyyy")) -> 05-Sep-2025 | K38: 2025-09-05T18:40:49Z | L38: =IF(K38="", "", TEXT(DATEVALUE(LEFT(K38, 10)), "dd-mmm-yyyy")) -> 05-Sep-2025 | M38: Bug | N38: PRIORITY: Low, SKILL: Medium, STATUS: Released to Prod | O38: Matt-Keuning | P38: 3 | Q38: https://github.com/cloudwarriors-ai/zoom_presales_django/issues/395 | R38: =IFERROR(__xludf.DUMMYFUNCTION("IF(REGEXMATCH(N38, ""PRIORITY: Low""), ""Low"", IF(REGEXMATCH(N38, ""PRIORITY: Medium""), ""Medium"", IF(REGEXMATCH(N38, ""PRIORITY: High""), ""High"", """"))) "),"Low") -> Low | S38: =IFERROR(__xludf.DUMMYFUNCTION("IF(REGEXMATCH(N38, ""SKILL: Low""), ""Low"", IF(REGEXMATCH(N38, ""SKILL: Medium""), ""Medium"", IF(REGEXMATCH(N38, ""SKILL: High""), ""High"", """")))"),"Medium") -> Medium | T38: =IFERROR(__xludf.DUMMYFUNCTION("IF(REGEXMATCH(N38, ""STATUS: Dev Complete - Awaiting QA""), ""Dev Complete - Awaiting QA"", IF(REGEXMATCH(N38, ""STATUS: Follow-Up Required""), ""Follow-Up Required"", IF(REGEXMATCH(N38, ""STATUS: In Progress""), ""In Progress"", IF(REGEXMATCH(N38, ""STAT"&"US: In QA""), ""In QA"", IF(REGEXMATCH(N38, ""STATUS: Needs Customer Feedback""), ""Needs Customer Feedback"", IF(REGEXMATCH(N38, ""STATUS: QA Passed - Awaiting Release""), ""QA Passed - Awaiting Release"", IF(REGEXMATCH(N38, ""STATUS: Release to Prod""),"&" ""Release to Prod"", """")))))))"),"")
A39: cloudwarriors-ai/zoom_presales_django | B39: ZoomWarriors v1 | C39: 394 | D39: Tool Tip - Customer Information Page UI Enhancement | E39: closed | F39: 2025-07-10T06:03:16Z | G39: =IF(I39="", "", TEXT(DATEVALUE(LEFT(F39, 10)), "dd-mmm-yyyy")) -> 10-Jul-2025 | H39: abbyrien | I39: 2025-09-05T18:40:40Z | J39: =IF(I39="", "", TEXT(DATEVALUE(LEFT(I39, 10)), "dd-mmm-yyyy")) -> 05-Sep-2025 | K39: 2025-09-05T18:40:40Z | L39: =IF(K39="", "", TEXT(DATEVALUE(LEFT(K39, 10)), "dd-mmm-yyyy")) -> 05-Sep-2025 | M39: Feature | N39: PRIORITY: Low, SKILL: Low, STATUS: In Progress | O39: Matt-Keuning | P39: 5 | Q39: https://github.com/cloudwarriors-ai/zoom_presales_django/issues/394 | R39: =IFERROR(__xludf.DUMMYFUNCTION("IF(REGEXMATCH(N39, ""PRIORITY: Low""), ""Low"", IF(REGEXMATCH(N39, ""PRIORITY: Medium""), ""Medium"", IF(REGEXMATCH(N39, ""PRIORITY: High""), ""High"", """"))) "),"Low") -> Low | S39: =IFERROR(__xludf.DUMMYFUNCTION("IF(REGEXMATCH(N39, ""SKILL: Low""), ""Low"", IF(REGEXMATCH(N39, ""SKILL: Medium""), ""Medium"", IF(REGEXMATCH(N39, ""SKILL: High""), ""High"", """")))"),"Low") -> Low | T39: =IFERROR(__xludf.DUMMYFUNCTION("IF(REGEXMATCH(N39, ""STATUS: Dev Complete - Awaiting QA""), ""Dev Complete - Awaiting QA"", IF(REGEXMATCH(N39, ""STATUS: Follow-Up Required""), ""Follow-Up Required"", IF(REGEXMATCH(N39, ""STATUS: In Progress""), ""In Progress"", IF(REGEXMATCH(N39, ""STAT"&"US: In QA""), ""In QA"", IF(REGEXMATCH(N39, ""STATUS: Needs Customer Feedback""), ""Needs Customer Feedback"", IF(REGEXMATCH(N39, ""STATUS: QA Passed - Awaiting Release""), ""QA Passed - Awaiting Release"", IF(REGEXMATCH(N39, ""STATUS: Release to Prod""),"&" ""Release to Prod"", """")))))))"),"In Progress") -> In Progress
A40: cloudwarriors-ai/zoom_presales_django | B40: ZoomWarriors v1 | C40: 393 | D40: Add Button for 'Superusers' to go to Cloud Warriors Cost w/o Margin Page | E40: closed | F40: 2025-07-09T21:06:22Z | G40: =IF(I40="", "", TEXT(DATEVALUE(LEFT(F40, 10)), "dd-mmm-yyyy")) -> 09-Jul-2025 | H40: rebecca-cichy | I40: 2025-09-05T18:40:23Z | J40: =IF(I40="", "", TEXT(DATEVALUE(LEFT(I40, 10)), "dd-mmm-yyyy")) -> 05-Sep-2025 | K40: 2025-09-05T18:40:23Z | L40: =IF(K40="", "", TEXT(DATEVALUE(LEFT(K40, 10)), "dd-mmm-yyyy")) -> 05-Sep-2025 | M40: Feature | N40: PRIORITY: Low, SKILL: Low, STATUS: Update in v2.0 | O40: jvitato1 | P40: 3 | Q40: https://github.com/cloudwarriors-ai/zoom_presales_django/issues/393 | R40: =IFERROR(__xludf.DUMMYFUNCTION("IF(REGEXMATCH(N40, ""PRIORITY: Low""), ""Low"", IF(REGEXMATCH(N40, ""PRIORITY: Medium""), ""Medium"", IF(REGEXMATCH(N40, ""PRIORITY: High""), ""High"", """"))) "),"Low") -> Low | S40: =IFERROR(__xludf.DUMMYFUNCTION("IF(REGEXMATCH(N40, ""SKILL: Low""), ""Low"", IF(REGEXMATCH(N40, ""SKILL: Medium""), ""Medium"", IF(REGEXMATCH(N40, ""SKILL: High""), ""High"", """")))"),"Low") -> Low | T40: =IFERROR(__xludf.DUMMYFUNCTION("IF(REGEXMATCH(N40, ""STATUS: Dev Complete - Awaiting QA""), ""Dev Complete - Awaiting QA"", IF(REGEXMATCH(N40, ""STATUS: Follow-Up Required""), ""Follow-Up Required"", IF(REGEXMATCH(N40, ""STATUS: In Progress""), ""In Progress"", IF(REGEXMATCH(N40, ""STAT"&"US: In QA""), ""In QA"", IF(REGEXMATCH(N40, ""STATUS: Needs Customer Feedback""), ""Needs Customer Feedback"", IF(REGEXMATCH(N40, ""STATUS: QA Passed - Awaiting Release""), ""QA Passed - Awaiting Release"", IF(REGEXMATCH(N40, ""STATUS: Release to Prod""),"&" ""Release to Prod"", """")))))))"),"")
A41: cloudwarriors-ai/zoom_presales_django | B41: ZoomWarriors v1 | C41: 392 | D41: Discount Button - Add Discount Button in Django to Modify Quotes in Orders | E41: closed | F41: 2025-07-09T21:00:11Z | G41: =IF(I41="", "", TEXT(DATEVALUE(LEFT(F41, 10)), "dd-mmm-yyyy")) -> 09-Jul-2025 | H41: rebecca-cichy | I41: 2025-07-31T21:12:53Z | J41: =IF(I41="", "", TEXT(DATEVALUE(LEFT(I41, 10)), "dd-mmm-yyyy")) -> 31-Jul-2025 | K41: 2025-07-31T21:12:53Z | L41: =IF(K41="", "", TEXT(DATEVALUE(LEFT(K41, 10)), "dd-mmm-yyyy")) -> 31-Jul-2025 | M41: Feature | N41: PRIORITY: Medium, SKILL: Low, STATUS: Update in v2.0 | O41: Jeffrey-Searcy | P41: 4 | Q41: https://github.com/cloudwarriors-ai/zoom_presales_django/issues/392 | R41: =IFERROR(__xludf.DUMMYFUNCTION("IF(REGEXMATCH(N41, ""PRIORITY: Low""), ""Low"", IF(REGEXMATCH(N41, ""PRIORITY: Medium""), ""Medium"", IF(REGEXMATCH(N41, ""PRIORITY: High""), ""High"", """"))) "),"Medium") -> Medium | S41: =IFERROR(__xludf.DUMMYFUNCTION("IF(REGEXMATCH(N41, ""SKILL: Low""), ""Low"", IF(REGEXMATCH(N41, ""SKILL: Medium""), ""Medium"", IF(REGEXMATCH(N41, ""SKILL: High""), ""High"", """")))"),"Low") -> Low | T41: =IFERROR(__xludf.DUMMYFUNCTION("IF(REGEXMATCH(N41, ""STATUS: Dev Complete - Awaiting QA""), ""Dev Complete - Awaiting QA"", IF(REGEXMATCH(N41, ""STATUS: Follow-Up Required""), ""Follow-Up Required"", IF(REGEXMATCH(N41, ""STATUS: In Progress""), ""In Progress"", IF(REGEXMATCH(N41, ""STAT"&"US: In QA""), ""In QA"", IF(REGEXMATCH(N41, ""STATUS: Needs Customer Feedback""), ""Needs Customer Feedback"", IF(REGEXMATCH(N41, ""STATUS: QA Passed - Awaiting Release""), ""QA Passed - Awaiting Release"", IF(REGEXMATCH(N41, ""STATUS: Release to Prod""),"&" ""Release to Prod"", """")))))))"),"")
A42: cloudwarriors-ai/zoom_presales_django | B42: ZoomWarriors v1 | C42: 391 | D42: Zoom Warriors Dev Site: "Zoom Phone Paging Configuration" Page Unresponsive Buttons | E42: closed | F42: 2025-07-08T20:11:19Z | G42: =IF(I42="", "", TEXT(DATEVALUE(LEFT(F42, 10)), "dd-mmm-yyyy")) -> 08-Jul-2025 | H42: Matt-Keuning | I42: 2025-07-31T22:39:08Z | J42: =IF(I42="", "", TEXT(DATEVALUE(LEFT(I42, 10)), "dd-mmm-yyyy")) -> 31-Jul-2025 | K42: 2025-07-11T16:07:43Z | L42: =IF(K42="", "", TEXT(DATEVALUE(LEFT(K42, 10)), "dd-mmm-yyyy")) -> 11-Jul-2025 | M42: Bug | N42: None | O42: rebecca-cichy | P42: 1 | Q42: https://github.com/cloudwarriors-ai/zoom_presales_django/issues/391 | R42: =IFERROR(__xludf.DUMMYFUNCTION("IF(REGEXMATCH(N42, ""PRIORITY: Low""), ""Low"", IF(REGEXMATCH(N42, ""PRIORITY: Medium""), ""Medium"", IF(REGEXMATCH(N42, ""PRIORITY: High""), ""High"", """"))) "),"") | S42: =IFERROR(__xludf.DUMMYFUNCTION("IF(REGEXMATCH(N42, ""SKILL: Low""), ""Low"", IF(REGEXMATCH(N42, ""SKILL: Medium""), ""Medium"", IF(REGEXMATCH(N42, ""SKILL: High""), ""High"", """")))"),"") | T42: =IFERROR(__xludf.DUMMYFUNCTION("IF(REGEXMATCH(N42, ""STATUS: Dev Complete - Awaiting QA""), ""Dev Complete - Awaiting QA"", IF(REGEXMATCH(N42, ""STATUS: Follow-Up Required""), ""Follow-Up Required"", IF(REGEXMATCH(N42, ""STATUS: In Progress""), ""In Progress"", IF(REGEXMATCH(N42, ""STAT"&"US: In QA""), ""In QA"", IF(REGEXMATCH(N42, ""STATUS: Needs Customer Feedback""), ""Needs Customer Feedback"", IF(REGEXMATCH(N42, ""STATUS: QA Passed - Awaiting Release""), ""QA Passed - Awaiting Release"", IF(REGEXMATCH(N42, ""STATUS: Release to Prod""),"&" ""Release to Prod"", """")))))))"),"")
A43: cloudwarriors-ai/zoom_presales_django | B43: ZoomWarriors v1 | C43: 390 | D43: ZCC zoom contact center input not updating | E43: closed | F43: 2025-07-08T13:51:25Z | G43: =IF(I43="", "", TEXT(DATEVALUE(LEFT(F43, 10)), "dd-mmm-yyyy")) -> 08-Jul-2025 | H43: dan-fellner | I43: 2025-07-31T18:45:27Z | J43: =IF(I43="", "", TEXT(DATEVALUE(LEFT(I43, 10)), "dd-mmm-yyyy")) -> 31-Jul-2025 | K43: 2025-07-31T18:45:27Z | L43: =IF(K43="", "", TEXT(DATEVALUE(LEFT(K43, 10)), "dd-mmm-yyyy")) -> 31-Jul-2025 | M43: Bug | N43: SKILL: Medium, STATUS: Follow-Up Required | O43: rebecca-cichy | P43: 4 | Q43: https://github.com/cloudwarriors-ai/zoom_presales_django/issues/390 | R43: =IFERROR(__xludf.DUMMYFUNCTION("IF(REGEXMATCH(N43, ""PRIORITY: Low""), ""Low"", IF(REGEXMATCH(N43, ""PRIORITY: Medium""), ""Medium"", IF(REGEXMATCH(N43, ""PRIORITY: High""), ""High"", """"))) "),"") | S43: =IFERROR(__xludf.DUMMYFUNCTION("IF(REGEXMATCH(N43, ""SKILL: Low""), ""Low"", IF(REGEXMATCH(N43, ""SKILL: Medium""), ""Medium"", IF(REGEXMATCH(N43, ""SKILL: High""), ""High"", """")))"),"Medium") -> Medium | T43: =IFERROR(__xludf.DUMMYFUNCTION("IF(REGEXMATCH(N43, ""STATUS: Dev Complete - Awaiting QA""), ""Dev Complete - Awaiting QA"", IF(REGEXMATCH(N43, ""STATUS: Follow-Up Required""), ""Follow-Up Required"", IF(REGEXMATCH(N43, ""STATUS: In Progress""), ""In Progress"", IF(REGEXMATCH(N43, ""STAT"&"US: In QA""), ""In QA"", IF(REGEXMATCH(N43, ""STATUS: Needs Customer Feedback""), ""Needs Customer Feedback"", IF(REGEXMATCH(N43, ""STATUS: QA Passed - Awaiting Release""), ""QA Passed - Awaiting Release"", IF(REGEXMATCH(N43, ""STATUS: Release to Prod""),"&" ""Release to Prod"", """")))))))"),"Follow-Up Required") -> Follow-Up Required
A44: cloudwarriors-ai/zoom_presales_django | B44: ZoomWarriors v1 | C44: 388 | D44: Tool Tip Change - Zoom Phone Paging Configuration | E44: closed | F44: 2025-06-26T18:55:37Z | G44: =IF(I44="", "", TEXT(DATEVALUE(LEFT(F44, 10)), "dd-mmm-yyyy")) -> 26-Jun-2025 | H44: Drake-Lankford | I44: 2025-09-26T14:48:16Z | J44: =IF(I44="", "", TEXT(DATEVALUE(LEFT(I44, 10)), "dd-mmm-yyyy")) -> 26-Sep-2025 | K44: 2025-06-30T18:30:20Z | L44: =IF(K44="", "", TEXT(DATEVALUE(LEFT(K44, 10)), "dd-mmm-yyyy")) -> 30-Jun-2025 | M44: Feature | N44: None | P44: 1 | Q44: https://github.com/cloudwarriors-ai/zoom_presales_django/issues/388 | R44: =IFERROR(__xludf.DUMMYFUNCTION("IF(REGEXMATCH(N44, ""PRIORITY: Low""), ""Low"", IF(REGEXMATCH(N44, ""PRIORITY: Medium""), ""Medium"", IF(REGEXMATCH(N44, ""PRIORITY: High""), ""High"", """"))) "),"") | S44: =IFERROR(__xludf.DUMMYFUNCTION("IF(REGEXMATCH(N44, ""SKILL: Low""), ""Low"", IF(REGEXMATCH(N44, ""SKILL: Medium""), ""Medium"", IF(REGEXMATCH(N44, ""SKILL: High""), ""High"", """")))"),"") | T44: =IFERROR(__xludf.DUMMYFUNCTION("IF(REGEXMATCH(N44, ""STATUS: Dev Complete - Awaiting QA""), ""Dev Complete - Awaiting QA"", IF(REGEXMATCH(N44, ""STATUS: Follow-Up Required""), ""Follow-Up Required"", IF(REGEXMATCH(N44, ""STATUS: In Progress""), ""In Progress"", IF(REGEXMATCH(N44, ""STAT"&"US: In QA""), ""In QA"", IF(REGEXMATCH(N44, ""STATUS: Needs Customer Feedback""), ""Needs Customer Feedback"", IF(REGEXMATCH(N44, ""STATUS: QA Passed - Awaiting Release""), ""QA Passed - Awaiting Release"", IF(REGEXMATCH(N44, ""STATUS: Release to Prod""),"&" ""Release to Prod"", """")))))))"),"")
A45: cloudwarriors-ai/zoom_presales_django | B45: ZoomWarriors v1 | C45: 387 | D45: TEST - Change Color to Blue & White | E45: closed | F45: 2025-06-26T16:02:59Z | G45: =IF(I45="", "", TEXT(DATEVALUE(LEFT(F45, 10)), "dd-mmm-yyyy")) -> 26-Jun-2025 | H45: rebecca-cichy | I45: 2025-07-31T22:39:07Z | J45: =IF(I45="", "", TEXT(DATEVALUE(LEFT(I45, 10)), "dd-mmm-yyyy")) -> 31-Jul-2025 | K45: 2025-06-26T17:03:28Z | L45: =IF(K45="", "", TEXT(DATEVALUE(LEFT(K45, 10)), "dd-mmm-yyyy")) -> 26-Jun-2025 | M45: Feature | N45: None | P45: 1 | Q45: https://github.com/cloudwarriors-ai/zoom_presales_django/issues/387 | R45: =IFERROR(__xludf.DUMMYFUNCTION("IF(REGEXMATCH(N45, ""PRIORITY: Low""), ""Low"", IF(REGEXMATCH(N45, ""PRIORITY: Medium""), ""Medium"", IF(REGEXMATCH(N45, ""PRIORITY: High""), ""High"", """"))) "),"") | S45: =IFERROR(__xludf.DUMMYFUNCTION("IF(REGEXMATCH(N45, ""SKILL: Low""), ""Low"", IF(REGEXMATCH(N45, ""SKILL: Medium""), ""Medium"", IF(REGEXMATCH(N45, ""SKILL: High""), ""High"", """")))"),"") | T45: =IFERROR(__xludf.DUMMYFUNCTION("IF(REGEXMATCH(N45, ""STATUS: Dev Complete - Awaiting QA""), ""Dev Complete - Awaiting QA"", IF(REGEXMATCH(N45, ""STATUS: Follow-Up Required""), ""Follow-Up Required"", IF(REGEXMATCH(N45, ""STATUS: In Progress""), ""In Progress"", IF(REGEXMATCH(N45, ""STAT"&"US: In QA""), ""In QA"", IF(REGEXMATCH(N45, ""STATUS: Needs Customer Feedback""), ""Needs Customer Feedback"", IF(REGEXMATCH(N45, ""STATUS: QA Passed - Awaiting Release""), ""QA Passed - Awaiting Release"", IF(REGEXMATCH(N45, ""STATUS: Release to Prod""),"&" ""Release to Prod"", """")))))))"),"")
A46: cloudwarriors-ai/zoom_presales_django | B46: ZoomWarriors v1 | C46: 386 | D46: SOW Issue - SOW Number Naming Convention | E46: closed | F46: 2025-06-26T10:46:49Z | G46: =IF(I46="", "", TEXT(DATEVALUE(LEFT(F46, 10)), "dd-mmm-yyyy")) -> 26-Jun-2025 | H46: rebecca-cichy | I46: 2025-09-26T14:48:16Z | J46: =IF(I46="", "", TEXT(DATEVALUE(LEFT(I46, 10)), "dd-mmm-yyyy")) -> 26-Sep-2025 | K46: 2025-06-26T12:04:05Z | L46: =IF(K46="", "", TEXT(DATEVALUE(LEFT(K46, 10)), "dd-mmm-yyyy")) -> 26-Jun-2025 | M46: Bug | N46: None | P46: 1 | Q46: https://github.com/cloudwarriors-ai/zoom_presales_django/issues/386 | R46: =IFERROR(__xludf.DUMMYFUNCTION("IF(REGEXMATCH(N46, ""PRIORITY: Low""), ""Low"", IF(REGEXMATCH(N46, ""PRIORITY: Medium""), ""Medium"", IF(REGEXMATCH(N46, ""PRIORITY: High""), ""High"", """"))) "),"") | S46: =IFERROR(__xludf.DUMMYFUNCTION("IF(REGEXMATCH(N46, ""SKILL: Low""), ""Low"", IF(REGEXMATCH(N46, ""SKILL: Medium""), ""Medium"", IF(REGEXMATCH(N46, ""SKILL: High""), ""High"", """")))"),"") | T46: =IFERROR(__xludf.DUMMYFUNCTION("IF(REGEXMATCH(N46, ""STATUS: Dev Complete - Awaiting QA""), ""Dev Complete - Awaiting QA"", IF(REGEXMATCH(N46, ""STATUS: Follow-Up Required""), ""Follow-Up Required"", IF(REGEXMATCH(N46, ""STATUS: In Progress""), ""In Progress"", IF(REGEXMATCH(N46, ""STAT"&"US: In QA""), ""In QA"", IF(REGEXMATCH(N46, ""STATUS: Needs Customer Feedback""), ""Needs Customer Feedback"", IF(REGEXMATCH(N46, ""STATUS: QA Passed - Awaiting Release""), ""QA Passed - Awaiting Release"", IF(REGEXMATCH(N46, ""STATUS: Release to Prod""),"&" ""Release to Prod"", """")))))))"),"")
A47: cloudwarriors-ai/zoom_presales_django | B47: ZoomWarriors v1 | C47: 385 | D47: Tool Tip - ZCC Page - Spell out # on Bubble | E47: closed | F47: 2025-06-25T21:03:24Z | G47: =IF(I47="", "", TEXT(DATEVALUE(LEFT(F47, 10)), "dd-mmm-yyyy")) -> 25-Jun-2025 | H47: rebecca-cichy | I47: 2025-07-11T20:59:52Z | J47: =IF(I47="", "", TEXT(DATEVALUE(LEFT(I47, 10)), "dd-mmm-yyyy")) -> 11-Jul-2025 | K47: 2025-06-25T21:04:20Z | L47: =IF(K47="", "", TEXT(DATEVALUE(LEFT(K47, 10)), "dd-mmm-yyyy")) -> 25-Jun-2025 | M47: Feature | N47: None | P47: 0 | Q47: https://github.com/cloudwarriors-ai/zoom_presales_django/issues/385 | R47: =IFERROR(__xludf.DUMMYFUNCTION("IF(REGEXMATCH(N47, ""PRIORITY: Low""), ""Low"", IF(REGEXMATCH(N47, ""PRIORITY: Medium""), ""Medium"", IF(REGEXMATCH(N47, ""PRIORITY: High""), ""High"", """"))) "),"") | S47: =IFERROR(__xludf.DUMMYFUNCTION("IF(REGEXMATCH(N47, ""SKILL: Low""), ""Low"", IF(REGEXMATCH(N47, ""SKILL: Medium""), ""Medium"", IF(REGEXMATCH(N47, ""SKILL: High""), ""High"", """")))"),"") | T47: =IFERROR(__xludf.DUMMYFUNCTION("IF(REGEXMATCH(N47, ""STATUS: Dev Complete - Awaiting QA""), ""Dev Complete - Awaiting QA"", IF(REGEXMATCH(N47, ""STATUS: Follow-Up Required""), ""Follow-Up Required"", IF(REGEXMATCH(N47, ""STATUS: In Progress""), ""In Progress"", IF(REGEXMATCH(N47, ""STAT"&"US: In QA""), ""In QA"", IF(REGEXMATCH(N47, ""STATUS: Needs Customer Feedback""), ""Needs Customer Feedback"", IF(REGEXMATCH(N47, ""STATUS: QA Passed - Awaiting Release""), ""QA Passed - Awaiting Release"", IF(REGEXMATCH(N47, ""STATUS: Release to Prod""),"&" ""Release to Prod"", """")))))))"),"")
A48: cloudwarriors-ai/zoom_presales_django | B48: ZoomWarriors v1 | C48: 384 | D48: Tool Tip Change - ZCC Page - # | E48: closed | F48: 2025-06-25T21:01:27Z | G48: =IF(I48="", "", TEXT(DATEVALUE(LEFT(F48, 10)), "dd-mmm-yyyy")) -> 25-Jun-2025 | H48: abbyrien | I48: 2025-09-26T14:48:15Z | J48: =IF(I48="", "", TEXT(DATEVALUE(LEFT(I48, 10)), "dd-mmm-yyyy")) -> 26-Sep-2025 | K48: 2025-06-26T12:05:01Z | L48: =IF(K48="", "", TEXT(DATEVALUE(LEFT(K48, 10)), "dd-mmm-yyyy")) -> 26-Jun-2025 | M48: Feature | N48: None | P48: 1 | Q48: https://github.com/cloudwarriors-ai/zoom_presales_django/issues/384 | R48: =IFERROR(__xludf.DUMMYFUNCTION("IF(REGEXMATCH(N48, ""PRIORITY: Low""), ""Low"", IF(REGEXMATCH(N48, ""PRIORITY: Medium""), ""Medium"", IF(REGEXMATCH(N48, ""PRIORITY: High""), ""High"", """"))) "),"") | S48: =IFERROR(__xludf.DUMMYFUNCTION("IF(REGEXMATCH(N48, ""SKILL: Low""), ""Low"", IF(REGEXMATCH(N48, ""SKILL: Medium""), ""Medium"", IF(REGEXMATCH(N48, ""SKILL: High""), ""High"", """")))"),"") | T48: =IFERROR(__xludf.DUMMYFUNCTION("IF(REGEXMATCH(N48, ""STATUS: Dev Complete - Awaiting QA""), ""Dev Complete - Awaiting QA"", IF(REGEXMATCH(N48, ""STATUS: Follow-Up Required""), ""Follow-Up Required"", IF(REGEXMATCH(N48, ""STATUS: In Progress""), ""In Progress"", IF(REGEXMATCH(N48, ""STAT"&"US: In QA""), ""In QA"", IF(REGEXMATCH(N48, ""STATUS: Needs Customer Feedback""), ""Needs Customer Feedback"", IF(REGEXMATCH(N48, ""STATUS: QA Passed - Awaiting Release""), ""QA Passed - Awaiting Release"", IF(REGEXMATCH(N48, ""STATUS: Release to Prod""),"&" ""Release to Prod"", """")))))))"),"")
A49: cloudwarriors-ai/zoom_presales_django | B49: ZoomWarriors v1 | C49: 383 | D49: Tool Tip Change - ZCC Page - Bubble Size | E49: closed | F49: 2025-06-25T20:58:34Z | G49: =IF(I49="", "", TEXT(DATEVALUE(LEFT(F49, 10)), "dd-mmm-yyyy")) -> 25-Jun-2025 | H49: abbyrien | I49: 2025-09-26T14:48:15Z | J49: =IF(I49="", "", TEXT(DATEVALUE(LEFT(I49, 10)), "dd-mmm-yyyy")) -> 26-Sep-2025 | K49: 2025-06-26T12:04:44Z | L49: =IF(K49="", "", TEXT(DATEVALUE(LEFT(K49, 10)), "dd-mmm-yyyy")) -> 26-Jun-2025 | M49: Feature | N49: None | P49: 1 | Q49: https://github.com/cloudwarriors-ai/zoom_presales_django/issues/383 | R49: =IFERROR(__xludf.DUMMYFUNCTION("IF(REGEXMATCH(N49, ""PRIORITY: Low""), ""Low"", IF(REGEXMATCH(N49, ""PRIORITY: Medium""), ""Medium"", IF(REGEXMATCH(N49, ""PRIORITY: High""), ""High"", """"))) "),"") | S49: =IFERROR(__xludf.DUMMYFUNCTION("IF(REGEXMATCH(N49, ""SKILL: Low""), ""Low"", IF(REGEXMATCH(N49, ""SKILL: Medium""), ""Medium"", IF(REGEXMATCH(N49, ""SKILL: High""), ""High"", """")))"),"") | T49: =IFERROR(__xludf.DUMMYFUNCTION("IF(REGEXMATCH(N49, ""STATUS: Dev Complete - Awaiting QA""), ""Dev Complete - Awaiting QA"", IF(REGEXMATCH(N49, ""STATUS: Follow-Up Required""), ""Follow-Up Required"", IF(REGEXMATCH(N49, ""STATUS: In Progress""), ""In Progress"", IF(REGEXMATCH(N49, ""STAT"&"US: In QA""), ""In QA"", IF(REGEXMATCH(N49, ""STATUS: Needs Customer Feedback""), ""Needs Customer Feedback"", IF(REGEXMATCH(N49, ""STATUS: QA Passed - Awaiting Release""), ""QA Passed - Awaiting Release"", IF(REGEXMATCH(N49, ""STATUS: Release to Prod""),"&" ""Release to Prod"", """")))))))"),"")
A50: cloudwarriors-ai/zoom_presales_django | B50: ZoomWarriors v1 | C50: 382 | D50: Tool Tip Change - ZCC Page | E50: closed | F50: 2025-06-25T20:56:58Z | G50: =IF(I50="", "", TEXT(DATEVALUE(LEFT(F50, 10)), "dd-mmm-yyyy")) -> 25-Jun-2025 | H50: abbyrien | I50: 2025-09-05T18:40:13Z | J50: =IF(I50="", "", TEXT(DATEVALUE(LEFT(I50, 10)), "dd-mmm-yyyy")) -> 05-Sep-2025 | K50: 2025-09-05T18:40:13Z | L50: =IF(K50="", "", TEXT(DATEVALUE(LEFT(K50, 10)), "dd-mmm-yyyy")) -> 05-Sep-2025 | M50: Feature | N50: PRIORITY: Low, SKILL: Low, STATUS: Released to Prod | O50: Matt-Keuning | P50: 2 | Q50: https://github.com/cloudwarriors-ai/zoom_presales_django/issues/382 | R50: =IFERROR(__xludf.DUMMYFUNCTION("IF(REGEXMATCH(N50, ""PRIORITY: Low""), ""Low"", IF(REGEXMATCH(N50, ""PRIORITY: Medium""), ""Medium"", IF(REGEXMATCH(N50, ""PRIORITY: High""), ""High"", """"))) "),"Low") -> Low | S50: =IFERROR(__xludf.DUMMYFUNCTION("IF(REGEXMATCH(N50, ""SKILL: Low""), ""Low"", IF(REGEXMATCH(N50, ""SKILL: Medium""), ""Medium"", IF(REGEXMATCH(N50, ""SKILL: High""), ""High"", """")))"),"Low") -> Low | T50: =IFERROR(__xludf.DUMMYFUNCTION("IF(REGEXMATCH(N50, ""STATUS: Dev Complete - Awaiting QA""), ""Dev Complete - Awaiting QA"", IF(REGEXMATCH(N50, ""STATUS: Follow-Up Required""), ""Follow-Up Required"", IF(REGEXMATCH(N50, ""STATUS: In Progress""), ""In Progress"", IF(REGEXMATCH(N50, ""STAT"&"US: In QA""), ""In QA"", IF(REGEXMATCH(N50, ""STATUS: Needs Customer Feedback""), ""Needs Customer Feedback"", IF(REGEXMATCH(N50, ""STATUS: QA Passed - Awaiting Release""), ""QA Passed - Awaiting Release"", IF(REGEXMATCH(N50, ""STATUS: Release to Prod""),"&" ""Release to Prod"", """")))))))"),"")
A51: cloudwarriors-ai/zoom_presales_django | B51: ZoomWarriors v1 | C51: 381 | D51: Zoom Contact Center Page- Delete Price on Bubble | E51: closed | F51: 2025-06-25T20:55:32Z | G51: =IF(I51="", "", TEXT(DATEVALUE(LEFT(F51, 10)), "dd-mmm-yyyy")) -> 25-Jun-2025 | H51: abbyrien | I51: 2025-09-26T14:48:14Z | J51: =IF(I51="", "", TEXT(DATEVALUE(LEFT(I51, 10)), "dd-mmm-yyyy")) -> 26-Sep-2025 | K51: 2025-06-25T21:06:43Z | L51: =IF(K51="", "", TEXT(DATEVALUE(LEFT(K51, 10)), "dd-mmm-yyyy")) -> 25-Jun-2025 | M51: Task | N51: None | P51: 0 | Q51: https://github.com/cloudwarriors-ai/zoom_presales_django/issues/381 | R51: =IFERROR(__xludf.DUMMYFUNCTION("IF(REGEXMATCH(N51, ""PRIORITY: Low""), ""Low"", IF(REGEXMATCH(N51, ""PRIORITY: Medium""), ""Medium"", IF(REGEXMATCH(N51, ""PRIORITY: High""), ""High"", """"))) "),"") | S51: =IFERROR(__xludf.DUMMYFUNCTION("IF(REGEXMATCH(N51, ""SKILL: Low""), ""Low"", IF(REGEXMATCH(N51, ""SKILL: Medium""), ""Medium"", IF(REGEXMATCH(N51, ""SKILL: High""), ""High"", """")))"),"") | T51: =IFERROR(__xludf.DUMMYFUNCTION("IF(REGEXMATCH(N51, ""STATUS: Dev Complete - Awaiting QA""), ""Dev Complete - Awaiting QA"", IF(REGEXMATCH(N51, ""STATUS: Follow-Up Required""), ""Follow-Up Required"", IF(REGEXMATCH(N51, ""STATUS: In Progress""), ""In Progress"", IF(REGEXMATCH(N51, ""STAT"&"US: In QA""), ""In QA"", IF(REGEXMATCH(N51, ""STATUS: Needs Customer Feedback""), ""Needs Customer Feedback"", IF(REGEXMATCH(N51, ""STATUS: QA Passed - Awaiting Release""), ""QA Passed - Awaiting Release"", IF(REGEXMATCH(N51, ""STATUS: Release to Prod""),"&" ""Release to Prod"", """")))))))"),"")
A52: cloudwarriors-ai/zoom_presales_django | B52: ZoomWarriors v1 | C52: 380 | D52: ZP & ZCC Custom Additions Page - SAML Format | E52: closed | F52: 2025-06-25T20:52:01Z | G52: =IF(I52="", "", TEXT(DATEVALUE(LEFT(F52, 10)), "dd-mmm-yyyy")) -> 25-Jun-2025 | H52: abbyrien | I52: 2025-09-05T18:40:03Z | J52: =IF(I52="", "", TEXT(DATEVALUE(LEFT(I52, 10)), "dd-mmm-yyyy")) -> 05-Sep-2025 | K52: 2025-09-05T18:40:03Z | L52: =IF(K52="", "", TEXT(DATEVALUE(LEFT(K52, 10)), "dd-mmm-yyyy")) -> 05-Sep-2025 | M52: Feature | N52: PRIORITY: Low, SKILL: Low, STATUS: Released to Prod | O52: Matt-Keuning | P52: 2 | Q52: https://github.com/cloudwarriors-ai/zoom_presales_django/issues/380 | R52: =IFERROR(__xludf.DUMMYFUNCTION("IF(REGEXMATCH(N52, ""PRIORITY: Low""), ""Low"", IF(REGEXMATCH(N52, ""PRIORITY: Medium""), ""Medium"", IF(REGEXMATCH(N52, ""PRIORITY: High""), ""High"", """"))) "),"Low") -> Low | S52: =IFERROR(__xludf.DUMMYFUNCTION("IF(REGEXMATCH(N52, ""SKILL: Low""), ""Low"", IF(REGEXMATCH(N52, ""SKILL: Medium""), ""Medium"", IF(REGEXMATCH(N52, ""SKILL: High""), ""High"", """")))"),"Low") -> Low | T52: =IFERROR(__xludf.DUMMYFUNCTION("IF(REGEXMATCH(N52, ""STATUS: Dev Complete - Awaiting QA""), ""Dev Complete - Awaiting QA"", IF(REGEXMATCH(N52, ""STATUS: Follow-Up Required""), ""Follow-Up Required"", IF(REGEXMATCH(N52, ""STATUS: In Progress""), ""In Progress"", IF(REGEXMATCH(N52, ""STAT"&"US: In QA""), ""In QA"", IF(REGEXMATCH(N52, ""STATUS: Needs Customer Feedback""), ""Needs Customer Feedback"", IF(REGEXMATCH(N52, ""STATUS: QA Passed - Awaiting Release""), ""QA Passed - Awaiting Release"", IF(REGEXMATCH(N52, ""STATUS: Release to Prod""),"&" ""Release to Prod"", """")))))))"),"")
A53: cloudwarriors-ai/zoom_presales_django | B53: ZoomWarriors v1 | C53: 379 | D53: Tool Tip Change - ZP & ZCC Custom Additions Page | E53: closed | F53: 2025-06-25T20:48:27Z | G53: =IF(I53="", "", TEXT(DATEVALUE(LEFT(F53, 10)), "dd-mmm-yyyy")) -> 25-Jun-2025 | H53: abbyrien | I53: 2025-09-26T14:48:14Z | J53: =IF(I53="", "", TEXT(DATEVALUE(LEFT(I53, 10)), "dd-mmm-yyyy")) -> 26-Sep-2025 | K53: 2025-07-14T19:55:42Z | L53: =IF(K53="", "", TEXT(DATEVALUE(LEFT(K53, 10)), "dd-mmm-yyyy")) -> 14-Jul-2025 | M53: Feature | N53: PRIORITY: Low, TYPE: Duplicate | P53: 1 | Q53: https://github.com/cloudwarriors-ai/zoom_presales_django/issues/379 | R53: =IFERROR(__xludf.DUMMYFUNCTION("IF(REGEXMATCH(N53, ""PRIORITY: Low""), ""Low"", IF(REGEXMATCH(N53, ""PRIORITY: Medium""), ""Medium"", IF(REGEXMATCH(N53, ""PRIORITY: High""), ""High"", """"))) "),"Low") -> Low | S53: =IFERROR(__xludf.DUMMYFUNCTION("IF(REGEXMATCH(N53, ""SKILL: Low""), ""Low"", IF(REGEXMATCH(N53, ""SKILL: Medium""), ""Medium"", IF(REGEXMATCH(N53, ""SKILL: High""), ""High"", """")))"),"") | T53: =IFERROR(__xludf.DUMMYFUNCTION("IF(REGEXMATCH(N53, ""STATUS: Dev Complete - Awaiting QA""), ""Dev Complete - Awaiting QA"", IF(REGEXMATCH(N53, ""STATUS: Follow-Up Required""), ""Follow-Up Required"", IF(REGEXMATCH(N53, ""STATUS: In Progress""), ""In Progress"", IF(REGEXMATCH(N53, ""STAT"&"US: In QA""), ""In QA"", IF(REGEXMATCH(N53, ""STATUS: Needs Customer Feedback""), ""Needs Customer Feedback"", IF(REGEXMATCH(N53, ""STATUS: QA Passed - Awaiting Release""), ""QA Passed - Awaiting Release"", IF(REGEXMATCH(N53, ""STATUS: Release to Prod""),"&" ""Release to Prod"", """")))))))"),"")
A54: cloudwarriors-ai/zoom_presales_django | B54: ZoomWarriors v1 | C54: 378 | D54: Zoom Phone & Contact Center Custom Additions Page- Delete Prices for CTI Integration | E54: closed | F54: 2025-06-25T20:43:46Z | G54: =IF(I54="", "", TEXT(DATEVALUE(LEFT(F54, 10)), "dd-mmm-yyyy")) -> 25-Jun-2025 | H54: abbyrien | I54: 2025-09-26T14:48:14Z | J54: =IF(I54="", "", TEXT(DATEVALUE(LEFT(I54, 10)), "dd-mmm-yyyy")) -> 26-Sep-2025 | K54: 2025-06-25T21:07:09Z | L54: =IF(K54="", "", TEXT(DATEVALUE(LEFT(K54, 10)), "dd-mmm-yyyy")) -> 25-Jun-2025 | M54: Task | N54: None | P54: 0 | Q54: https://github.com/cloudwarriors-ai/zoom_presales_django/issues/378 | R54: =IFERROR(__xludf.DUMMYFUNCTION("IF(REGEXMATCH(N54, ""PRIORITY: Low""), ""Low"", IF(REGEXMATCH(N54, ""PRIORITY: Medium""), ""Medium"", IF(REGEXMATCH(N54, ""PRIORITY: High""), ""High"", """"))) "),"") | S54: =IFERROR(__xludf.DUMMYFUNCTION("IF(REGEXMATCH(N54, ""SKILL: Low""), ""Low"", IF(REGEXMATCH(N54, ""SKILL: Medium""), ""Medium"", IF(REGEXMATCH(N54, ""SKILL: High""), ""High"", """")))"),"") | T54: =IFERROR(__xludf.DUMMYFUNCTION("IF(REGEXMATCH(N54, ""STATUS: Dev Complete - Awaiting QA""), ""Dev Complete - Awaiting QA"", IF(REGEXMATCH(N54, ""STATUS: Follow-Up Required""), ""Follow-Up Required"", IF(REGEXMATCH(N54, ""STATUS: In Progress""), ""In Progress"", IF(REGEXMATCH(N54, ""STAT"&"US: In QA""), ""In QA"", IF(REGEXMATCH(N54, ""STATUS: Needs Customer Feedback""), ""Needs Customer Feedback"", IF(REGEXMATCH(N54, ""STATUS: QA Passed - Awaiting Release""), ""QA Passed - Awaiting Release"", IF(REGEXMATCH(N54, ""STATUS: Release to Prod""),"&" ""Release to Prod"", """")))))))"),"")
A55: cloudwarriors-ai/zoom_presales_django | B55: ZoomWarriors v1 | C55: 377 | D55: Tool Tip Change - ZP SBC & PBX Page - PBX Explanation | E55: closed | F55: 2025-06-25T20:38:42Z | G55: =IF(I55="", "", TEXT(DATEVALUE(LEFT(F55, 10)), "dd-mmm-yyyy")) -> 25-Jun-2025 | H55: abbyrien | I55: 2025-09-26T14:48:13Z | J55: =IF(I55="", "", TEXT(DATEVALUE(LEFT(I55, 10)), "dd-mmm-yyyy")) -> 26-Sep-2025 | K55: 2025-06-26T12:04:27Z | L55: =IF(K55="", "", TEXT(DATEVALUE(LEFT(K55, 10)), "dd-mmm-yyyy")) -> 26-Jun-2025 | M55: Feature | N55: None | P55: 1 | Q55: https://github.com/cloudwarriors-ai/zoom_presales_django/issues/377 | R55: =IFERROR(__xludf.DUMMYFUNCTION("IF(REGEXMATCH(N55, ""PRIORITY: Low""), ""Low"", IF(REGEXMATCH(N55, ""PRIORITY: Medium""), ""Medium"", IF(REGEXMATCH(N55, ""PRIORITY: High""), ""High"", """"))) "),"") | S55: =IFERROR(__xludf.DUMMYFUNCTION("IF(REGEXMATCH(N55, ""SKILL: Low""), ""Low"", IF(REGEXMATCH(N55, ""SKILL: Medium""), ""Medium"", IF(REGEXMATCH(N55, ""SKILL: High""), ""High"", """")))"),"") | T55: =IFERROR(__xludf.DUMMYFUNCTION("IF(REGEXMATCH(N55, ""STATUS: Dev Complete - Awaiting QA""), ""Dev Complete - Awaiting QA"", IF(REGEXMATCH(N55, ""STATUS: Follow-Up Required""), ""Follow-Up Required"", IF(REGEXMATCH(N55, ""STATUS: In Progress""), ""In Progress"", IF(REGEXMATCH(N55, ""STAT"&"US: In QA""), ""In QA"", IF(REGEXMATCH(N55, ""STATUS: Needs Customer Feedback""), ""Needs Customer Feedback"", IF(REGEXMATCH(N55, ""STATUS: QA Passed - Awaiting Release""), ""QA Passed - Awaiting Release"", IF(REGEXMATCH(N55, ""STATUS: Release to Prod""),"&" ""Release to Prod"", """")))))))"),"")
A56: cloudwarriors-ai/zoom_presales_django | B56: ZoomWarriors v1 | C56: 376 | D56: ZP SBC & PBX Page - Adjust Page Structure To Toggle On/Off & Expansions | E56: closed | F56: 2025-06-25T20:36:51Z | G56: =IF(I56="", "", TEXT(DATEVALUE(LEFT(F56, 10)), "dd-mmm-yyyy")) -> 25-Jun-2025 | H56: abbyrien | I56: 2025-08-18T19:41:32Z | J56: =IF(I56="", "", TEXT(DATEVALUE(LEFT(I56, 10)), "dd-mmm-yyyy")) -> 18-Aug-2025 | K56: 2025-08-18T19:41:32Z | L56: =IF(K56="", "", TEXT(DATEVALUE(LEFT(K56, 10)), "dd-mmm-yyyy")) -> 18-Aug-2025 | M56: Feature | N56: PRIORITY: Medium, SKILL: Low, STATUS: Update in v2.0 | O56: jvitato1 | P56: 10 | Q56: https://github.com/cloudwarriors-ai/zoom_presales_django/issues/376 | R56: =IFERROR(__xludf.DUMMYFUNCTION("IF(REGEXMATCH(N56, ""PRIORITY: Low""), ""Low"", IF(REGEXMATCH(N56, ""PRIORITY: Medium""), ""Medium"", IF(REGEXMATCH(N56, ""PRIORITY: High""), ""High"", """"))) "),"Medium") -> Medium | S56: =IFERROR(__xludf.DUMMYFUNCTION("IF(REGEXMATCH(N56, ""SKILL: Low""), ""Low"", IF(REGEXMATCH(N56, ""SKILL: Medium""), ""Medium"", IF(REGEXMATCH(N56, ""SKILL: High""), ""High"", """")))"),"Low") -> Low | T56: =IFERROR(__xludf.DUMMYFUNCTION("IF(REGEXMATCH(N56, ""STATUS: Dev Complete - Awaiting QA""), ""Dev Complete - Awaiting QA"", IF(REGEXMATCH(N56, ""STATUS: Follow-Up Required""), ""Follow-Up Required"", IF(REGEXMATCH(N56, ""STATUS: In Progress""), ""In Progress"", IF(REGEXMATCH(N56, ""STAT"&"US: In QA""), ""In QA"", IF(REGEXMATCH(N56, ""STATUS: Needs Customer Feedback""), ""Needs Customer Feedback"", IF(REGEXMATCH(N56, ""STATUS: QA Passed - Awaiting Release""), ""QA Passed - Awaiting Release"", IF(REGEXMATCH(N56, ""STATUS: Release to Prod""),"&" ""Release to Prod"", """")))))))"),"")
A57: cloudwarriors-ai/zoom_presales_django | B57: ZoomWarriors v1 | C57: 375 | D57: Tool Tip Change - ZP SBC & PBX Page | E57: closed | F57: 2025-06-25T20:34:37Z | G57: =IF(I57="", "", TEXT(DATEVALUE(LEFT(F57, 10)), "dd-mmm-yyyy")) -> 25-Jun-2025 | H57: abbyrien | I57: 2025-09-05T18:39:53Z | J57: =IF(I57="", "", TEXT(DATEVALUE(LEFT(I57, 10)), "dd-mmm-yyyy")) -> 05-Sep-2025 | K57: 2025-09-05T18:39:53Z | L57: =IF(K57="", "", TEXT(DATEVALUE(LEFT(K57, 10)), "dd-mmm-yyyy")) -> 05-Sep-2025 | M57: Feature | N57: PRIORITY: Low, SKILL: Low, STATUS: Released to Prod | O57: Matt-Keuning | P57: 2 | Q57: https://github.com/cloudwarriors-ai/zoom_presales_django/issues/375 | R57: =IFERROR(__xludf.DUMMYFUNCTION("IF(REGEXMATCH(N57, ""PRIORITY: Low""), ""Low"", IF(REGEXMATCH(N57, ""PRIORITY: Medium""), ""Medium"", IF(REGEXMATCH(N57, ""PRIORITY: High""), ""High"", """"))) "),"Low") -> Low | S57: =IFERROR(__xludf.DUMMYFUNCTION("IF(REGEXMATCH(N57, ""SKILL: Low""), ""Low"", IF(REGEXMATCH(N57, ""SKILL: Medium""), ""Medium"", IF(REGEXMATCH(N57, ""SKILL: High""), ""High"", """")))"),"Low") -> Low | T57: =IFERROR(__xludf.DUMMYFUNCTION("IF(REGEXMATCH(N57, ""STATUS: Dev Complete - Awaiting QA""), ""Dev Complete - Awaiting QA"", IF(REGEXMATCH(N57, ""STATUS: Follow-Up Required""), ""Follow-Up Required"", IF(REGEXMATCH(N57, ""STATUS: In Progress""), ""In Progress"", IF(REGEXMATCH(N57, ""STAT"&"US: In QA""), ""In QA"", IF(REGEXMATCH(N57, ""STATUS: Needs Customer Feedback""), ""Needs Customer Feedback"", IF(REGEXMATCH(N57, ""STATUS: QA Passed - Awaiting Release""), ""QA Passed - Awaiting Release"", IF(REGEXMATCH(N57, ""STATUS: Release to Prod""),"&" ""Release to Prod"", """")))))))"),"")
A58: cloudwarriors-ai/zoom_presales_django | B58: ZoomWarriors v1 | C58: 374 | D58: ZP SBC & PBX Page - Does Not Save When You Review & Edit | E58: closed | F58: 2025-06-25T20:32:02Z | G58: =IF(I58="", "", TEXT(DATEVALUE(LEFT(F58, 10)), "dd-mmm-yyyy")) -> 25-Jun-2025 | H58: abbyrien | I58: 2025-08-22T00:38:44Z | J58: =IF(I58="", "", TEXT(DATEVALUE(LEFT(I58, 10)), "dd-mmm-yyyy")) -> 22-Aug-2025 | K58: 2025-08-11T20:33:33Z | L58: =IF(K58="", "", TEXT(DATEVALUE(LEFT(K58, 10)), "dd-mmm-yyyy")) -> 11-Aug-2025 | M58: Bug | N58: PRIORITY: High, SKILL: Medium, STATUS: Released to Prod | O58: campbellayers | P58: 8 | Q58: https://github.com/cloudwarriors-ai/zoom_presales_django/issues/374 | R58: =IFERROR(__xludf.DUMMYFUNCTION("IF(REGEXMATCH(N58, ""PRIORITY: Low""), ""Low"", IF(REGEXMATCH(N58, ""PRIORITY: Medium""), ""Medium"", IF(REGEXMATCH(N58, ""PRIORITY: High""), ""High"", """"))) "),"High") -> High | S58: =IFERROR(__xludf.DUMMYFUNCTION("IF(REGEXMATCH(N58, ""SKILL: Low""), ""Low"", IF(REGEXMATCH(N58, ""SKILL: Medium""), ""Medium"", IF(REGEXMATCH(N58, ""SKILL: High""), ""High"", """")))"),"Medium") -> Medium | T58: =IFERROR(__xludf.DUMMYFUNCTION("IF(REGEXMATCH(N58, ""STATUS: Dev Complete - Awaiting QA""), ""Dev Complete - Awaiting QA"", IF(REGEXMATCH(N58, ""STATUS: Follow-Up Required""), ""Follow-Up Required"", IF(REGEXMATCH(N58, ""STATUS: In Progress""), ""In Progress"", IF(REGEXMATCH(N58, ""STAT"&"US: In QA""), ""In QA"", IF(REGEXMATCH(N58, ""STATUS: Needs Customer Feedback""), ""Needs Customer Feedback"", IF(REGEXMATCH(N58, ""STATUS: QA Passed - Awaiting Release""), ""QA Passed - Awaiting Release"", IF(REGEXMATCH(N58, ""STATUS: Release to Prod""),"&" ""Release to Prod"", """")))))))"),"")
A59: cloudwarriors-ai/zoom_presales_django | B59: ZoomWarriors v1 | C59: 373 | D59: ZP Paging Hardware Page - Increase Font Size | E59: closed | F59: 2025-06-25T20:28:00Z | G59: =IF(I59="", "", TEXT(DATEVALUE(LEFT(F59, 10)), "dd-mmm-yyyy")) -> 25-Jun-2025 | H59: abbyrien | I59: 2025-09-26T14:48:13Z | J59: =IF(I59="", "", TEXT(DATEVALUE(LEFT(I59, 10)), "dd-mmm-yyyy")) -> 26-Sep-2025 | K59: 2025-07-15T17:06:54Z | L59: =IF(K59="", "", TEXT(DATEVALUE(LEFT(K59, 10)), "dd-mmm-yyyy")) -> 15-Jul-2025 | M59: Feature | N59: PRIORITY: Low, STATUS: Dev Complete - Awaiting QA | P59: 2 | Q59: https://github.com/cloudwarriors-ai/zoom_presales_django/issues/373 | R59: =IFERROR(__xludf.DUMMYFUNCTION("IF(REGEXMATCH(N59, ""PRIORITY: Low""), ""Low"", IF(REGEXMATCH(N59, ""PRIORITY: Medium""), ""Medium"", IF(REGEXMATCH(N59, ""PRIORITY: High""), ""High"", """"))) "),"Low") -> Low | S59: =IFERROR(__xludf.DUMMYFUNCTION("IF(REGEXMATCH(N59, ""SKILL: Low""), ""Low"", IF(REGEXMATCH(N59, ""SKILL: Medium""), ""Medium"", IF(REGEXMATCH(N59, ""SKILL: High""), ""High"", """")))"),"") | T59: =IFERROR(__xludf.DUMMYFUNCTION("IF(REGEXMATCH(N59, ""STATUS: Dev Complete - Awaiting QA""), ""Dev Complete - Awaiting QA"", IF(REGEXMATCH(N59, ""STATUS: Follow-Up Required""), ""Follow-Up Required"", IF(REGEXMATCH(N59, ""STATUS: In Progress""), ""In Progress"", IF(REGEXMATCH(N59, ""STAT"&"US: In QA""), ""In QA"", IF(REGEXMATCH(N59, ""STATUS: Needs Customer Feedback""), ""Needs Customer Feedback"", IF(REGEXMATCH(N59, ""STATUS: QA Passed - Awaiting Release""), ""QA Passed - Awaiting Release"", IF(REGEXMATCH(N59, ""STATUS: Release to Prod""),"&" ""Release to Prod"", """")))))))"),"Dev Complete - Awaiting QA") -> Dev Complete - Awaiting QA
A60: cloudwarriors-ai/zoom_presales_django | B60: ZoomWarriors v1 | C60: 372 | D60: Tool Tip Addition - ZP Features (ATA) Page | E60: closed | F60: 2025-06-25T20:25:54Z | G60: =IF(I60="", "", TEXT(DATEVALUE(LEFT(F60, 10)), "dd-mmm-yyyy")) -> 25-Jun-2025 | H60: abbyrien | I60: 2025-09-05T18:39:42Z | J60: =IF(I60="", "", TEXT(DATEVALUE(LEFT(I60, 10)), "dd-mmm-yyyy")) -> 05-Sep-2025 | K60: 2025-09-05T18:39:42Z | L60: =IF(K60="", "", TEXT(DATEVALUE(LEFT(K60, 10)), "dd-mmm-yyyy")) -> 05-Sep-2025 | M60: Feature | N60: PRIORITY: Low, SKILL: Low, STATUS: Released to Prod | O60: Matt-Keuning | P60: 3 | Q60: https://github.com/cloudwarriors-ai/zoom_presales_django/issues/372 | R60: =IFERROR(__xludf.DUMMYFUNCTION("IF(REGEXMATCH(N60, ""PRIORITY: Low""), ""Low"", IF(REGEXMATCH(N60, ""PRIORITY: Medium""), ""Medium"", IF(REGEXMATCH(N60, ""PRIORITY: High""), ""High"", """"))) "),"Low") -> Low | S60: =IFERROR(__xludf.DUMMYFUNCTION("IF(REGEXMATCH(N60, ""SKILL: Low""), ""Low"", IF(REGEXMATCH(N60, ""SKILL: Medium""), ""Medium"", IF(REGEXMATCH(N60, ""SKILL: High""), ""High"", """")))"),"Low") -> Low | T60: =IFERROR(__xludf.DUMMYFUNCTION("IF(REGEXMATCH(N60, ""STATUS: Dev Complete - Awaiting QA""), ""Dev Complete - Awaiting QA"", IF(REGEXMATCH(N60, ""STATUS: Follow-Up Required""), ""Follow-Up Required"", IF(REGEXMATCH(N60, ""STATUS: In Progress""), ""In Progress"", IF(REGEXMATCH(N60, ""STAT"&"US: In QA""), ""In QA"", IF(REGEXMATCH(N60, ""STATUS: Needs Customer Feedback""), ""Needs Customer Feedback"", IF(REGEXMATCH(N60, ""STATUS: QA Passed - Awaiting Release""), ""QA Passed - Awaiting Release"", IF(REGEXMATCH(N60, ""STATUS: Release to Prod""),"&" ""Release to Prod"", """")))))))"),"")
A61: cloudwarriors-ai/zoom_presales_django | B61: ZoomWarriors v1 | C61: 371 | D61: ZP Features Page - Format Change | E61: closed | F61: 2025-06-25T20:15:59Z | G61: =IF(I61="", "", TEXT(DATEVALUE(LEFT(F61, 10)), "dd-mmm-yyyy")) -> 25-Jun-2025 | H61: abbyrien | I61: 2025-09-26T14:48:12Z | J61: =IF(I61="", "", TEXT(DATEVALUE(LEFT(I61, 10)), "dd-mmm-yyyy")) -> 26-Sep-2025 | K61: 2025-06-27T19:39:59Z | L61: =IF(K61="", "", TEXT(DATEVALUE(LEFT(K61, 10)), "dd-mmm-yyyy")) -> 27-Jun-2025 | M61: Feature | N61: None | P61: 2 | Q61: https://github.com/cloudwarriors-ai/zoom_presales_django/issues/371 | R61: =IFERROR(__xludf.DUMMYFUNCTION("IF(REGEXMATCH(N61, ""PRIORITY: Low""), ""Low"", IF(REGEXMATCH(N61, ""PRIORITY: Medium""), ""Medium"", IF(REGEXMATCH(N61, ""PRIORITY: High""), ""High"", """"))) "),"") | S61: =IFERROR(__xludf.DUMMYFUNCTION("IF(REGEXMATCH(N61, ""SKILL: Low""), ""Low"", IF(REGEXMATCH(N61, ""SKILL: Medium""), ""Medium"", IF(REGEXMATCH(N61, ""SKILL: High""), ""High"", """")))"),"") | T61: =IFERROR(__xludf.DUMMYFUNCTION("IF(REGEXMATCH(N61, ""STATUS: Dev Complete - Awaiting QA""), ""Dev Complete - Awaiting QA"", IF(REGEXMATCH(N61, ""STATUS: Follow-Up Required""), ""Follow-Up Required"", IF(REGEXMATCH(N61, ""STATUS: In Progress""), ""In Progress"", IF(REGEXMATCH(N61, ""STAT"&"US: In QA""), ""In QA"", IF(REGEXMATCH(N61, ""STATUS: Needs Customer Feedback""), ""Needs Customer Feedback"", IF(REGEXMATCH(N61, ""STATUS: QA Passed - Awaiting Release""), ""QA Passed - Awaiting Release"", IF(REGEXMATCH(N61, ""STATUS: Release to Prod""),"&" ""Release to Prod"", """")))))))"),"")
A62: cloudwarriors-ai/zoom_presales_django | B62: ZoomWarriors v1 | C62: 370 | D62: ZP Locations Page - Format Change | E62: closed | F62: 2025-06-25T20:12:45Z | G62: =IF(I62="", "", TEXT(DATEVALUE(LEFT(F62, 10)), "dd-mmm-yyyy")) -> 25-Jun-2025 | H62: abbyrien | I62: 2025-09-26T14:48:12Z | J62: =IF(I62="", "", TEXT(DATEVALUE(LEFT(I62, 10)), "dd-mmm-yyyy")) -> 26-Sep-2025 | K62: 2025-07-15T17:41:49Z | L62: =IF(K62="", "", TEXT(DATEVALUE(LEFT(K62, 10)), "dd-mmm-yyyy")) -> 15-Jul-2025 | M62: Feature | N62: PRIORITY: Medium, STATUS: Dev Complete - Awaiting QA | P62: 2 | Q62: https://github.com/cloudwarriors-ai/zoom_presales_django/issues/370 | R62: =IFERROR(__xludf.DUMMYFUNCTION("IF(REGEXMATCH(N62, ""PRIORITY: Low""), ""Low"", IF(REGEXMATCH(N62, ""PRIORITY: Medium""), ""Medium"", IF(REGEXMATCH(N62, ""PRIORITY: High""), ""High"", """"))) "),"Medium") -> Medium | S62: =IFERROR(__xludf.DUMMYFUNCTION("IF(REGEXMATCH(N62, ""SKILL: Low""), ""Low"", IF(REGEXMATCH(N62, ""SKILL: Medium""), ""Medium"", IF(REGEXMATCH(N62, ""SKILL: High""), ""High"", """")))"),"") | T62: =IFERROR(__xludf.DUMMYFUNCTION("IF(REGEXMATCH(N62, ""STATUS: Dev Complete - Awaiting QA""), ""Dev Complete - Awaiting QA"", IF(REGEXMATCH(N62, ""STATUS: Follow-Up Required""), ""Follow-Up Required"", IF(REGEXMATCH(N62, ""STATUS: In Progress""), ""In Progress"", IF(REGEXMATCH(N62, ""STAT"&"US: In QA""), ""In QA"", IF(REGEXMATCH(N62, ""STATUS: Needs Customer Feedback""), ""Needs Customer Feedback"", IF(REGEXMATCH(N62, ""STATUS: QA Passed - Awaiting Release""), ""QA Passed - Awaiting Release"", IF(REGEXMATCH(N62, ""STATUS: Release to Prod""),"&" ""Release to Prod"", """")))))))"),"Dev Complete - Awaiting QA") -> Dev Complete - Awaiting QA
A63: cloudwarriors-ai/zoom_presales_django | B63: ZoomWarriors v1 | C63: 369 | D63: Tool Tip Change - ZP Locations Page | E63: closed | F63: 2025-06-25T20:03:24Z | G63: =IF(I63="", "", TEXT(DATEVALUE(LEFT(F63, 10)), "dd-mmm-yyyy")) -> 25-Jun-2025 | H63: abbyrien | I63: 2025-09-05T18:39:33Z | J63: =IF(I63="", "", TEXT(DATEVALUE(LEFT(I63, 10)), "dd-mmm-yyyy")) -> 05-Sep-2025 | K63: 2025-09-05T18:39:33Z | L63: =IF(K63="", "", TEXT(DATEVALUE(LEFT(K63, 10)), "dd-mmm-yyyy")) -> 05-Sep-2025 | M63: Feature | N63: PRIORITY: Low, SKILL: Low, STATUS: Released to Prod | O63: Matt-Keuning | P63: 5 | Q63: https://github.com/cloudwarriors-ai/zoom_presales_django/issues/369 | R63: =IFERROR(__xludf.DUMMYFUNCTION("IF(REGEXMATCH(N63, ""PRIORITY: Low""), ""Low"", IF(REGEXMATCH(N63, ""PRIORITY: Medium""), ""Medium"", IF(REGEXMATCH(N63, ""PRIORITY: High""), ""High"", """"))) "),"Low") -> Low | S63: =IFERROR(__xludf.DUMMYFUNCTION("IF(REGEXMATCH(N63, ""SKILL: Low""), ""Low"", IF(REGEXMATCH(N63, ""SKILL: Medium""), ""Medium"", IF(REGEXMATCH(N63, ""SKILL: High""), ""High"", """")))"),"Low") -> Low | T63: =IFERROR(__xludf.DUMMYFUNCTION("IF(REGEXMATCH(N63, ""STATUS: Dev Complete - Awaiting QA""), ""Dev Complete - Awaiting QA"", IF(REGEXMATCH(N63, ""STATUS: Follow-Up Required""), ""Follow-Up Required"", IF(REGEXMATCH(N63, ""STATUS: In Progress""), ""In Progress"", IF(REGEXMATCH(N63, ""STAT"&"US: In QA""), ""In QA"", IF(REGEXMATCH(N63, ""STATUS: Needs Customer Feedback""), ""Needs Customer Feedback"", IF(REGEXMATCH(N63, ""STATUS: QA Passed - Awaiting Release""), ""QA Passed - Awaiting Release"", IF(REGEXMATCH(N63, ""STATUS: Release to Prod""),"&" ""Release to Prod"", """")))))))"),"")
A64: cloudwarriors-ai/zoom_presales_django | B64: ZoomWarriors v1 | C64: 368 | D64: Zoom Page Locations Page- Delete Cost Bubble for E911 | E64: closed | F64: 2025-06-25T19:53:58Z | G64: =IF(I64="", "", TEXT(DATEVALUE(LEFT(F64, 10)), "dd-mmm-yyyy")) -> 25-Jun-2025 | H64: abbyrien | I64: 2025-09-26T14:48:12Z | J64: =IF(I64="", "", TEXT(DATEVALUE(LEFT(I64, 10)), "dd-mmm-yyyy")) -> 26-Sep-2025 | K64: 2025-06-25T21:14:44Z | L64: =IF(K64="", "", TEXT(DATEVALUE(LEFT(K64, 10)), "dd-mmm-yyyy")) -> 25-Jun-2025 | M64: Feature | N64: None | P64: 0 | Q64: https://github.com/cloudwarriors-ai/zoom_presales_django/issues/368 | R64: =IFERROR(__xludf.DUMMYFUNCTION("IF(REGEXMATCH(N64, ""PRIORITY: Low""), ""Low"", IF(REGEXMATCH(N64, ""PRIORITY: Medium""), ""Medium"", IF(REGEXMATCH(N64, ""PRIORITY: High""), ""High"", """"))) "),"") | S64: =IFERROR(__xludf.DUMMYFUNCTION("IF(REGEXMATCH(N64, ""SKILL: Low""), ""Low"", IF(REGEXMATCH(N64, ""SKILL: Medium""), ""Medium"", IF(REGEXMATCH(N64, ""SKILL: High""), ""High"", """")))"),"") | T64: =IFERROR(__xludf.DUMMYFUNCTION("IF(REGEXMATCH(N64, ""STATUS: Dev Complete - Awaiting QA""), ""Dev Complete - Awaiting QA"", IF(REGEXMATCH(N64, ""STATUS: Follow-Up Required""), ""Follow-Up Required"", IF(REGEXMATCH(N64, ""STATUS: In Progress""), ""In Progress"", IF(REGEXMATCH(N64, ""STAT"&"US: In QA""), ""In QA"", IF(REGEXMATCH(N64, ""STATUS: Needs Customer Feedback""), ""Needs Customer Feedback"", IF(REGEXMATCH(N64, ""STATUS: QA Passed - Awaiting Release""), ""QA Passed - Awaiting Release"", IF(REGEXMATCH(N64, ""STATUS: Release to Prod""),"&" ""Release to Prod"", """")))))))"),"")
A65: cloudwarriors-ai/zoom_presales_django | B65: ZoomWarriors v1 | C65: 367 | D65: ZP Locations Page- UI Enhancement for E911 Zone Field | E65: closed | F65: 2025-06-25T19:45:08Z | G65: =IF(I65="", "", TEXT(DATEVALUE(LEFT(F65, 10)), "dd-mmm-yyyy")) -> 25-Jun-2025 | H65: abbyrien | I65: 2025-09-26T14:48:11Z | J65: =IF(I65="", "", TEXT(DATEVALUE(LEFT(I65, 10)), "dd-mmm-yyyy")) -> 26-Sep-2025 | K65: 2025-07-15T17:44:35Z | L65: =IF(K65="", "", TEXT(DATEVALUE(LEFT(K65, 10)), "dd-mmm-yyyy")) -> 15-Jul-2025 | M65: Feature | N65: PRIORITY: Low, STATUS: Dev Complete - Awaiting QA | P65: 2 | Q65: https://github.com/cloudwarriors-ai/zoom_presales_django/issues/367 | R65: =IFERROR(__xludf.DUMMYFUNCTION("IF(REGEXMATCH(N65, ""PRIORITY: Low""), ""Low"", IF(REGEXMATCH(N65, ""PRIORITY: Medium""), ""Medium"", IF(REGEXMATCH(N65, ""PRIORITY: High""), ""High"", """"))) "),"Low") -> Low | S65: =IFERROR(__xludf.DUMMYFUNCTION("IF(REGEXMATCH(N65, ""SKILL: Low""), ""Low"", IF(REGEXMATCH(N65, ""SKILL: Medium""), ""Medium"", IF(REGEXMATCH(N65, ""SKILL: High""), ""High"", """")))"),"") | T65: =IFERROR(__xludf.DUMMYFUNCTION("IF(REGEXMATCH(N65, ""STATUS: Dev Complete - Awaiting QA""), ""Dev Complete - Awaiting QA"", IF(REGEXMATCH(N65, ""STATUS: Follow-Up Required""), ""Follow-Up Required"", IF(REGEXMATCH(N65, ""STATUS: In Progress""), ""In Progress"", IF(REGEXMATCH(N65, ""STAT"&"US: In QA""), ""In QA"", IF(REGEXMATCH(N65, ""STATUS: Needs Customer Feedback""), ""Needs Customer Feedback"", IF(REGEXMATCH(N65, ""STATUS: QA Passed - Awaiting Release""), ""QA Passed - Awaiting Release"", IF(REGEXMATCH(N65, ""STATUS: Release to Prod""),"&" ""Release to Prod"", """")))))))"),"Dev Complete - Awaiting QA") -> Dev Complete - Awaiting QA
A66: cloudwarriors-ai/zoom_presales_django | B66: ZoomWarriors v1 | C66: 366 | D66: Tool Tip Addition - ZP Locations Page - Small Site Explanation | E66: closed | F66: 2025-06-25T19:42:55Z | G66: =IF(I66="", "", TEXT(DATEVALUE(LEFT(F66, 10)), "dd-mmm-yyyy")) -> 25-Jun-2025 | H66: abbyrien | I66: 2025-08-28T19:17:33Z | J66: =IF(I66="", "", TEXT(DATEVALUE(LEFT(I66, 10)), "dd-mmm-yyyy")) -> 28-Aug-2025 | K66: 2025-08-28T19:17:33Z | L66: =IF(K66="", "", TEXT(DATEVALUE(LEFT(K66, 10)), "dd-mmm-yyyy")) -> 28-Aug-2025 | M66: Feature | N66: PRIORITY: Low, SKILL: Low, STATUS: QA Passed - Awaiting Release | O66: Matt-Keuning | P66: 3 | Q66: https://github.com/cloudwarriors-ai/zoom_presales_django/issues/366 | R66: =IFERROR(__xludf.DUMMYFUNCTION("IF(REGEXMATCH(N66, ""PRIORITY: Low""), ""Low"", IF(REGEXMATCH(N66, ""PRIORITY: Medium""), ""Medium"", IF(REGEXMATCH(N66, ""PRIORITY: High""), ""High"", """"))) "),"Low") -> Low | S66: =IFERROR(__xludf.DUMMYFUNCTION("IF(REGEXMATCH(N66, ""SKILL: Low""), ""Low"", IF(REGEXMATCH(N66, ""SKILL: Medium""), ""Medium"", IF(REGEXMATCH(N66, ""SKILL: High""), ""High"", """")))"),"Low") -> Low | T66: =IFERROR(__xludf.DUMMYFUNCTION("IF(REGEXMATCH(N66, ""STATUS: Dev Complete - Awaiting QA""), ""Dev Complete - Awaiting QA"", IF(REGEXMATCH(N66, ""STATUS: Follow-Up Required""), ""Follow-Up Required"", IF(REGEXMATCH(N66, ""STATUS: In Progress""), ""In Progress"", IF(REGEXMATCH(N66, ""STAT"&"US: In QA""), ""In QA"", IF(REGEXMATCH(N66, ""STATUS: Needs Customer Feedback""), ""Needs Customer Feedback"", IF(REGEXMATCH(N66, ""STATUS: QA Passed - Awaiting Release""), ""QA Passed - Awaiting Release"", IF(REGEXMATCH(N66, ""STATUS: Release to Prod""),"&" ""Release to Prod"", """")))))))"),"QA Passed - Awaiting Release") -> QA Passed - Awaiting Release
A67: cloudwarriors-ai/zoom_presales_django | B67: ZoomWarriors v1 | C67: 365 | D67: SOW Issue - "Training Session" Addition to ZP | E67: closed | F67: 2025-06-25T19:37:18Z | G67: =IF(I67="", "", TEXT(DATEVALUE(LEFT(F67, 10)), "dd-mmm-yyyy")) -> 25-Jun-2025 | H67: abbyrien | I67: 2025-09-26T14:48:11Z | J67: =IF(I67="", "", TEXT(DATEVALUE(LEFT(I67, 10)), "dd-mmm-yyyy")) -> 26-Sep-2025 | K67: 2025-06-27T19:42:59Z | L67: =IF(K67="", "", TEXT(DATEVALUE(LEFT(K67, 10)), "dd-mmm-yyyy")) -> 27-Jun-2025 | M67: Bug | N67: None | P67: 3 | Q67: https://github.com/cloudwarriors-ai/zoom_presales_django/issues/365 | R67: =IFERROR(__xludf.DUMMYFUNCTION("IF(REGEXMATCH(N67, ""PRIORITY: Low""), ""Low"", IF(REGEXMATCH(N67, ""PRIORITY: Medium""), ""Medium"", IF(REGEXMATCH(N67, ""PRIORITY: High""), ""High"", """"))) "),"") | S67: =IFERROR(__xludf.DUMMYFUNCTION("IF(REGEXMATCH(N67, ""SKILL: Low""), ""Low"", IF(REGEXMATCH(N67, ""SKILL: Medium""), ""Medium"", IF(REGEXMATCH(N67, ""SKILL: High""), ""High"", """")))"),"") | T67: =IFERROR(__xludf.DUMMYFUNCTION("IF(REGEXMATCH(N67, ""STATUS: Dev Complete - Awaiting QA""), ""Dev Complete - Awaiting QA"", IF(REGEXMATCH(N67, ""STATUS: Follow-Up Required""), ""Follow-Up Required"", IF(REGEXMATCH(N67, ""STATUS: In Progress""), ""In Progress"", IF(REGEXMATCH(N67, ""STAT"&"US: In QA""), ""In QA"", IF(REGEXMATCH(N67, ""STATUS: Needs Customer Feedback""), ""Needs Customer Feedback"", IF(REGEXMATCH(N67, ""STATUS: QA Passed - Awaiting Release""), ""QA Passed - Awaiting Release"", IF(REGEXMATCH(N67, ""STATUS: Release to Prod""),"&" ""Release to Prod"", """")))))))"),"")
A68: cloudwarriors-ai/zoom_presales_django | B68: ZoomWarriors v1 | C68: 364 | D68: ZP License Types Page - Spelling Error | E68: closed | F68: 2025-06-25T19:07:46Z | G68: =IF(I68="", "", TEXT(DATEVALUE(LEFT(F68, 10)), "dd-mmm-yyyy")) -> 25-Jun-2025 | H68: abbyrien | I68: 2025-08-28T19:17:33Z | J68: =IF(I68="", "", TEXT(DATEVALUE(LEFT(I68, 10)), "dd-mmm-yyyy")) -> 28-Aug-2025 | K68: 2025-08-28T19:17:33Z | L68: =IF(K68="", "", TEXT(DATEVALUE(LEFT(K68, 10)), "dd-mmm-yyyy")) -> 28-Aug-2025 | M68: Feature | N68: PRIORITY: Medium, SKILL: Low, STATUS: QA Passed - Awaiting Release | O68: Matt-Keuning | P68: 3 | Q68: https://github.com/cloudwarriors-ai/zoom_presales_django/issues/364 | R68: =IFERROR(__xludf.DUMMYFUNCTION("IF(REGEXMATCH(N68, ""PRIORITY: Low""), ""Low"", IF(REGEXMATCH(N68, ""PRIORITY: Medium""), ""Medium"", IF(REGEXMATCH(N68, ""PRIORITY: High""), ""High"", """"))) "),"Medium") -> Medium | S68: =IFERROR(__xludf.DUMMYFUNCTION("IF(REGEXMATCH(N68, ""SKILL: Low""), ""Low"", IF(REGEXMATCH(N68, ""SKILL: Medium""), ""Medium"", IF(REGEXMATCH(N68, ""SKILL: High""), ""High"", """")))"),"Low") -> Low | T68: =IFERROR(__xludf.DUMMYFUNCTION("IF(REGEXMATCH(N68, ""STATUS: Dev Complete - Awaiting QA""), ""Dev Complete - Awaiting QA"", IF(REGEXMATCH(N68, ""STATUS: Follow-Up Required""), ""Follow-Up Required"", IF(REGEXMATCH(N68, ""STATUS: In Progress""), ""In Progress"", IF(REGEXMATCH(N68, ""STAT"&"US: In QA""), ""In QA"", IF(REGEXMATCH(N68, ""STATUS: Needs Customer Feedback""), ""Needs Customer Feedback"", IF(REGEXMATCH(N68, ""STATUS: QA Passed - Awaiting Release""), ""QA Passed - Awaiting Release"", IF(REGEXMATCH(N68, ""STATUS: Release to Prod""),"&" ""Release to Prod"", """")))))))"),"QA Passed - Awaiting Release") -> QA Passed - Awaiting Release
A69: cloudwarriors-ai/zoom_presales_django | B69: ZoomWarriors v1 | C69: 363 | D69: Tool Tip Change - ZP License Page | E69: closed | F69: 2025-06-25T19:03:41Z | G69: =IF(I69="", "", TEXT(DATEVALUE(LEFT(F69, 10)), "dd-mmm-yyyy")) -> 25-Jun-2025 | H69: abbyrien | I69: 2025-08-28T19:17:34Z | J69: =IF(I69="", "", TEXT(DATEVALUE(LEFT(I69, 10)), "dd-mmm-yyyy")) -> 28-Aug-2025 | K69: 2025-08-28T19:17:34Z | L69: =IF(K69="", "", TEXT(DATEVALUE(LEFT(K69, 10)), "dd-mmm-yyyy")) -> 28-Aug-2025 | M69: Feature | N69: PRIORITY: Low, SKILL: Low, STATUS: QA Passed - Awaiting Release | O69: Matt-Keuning | P69: 1 | Q69: https://github.com/cloudwarriors-ai/zoom_presales_django/issues/363 | R69: =IFERROR(__xludf.DUMMYFUNCTION("IF(REGEXMATCH(N69, ""PRIORITY: Low""), ""Low"", IF(REGEXMATCH(N69, ""PRIORITY: Medium""), ""Medium"", IF(REGEXMATCH(N69, ""PRIORITY: High""), ""High"", """"))) "),"Low") -> Low | S69: =IFERROR(__xludf.DUMMYFUNCTION("IF(REGEXMATCH(N69, ""SKILL: Low""), ""Low"", IF(REGEXMATCH(N69, ""SKILL: Medium""), ""Medium"", IF(REGEXMATCH(N69, ""SKILL: High""), ""High"", """")))"),"Low") -> Low | T69: =IFERROR(__xludf.DUMMYFUNCTION("IF(REGEXMATCH(N69, ""STATUS: Dev Complete - Awaiting QA""), ""Dev Complete - Awaiting QA"", IF(REGEXMATCH(N69, ""STATUS: Follow-Up Required""), ""Follow-Up Required"", IF(REGEXMATCH(N69, ""STATUS: In Progress""), ""In Progress"", IF(REGEXMATCH(N69, ""STAT"&"US: In QA""), ""In QA"", IF(REGEXMATCH(N69, ""STATUS: Needs Customer Feedback""), ""Needs Customer Feedback"", IF(REGEXMATCH(N69, ""STATUS: QA Passed - Awaiting Release""), ""QA Passed - Awaiting Release"", IF(REGEXMATCH(N69, ""STATUS: Release to Prod""),"&" ""Release to Prod"", """")))))))"),"QA Passed - Awaiting Release") -> QA Passed - Awaiting Release
A70: cloudwarriors-ai/zoom_presales_django | B70: ZoomWarriors v1 | C70: 362 | D70: Tool Tip Change - Customer Information Page | E70: closed | F70: 2025-06-25T18:53:25Z | G70: =IF(I70="", "", TEXT(DATEVALUE(LEFT(F70, 10)), "dd-mmm-yyyy")) -> 25-Jun-2025 | H70: abbyrien | I70: 2025-08-06T18:30:10Z | J70: =IF(I70="", "", TEXT(DATEVALUE(LEFT(I70, 10)), "dd-mmm-yyyy")) -> 06-Aug-2025 | K70: 2025-08-06T18:30:10Z | L70: =IF(K70="", "", TEXT(DATEVALUE(LEFT(K70, 10)), "dd-mmm-yyyy")) -> 06-Aug-2025 | M70: Feature | N70: PRIORITY: Low, SKILL: Low, STATUS: Released to Prod | O70: Matt-Keuning | P70: 2 | Q70: https://github.com/cloudwarriors-ai/zoom_presales_django/issues/362 | R70: =IFERROR(__xludf.DUMMYFUNCTION("IF(REGEXMATCH(N70, ""PRIORITY: Low""), ""Low"", IF(REGEXMATCH(N70, ""PRIORITY: Medium""), ""Medium"", IF(REGEXMATCH(N70, ""PRIORITY: High""), ""High"", """"))) "),"Low") -> Low | S70: =IFERROR(__xludf.DUMMYFUNCTION("IF(REGEXMATCH(N70, ""SKILL: Low""), ""Low"", IF(REGEXMATCH(N70, ""SKILL: Medium""), ""Medium"", IF(REGEXMATCH(N70, ""SKILL: High""), ""High"", """")))"),"Low") -> Low | T70: =IFERROR(__xludf.DUMMYFUNCTION("IF(REGEXMATCH(N70, ""STATUS: Dev Complete - Awaiting QA""), ""Dev Complete - Awaiting QA"", IF(REGEXMATCH(N70, ""STATUS: Follow-Up Required""), ""Follow-Up Required"", IF(REGEXMATCH(N70, ""STATUS: In Progress""), ""In Progress"", IF(REGEXMATCH(N70, ""STAT"&"US: In QA""), ""In QA"", IF(REGEXMATCH(N70, ""STATUS: Needs Customer Feedback""), ""Needs Customer Feedback"", IF(REGEXMATCH(N70, ""STATUS: QA Passed - Awaiting Release""), ""QA Passed - Awaiting Release"", IF(REGEXMATCH(N70, ""STATUS: Release to Prod""),"&" ""Release to Prod"", """")))))))"),"")
A71: cloudwarriors-ai/zoom_presales_django | B71: ZoomWarriors v1 | C71: 361 | D71: Tool Tip Change - Customer Information Page - Diction Change | E71: closed | F71: 2025-06-25T18:49:33Z | G71: =IF(I71="", "", TEXT(DATEVALUE(LEFT(F71, 10)), "dd-mmm-yyyy")) -> 25-Jun-2025 | H71: abbyrien | I71: 2025-09-05T18:39:21Z | J71: =IF(I71="", "", TEXT(DATEVALUE(LEFT(I71, 10)), "dd-mmm-yyyy")) -> 05-Sep-2025 | K71: 2025-09-05T18:39:21Z | L71: =IF(K71="", "", TEXT(DATEVALUE(LEFT(K71, 10)), "dd-mmm-yyyy")) -> 05-Sep-2025 | M71: Feature | N71: PRIORITY: Low, SKILL: Low, STATUS: Released to Prod | O71: Matt-Keuning | P71: 3 | Q71: https://github.com/cloudwarriors-ai/zoom_presales_django/issues/361 | R71: =IFERROR(__xludf.DUMMYFUNCTION("IF(REGEXMATCH(N71, ""PRIORITY: Low""), ""Low"", IF(REGEXMATCH(N71, ""PRIORITY: Medium""), ""Medium"", IF(REGEXMATCH(N71, ""PRIORITY: High""), ""High"", """"))) "),"Low") -> Low | S71: =IFERROR(__xludf.DUMMYFUNCTION("IF(REGEXMATCH(N71, ""SKILL: Low""), ""Low"", IF(REGEXMATCH(N71, ""SKILL: Medium""), ""Medium"", IF(REGEXMATCH(N71, ""SKILL: High""), ""High"", """")))"),"Low") -> Low | T71: =IFERROR(__xludf.DUMMYFUNCTION("IF(REGEXMATCH(N71, ""STATUS: Dev Complete - Awaiting QA""), ""Dev Complete - Awaiting QA"", IF(REGEXMATCH(N71, ""STATUS: Follow-Up Required""), ""Follow-Up Required"", IF(REGEXMATCH(N71, ""STATUS: In Progress""), ""In Progress"", IF(REGEXMATCH(N71, ""STAT"&"US: In QA""), ""In QA"", IF(REGEXMATCH(N71, ""STATUS: Needs Customer Feedback""), ""Needs Customer Feedback"", IF(REGEXMATCH(N71, ""STATUS: QA Passed - Awaiting Release""), ""QA Passed - Awaiting Release"", IF(REGEXMATCH(N71, ""STATUS: Release to Prod""),"&" ""Release to Prod"", """")))))))"),"")
A72: cloudwarriors-ai/zoom_presales_django | B72: ZoomWarriors v1 | C72: 360 | D72: ZP & ZCC Custom Additions - Add Zoom Marketplace Hyperlink | E72: closed | F72: 2025-06-25T11:44:09Z | G72: =IF(I72="", "", TEXT(DATEVALUE(LEFT(F72, 10)), "dd-mmm-yyyy")) -> 25-Jun-2025 | H72: rebecca-cichy | I72: 2025-08-04T18:11:19Z | J72: =IF(I72="", "", TEXT(DATEVALUE(LEFT(I72, 10)), "dd-mmm-yyyy")) -> 04-Aug-2025 | K72: 2025-08-04T18:11:19Z | L72: =IF(K72="", "", TEXT(DATEVALUE(LEFT(K72, 10)), "dd-mmm-yyyy")) -> 04-Aug-2025 | M72: Feature | N72: PRIORITY: Low, SKILL: Low, STATUS: In Progress | O72: jvitato1 | P72: 1 | Q72: https://github.com/cloudwarriors-ai/zoom_presales_django/issues/360 | R72: =IFERROR(__xludf.DUMMYFUNCTION("IF(REGEXMATCH(N72, ""PRIORITY: Low""), ""Low"", IF(REGEXMATCH(N72, ""PRIORITY: Medium""), ""Medium"", IF(REGEXMATCH(N72, ""PRIORITY: High""), ""High"", """"))) "),"Low") -> Low | S72: =IFERROR(__xludf.DUMMYFUNCTION("IF(REGEXMATCH(N72, ""SKILL: Low""), ""Low"", IF(REGEXMATCH(N72, ""SKILL: Medium""), ""Medium"", IF(REGEXMATCH(N72, ""SKILL: High""), ""High"", """")))"),"Low") -> Low | T72: =IFERROR(__xludf.DUMMYFUNCTION("IF(REGEXMATCH(N72, ""STATUS: Dev Complete - Awaiting QA""), ""Dev Complete - Awaiting QA"", IF(REGEXMATCH(N72, ""STATUS: Follow-Up Required""), ""Follow-Up Required"", IF(REGEXMATCH(N72, ""STATUS: In Progress""), ""In Progress"", IF(REGEXMATCH(N72, ""STAT"&"US: In QA""), ""In QA"", IF(REGEXMATCH(N72, ""STATUS: Needs Customer Feedback""), ""Needs Customer Feedback"", IF(REGEXMATCH(N72, ""STATUS: QA Passed - Awaiting Release""), ""QA Passed - Awaiting Release"", IF(REGEXMATCH(N72, ""STATUS: Release to Prod""),"&" ""Release to Prod"", """")))))))"),"In Progress") -> In Progress
A73: cloudwarriors-ai/zoom_presales_django | B73: ZoomWarriors v1 | C73: 359 | D73: ZP SBC & PBX - Explain SBC like PBX | E73: closed | F73: 2025-06-25T11:42:19Z | G73: =IF(I73="", "", TEXT(DATEVALUE(LEFT(F73, 10)), "dd-mmm-yyyy")) -> 25-Jun-2025 | H73: rebecca-cichy | I73: 2025-08-06T19:07:05Z | J73: =IF(I73="", "", TEXT(DATEVALUE(LEFT(I73, 10)), "dd-mmm-yyyy")) -> 06-Aug-2025 | K73: 2025-08-06T19:07:05Z | L73: =IF(K73="", "", TEXT(DATEVALUE(LEFT(K73, 10)), "dd-mmm-yyyy")) -> 06-Aug-2025 | M73: Feature | N73: PRIORITY: Low, SKILL: Low, STATUS: In Progress | O73: jvitato1 | P73: 1 | Q73: https://github.com/cloudwarriors-ai/zoom_presales_django/issues/359 | R73: =IFERROR(__xludf.DUMMYFUNCTION("IF(REGEXMATCH(N73, ""PRIORITY: Low""), ""Low"", IF(REGEXMATCH(N73, ""PRIORITY: Medium""), ""Medium"", IF(REGEXMATCH(N73, ""PRIORITY: High""), ""High"", """"))) "),"Low") -> Low | S73: =IFERROR(__xludf.DUMMYFUNCTION("IF(REGEXMATCH(N73, ""SKILL: Low""), ""Low"", IF(REGEXMATCH(N73, ""SKILL: Medium""), ""Medium"", IF(REGEXMATCH(N73, ""SKILL: High""), ""High"", """")))"),"Low") -> Low | T73: =IFERROR(__xludf.DUMMYFUNCTION("IF(REGEXMATCH(N73, ""STATUS: Dev Complete - Awaiting QA""), ""Dev Complete - Awaiting QA"", IF(REGEXMATCH(N73, ""STATUS: Follow-Up Required""), ""Follow-Up Required"", IF(REGEXMATCH(N73, ""STATUS: In Progress""), ""In Progress"", IF(REGEXMATCH(N73, ""STAT"&"US: In QA""), ""In QA"", IF(REGEXMATCH(N73, ""STATUS: Needs Customer Feedback""), ""Needs Customer Feedback"", IF(REGEXMATCH(N73, ""STATUS: QA Passed - Awaiting Release""), ""QA Passed - Awaiting Release"", IF(REGEXMATCH(N73, ""STATUS: Release to Prod""),"&" ""Release to Prod"", """")))))))"),"In Progress") -> In Progress
A74: cloudwarriors-ai/zoom_presales_django | B74: ZoomWarriors v1 | C74: 358 | D74: ZP Hardware - Increase Text Size on this Page | E74: closed | F74: 2025-06-25T11:39:37Z | G74: =IF(I74="", "", TEXT(DATEVALUE(LEFT(F74, 10)), "dd-mmm-yyyy")) -> 25-Jun-2025 | H74: rebecca-cichy | I74: 2025-07-31T22:39:05Z | J74: =IF(I74="", "", TEXT(DATEVALUE(LEFT(I74, 10)), "dd-mmm-yyyy")) -> 31-Jul-2025 | K74: 2025-07-11T16:53:07Z | L74: =IF(K74="", "", TEXT(DATEVALUE(LEFT(K74, 10)), "dd-mmm-yyyy")) -> 11-Jul-2025 | M74: Feature | N74: None | O74: rebecca-cichy | P74: 3 | Q74: https://github.com/cloudwarriors-ai/zoom_presales_django/issues/358 | R74: =IFERROR(__xludf.DUMMYFUNCTION("IF(REGEXMATCH(N74, ""PRIORITY: Low""), ""Low"", IF(REGEXMATCH(N74, ""PRIORITY: Medium""), ""Medium"", IF(REGEXMATCH(N74, ""PRIORITY: High""), ""High"", """"))) "),"") | S74: =IFERROR(__xludf.DUMMYFUNCTION("IF(REGEXMATCH(N74, ""SKILL: Low""), ""Low"", IF(REGEXMATCH(N74, ""SKILL: Medium""), ""Medium"", IF(REGEXMATCH(N74, ""SKILL: High""), ""High"", """")))"),"") | T74: =IFERROR(__xludf.DUMMYFUNCTION("IF(REGEXMATCH(N74, ""STATUS: Dev Complete - Awaiting QA""), ""Dev Complete - Awaiting QA"", IF(REGEXMATCH(N74, ""STATUS: Follow-Up Required""), ""Follow-Up Required"", IF(REGEXMATCH(N74, ""STATUS: In Progress""), ""In Progress"", IF(REGEXMATCH(N74, ""STAT"&"US: In QA""), ""In QA"", IF(REGEXMATCH(N74, ""STATUS: Needs Customer Feedback""), ""Needs Customer Feedback"", IF(REGEXMATCH(N74, ""STATUS: QA Passed - Awaiting Release""), ""QA Passed - Awaiting Release"", IF(REGEXMATCH(N74, ""STATUS: Release to Prod""),"&" ""Release to Prod"", """")))))))"),"")
A75: cloudwarriors-ai/zoom_presales_django | B75: ZoomWarriors v1 | C75: 357 | D75: ZP Features Page - Spell out ATA | E75: closed | F75: 2025-06-25T11:37:34Z | G75: =IF(I75="", "", TEXT(DATEVALUE(LEFT(F75, 10)), "dd-mmm-yyyy")) -> 25-Jun-2025 | H75: rebecca-cichy | I75: 2025-09-05T18:39:10Z | J75: =IF(I75="", "", TEXT(DATEVALUE(LEFT(I75, 10)), "dd-mmm-yyyy")) -> 05-Sep-2025 | K75: 2025-09-05T18:39:10Z | L75: =IF(K75="", "", TEXT(DATEVALUE(LEFT(K75, 10)), "dd-mmm-yyyy")) -> 05-Sep-2025 | M75: Feature | N75: PRIORITY: Low, SKILL: Low, STATUS: Released to Prod | O75: Matt-Keuning | P75: 3 | Q75: https://github.com/cloudwarriors-ai/zoom_presales_django/issues/357 | R75: =IFERROR(__xludf.DUMMYFUNCTION("IF(REGEXMATCH(N75, ""PRIORITY: Low""), ""Low"", IF(REGEXMATCH(N75, ""PRIORITY: Medium""), ""Medium"", IF(REGEXMATCH(N75, ""PRIORITY: High""), ""High"", """"))) "),"Low") -> Low | S75: =IFERROR(__xludf.DUMMYFUNCTION("IF(REGEXMATCH(N75, ""SKILL: Low""), ""Low"", IF(REGEXMATCH(N75, ""SKILL: Medium""), ""Medium"", IF(REGEXMATCH(N75, ""SKILL: High""), ""High"", """")))"),"Low") -> Low | T75: =IFERROR(__xludf.DUMMYFUNCTION("IF(REGEXMATCH(N75, ""STATUS: Dev Complete - Awaiting QA""), ""Dev Complete - Awaiting QA"", IF(REGEXMATCH(N75, ""STATUS: Follow-Up Required""), ""Follow-Up Required"", IF(REGEXMATCH(N75, ""STATUS: In Progress""), ""In Progress"", IF(REGEXMATCH(N75, ""STAT"&"US: In QA""), ""In QA"", IF(REGEXMATCH(N75, ""STATUS: Needs Customer Feedback""), ""Needs Customer Feedback"", IF(REGEXMATCH(N75, ""STATUS: QA Passed - Awaiting Release""), ""QA Passed - Awaiting Release"", IF(REGEXMATCH(N75, ""STATUS: Release to Prod""),"&" ""Release to Prod"", """")))))))"),"")
A76: cloudwarriors-ai/zoom_presales_django | B76: ZoomWarriors v1 | C76: 356 | D76: Tool Tip Change - Remove Pricing $ | E76: closed | F76: 2025-06-25T11:29:22Z | G76: =IF(I76="", "", TEXT(DATEVALUE(LEFT(F76, 10)), "dd-mmm-yyyy")) -> 25-Jun-2025 | H76: rebecca-cichy | I76: 2025-09-26T14:48:10Z | J76: =IF(I76="", "", TEXT(DATEVALUE(LEFT(I76, 10)), "dd-mmm-yyyy")) -> 26-Sep-2025 | K76: 2025-06-30T07:22:24Z | L76: =IF(K76="", "", TEXT(DATEVALUE(LEFT(K76, 10)), "dd-mmm-yyyy")) -> 30-Jun-2025 | M76: Bug | N76: None | P76: 2 | Q76: https://github.com/cloudwarriors-ai/zoom_presales_django/issues/356 | R76: =IFERROR(__xludf.DUMMYFUNCTION("IF(REGEXMATCH(N76, ""PRIORITY: Low""), ""Low"", IF(REGEXMATCH(N76, ""PRIORITY: Medium""), ""Medium"", IF(REGEXMATCH(N76, ""PRIORITY: High""), ""High"", """"))) "),"") | S76: =IFERROR(__xludf.DUMMYFUNCTION("IF(REGEXMATCH(N76, ""SKILL: Low""), ""Low"", IF(REGEXMATCH(N76, ""SKILL: Medium""), ""Medium"", IF(REGEXMATCH(N76, ""SKILL: High""), ""High"", """")))"),"") | T76: =IFERROR(__xludf.DUMMYFUNCTION("IF(REGEXMATCH(N76, ""STATUS: Dev Complete - Awaiting QA""), ""Dev Complete - Awaiting QA"", IF(REGEXMATCH(N76, ""STATUS: Follow-Up Required""), ""Follow-Up Required"", IF(REGEXMATCH(N76, ""STATUS: In Progress""), ""In Progress"", IF(REGEXMATCH(N76, ""STAT"&"US: In QA""), ""In QA"", IF(REGEXMATCH(N76, ""STATUS: Needs Customer Feedback""), ""Needs Customer Feedback"", IF(REGEXMATCH(N76, ""STATUS: QA Passed - Awaiting Release""), ""QA Passed - Awaiting Release"", IF(REGEXMATCH(N76, ""STATUS: Release to Prod""),"&" ""Release to Prod"", """")))))))"),"")
A77: cloudwarriors-ai/zoom_presales_django | B77: ZoomWarriors v1 | C77: 355 | D77: Update / Train BOT Capability | E77: closed | F77: 2025-06-25T03:55:10Z | G77: =IF(I77="", "", TEXT(DATEVALUE(LEFT(F77, 10)), "dd-mmm-yyyy")) -> 25-Jun-2025 | H77: rebecca-cichy | I77: 2025-09-05T18:38:45Z | J77: =IF(I77="", "", TEXT(DATEVALUE(LEFT(I77, 10)), "dd-mmm-yyyy")) -> 05-Sep-2025 | K77: 2025-09-05T18:38:45Z | L77: =IF(K77="", "", TEXT(DATEVALUE(LEFT(K77, 10)), "dd-mmm-yyyy")) -> 05-Sep-2025 | M77: Bug | N77: PRIORITY: Low, SKILL: Medium, STATUS: Update in v2.0 | O77: Jeffrey-Searcy | P77: 1 | Q77: https://github.com/cloudwarriors-ai/zoom_presales_django/issues/355 | R77: =IFERROR(__xludf.DUMMYFUNCTION("IF(REGEXMATCH(N77, ""PRIORITY: Low""), ""Low"", IF(REGEXMATCH(N77, ""PRIORITY: Medium""), ""Medium"", IF(REGEXMATCH(N77, ""PRIORITY: High""), ""High"", """"))) "),"Low") -> Low | S77: =IFERROR(__xludf.DUMMYFUNCTION("IF(REGEXMATCH(N77, ""SKILL: Low""), ""Low"", IF(REGEXMATCH(N77, ""SKILL: Medium""), ""Medium"", IF(REGEXMATCH(N77, ""SKILL: High""), ""High"", """")))"),"Medium") -> Medium | T77: =IFERROR(__xludf.DUMMYFUNCTION("IF(REGEXMATCH(N77, ""STATUS: Dev Complete - Awaiting QA""), ""Dev Complete - Awaiting QA"", IF(REGEXMATCH(N77, ""STATUS: Follow-Up Required""), ""Follow-Up Required"", IF(REGEXMATCH(N77, ""STATUS: In Progress""), ""In Progress"", IF(REGEXMATCH(N77, ""STAT"&"US: In QA""), ""In QA"", IF(REGEXMATCH(N77, ""STATUS: Needs Customer Feedback""), ""Needs Customer Feedback"", IF(REGEXMATCH(N77, ""STATUS: QA Passed - Awaiting Release""), ""QA Passed - Awaiting Release"", IF(REGEXMATCH(N77, ""STATUS: Release to Prod""),"&" ""Release to Prod"", """")))))))"),"")
A78: cloudwarriors-ai/zoom_presales_django | B78: ZoomWarriors v1 | C78: 354 | D78: SOW Issue - Generate SOW # On Page 1 | E78: closed | F78: 2025-06-24T18:26:16Z | G78: =IF(I78="", "", TEXT(DATEVALUE(LEFT(F78, 10)), "dd-mmm-yyyy")) -> 24-Jun-2025 | H78: rebecca-cichy | I78: 2025-09-26T14:48:10Z | J78: =IF(I78="", "", TEXT(DATEVALUE(LEFT(I78, 10)), "dd-mmm-yyyy")) -> 26-Sep-2025 | K78: 2025-06-27T01:07:31Z | L78: =IF(K78="", "", TEXT(DATEVALUE(LEFT(K78, 10)), "dd-mmm-yyyy")) -> 27-Jun-2025 | M78: Feature | N78: None | P78: 1 | Q78: https://github.com/cloudwarriors-ai/zoom_presales_django/issues/354 | R78: =IFERROR(__xludf.DUMMYFUNCTION("IF(REGEXMATCH(N78, ""PRIORITY: Low""), ""Low"", IF(REGEXMATCH(N78, ""PRIORITY: Medium""), ""Medium"", IF(REGEXMATCH(N78, ""PRIORITY: High""), ""High"", """"))) "),"") | S78: =IFERROR(__xludf.DUMMYFUNCTION("IF(REGEXMATCH(N78, ""SKILL: Low""), ""Low"", IF(REGEXMATCH(N78, ""SKILL: Medium""), ""Medium"", IF(REGEXMATCH(N78, ""SKILL: High""), ""High"", """")))"),"") | T78: =IFERROR(__xludf.DUMMYFUNCTION("IF(REGEXMATCH(N78, ""STATUS: Dev Complete - Awaiting QA""), ""Dev Complete - Awaiting QA"", IF(REGEXMATCH(N78, ""STATUS: Follow-Up Required""), ""Follow-Up Required"", IF(REGEXMATCH(N78, ""STATUS: In Progress""), ""In Progress"", IF(REGEXMATCH(N78, ""STAT"&"US: In QA""), ""In QA"", IF(REGEXMATCH(N78, ""STATUS: Needs Customer Feedback""), ""Needs Customer Feedback"", IF(REGEXMATCH(N78, ""STATUS: QA Passed - Awaiting Release""), ""QA Passed - Awaiting Release"", IF(REGEXMATCH(N78, ""STATUS: Release to Prod""),"&" ""Release to Prod"", """")))))))"),"")
A79: cloudwarriors-ai/zoom_presales_django | B79: ZoomWarriors v1 | C79: 353 | D79: SOW Issue - Add Contact Info (Email) to Line - CW PSO Rep Name | E79: closed | F79: 2025-06-24T18:23:58Z | G79: =IF(I79="", "", TEXT(DATEVALUE(LEFT(F79, 10)), "dd-mmm-yyyy")) -> 24-Jun-2025 | H79: rebecca-cichy | I79: 2025-07-31T21:26:19Z | J79: =IF(I79="", "", TEXT(DATEVALUE(LEFT(I79, 10)), "dd-mmm-yyyy")) -> 31-Jul-2025 | K79: 2025-07-31T21:26:19Z | L79: =IF(K79="", "", TEXT(DATEVALUE(LEFT(K79, 10)), "dd-mmm-yyyy")) -> 31-Jul-2025 | M79: Feature | N79: PRIORITY: Medium, SKILL: Low, STATUS: Update in v2.0 | O79: Jeffrey-Searcy | P79: 1 | Q79: https://github.com/cloudwarriors-ai/zoom_presales_django/issues/353 | R79: =IFERROR(__xludf.DUMMYFUNCTION("IF(REGEXMATCH(N79, ""PRIORITY: Low""), ""Low"", IF(REGEXMATCH(N79, ""PRIORITY: Medium""), ""Medium"", IF(REGEXMATCH(N79, ""PRIORITY: High""), ""High"", """"))) "),"Medium") -> Medium | S79: =IFERROR(__xludf.DUMMYFUNCTION("IF(REGEXMATCH(N79, ""SKILL: Low""), ""Low"", IF(REGEXMATCH(N79, ""SKILL: Medium""), ""Medium"", IF(REGEXMATCH(N79, ""SKILL: High""), ""High"", """")))"),"Low") -> Low | T79: =IFERROR(__xludf.DUMMYFUNCTION("IF(REGEXMATCH(N79, ""STATUS: Dev Complete - Awaiting QA""), ""Dev Complete - Awaiting QA"", IF(REGEXMATCH(N79, ""STATUS: Follow-Up Required""), ""Follow-Up Required"", IF(REGEXMATCH(N79, ""STATUS: In Progress""), ""In Progress"", IF(REGEXMATCH(N79, ""STAT"&"US: In QA""), ""In QA"", IF(REGEXMATCH(N79, ""STATUS: Needs Customer Feedback""), ""Needs Customer Feedback"", IF(REGEXMATCH(N79, ""STATUS: QA Passed - Awaiting Release""), ""QA Passed - Awaiting Release"", IF(REGEXMATCH(N79, ""STATUS: Release to Prod""),"&" ""Release to Prod"", """")))))))"),"")
A80: cloudwarriors-ai/zoom_presales_django | B80: ZoomWarriors v1 | C80: 352 | D80: Pricing - ZP Locations Change Foreign Port Request from $500 to $1500 | E80: closed | F80: 2025-06-18T21:11:01Z | G80: =IF(I80="", "", TEXT(DATEVALUE(LEFT(F80, 10)), "dd-mmm-yyyy")) -> 18-Jun-2025 | H80: rebecca-cichy | I80: 2025-09-26T14:48:09Z | J80: =IF(I80="", "", TEXT(DATEVALUE(LEFT(I80, 10)), "dd-mmm-yyyy")) -> 26-Sep-2025 | K80: 2025-06-30T16:28:34Z | L80: =IF(K80="", "", TEXT(DATEVALUE(LEFT(K80, 10)), "dd-mmm-yyyy")) -> 30-Jun-2025 | M80: Task | N80: None | P80: 3 | Q80: https://github.com/cloudwarriors-ai/zoom_presales_django/issues/352 | R80: =IFERROR(__xludf.DUMMYFUNCTION("IF(REGEXMATCH(N80, ""PRIORITY: Low""), ""Low"", IF(REGEXMATCH(N80, ""PRIORITY: Medium""), ""Medium"", IF(REGEXMATCH(N80, ""PRIORITY: High""), ""High"", """"))) "),"") | S80: =IFERROR(__xludf.DUMMYFUNCTION("IF(REGEXMATCH(N80, ""SKILL: Low""), ""Low"", IF(REGEXMATCH(N80, ""SKILL: Medium""), ""Medium"", IF(REGEXMATCH(N80, ""SKILL: High""), ""High"", """")))"),"") | T80: =IFERROR(__xludf.DUMMYFUNCTION("IF(REGEXMATCH(N80, ""STATUS: Dev Complete - Awaiting QA""), ""Dev Complete - Awaiting QA"", IF(REGEXMATCH(N80, ""STATUS: Follow-Up Required""), ""Follow-Up Required"", IF(REGEXMATCH(N80, ""STATUS: In Progress""), ""In Progress"", IF(REGEXMATCH(N80, ""STAT"&"US: In QA""), ""In QA"", IF(REGEXMATCH(N80, ""STATUS: Needs Customer Feedback""), ""Needs Customer Feedback"", IF(REGEXMATCH(N80, ""STATUS: QA Passed - Awaiting Release""), ""QA Passed - Awaiting Release"", IF(REGEXMATCH(N80, ""STATUS: Release to Prod""),"&" ""Release to Prod"", """")))))))"),"")
A81: cloudwarriors-ai/zoom_presales_django | B81: ZoomWarriors v1 | C81: 351 | D81: ZP Features Page - Highlight 'TOTAL' before Auto Receptionist & Call Queue | E81: closed | F81: 2025-06-18T21:08:21Z | G81: =IF(I81="", "", TEXT(DATEVALUE(LEFT(F81, 10)), "dd-mmm-yyyy")) -> 18-Jun-2025 | H81: rebecca-cichy | I81: 2025-09-26T14:48:09Z | J81: =IF(I81="", "", TEXT(DATEVALUE(LEFT(I81, 10)), "dd-mmm-yyyy")) -> 26-Sep-2025 | K81: 2025-06-27T01:00:03Z | L81: =IF(K81="", "", TEXT(DATEVALUE(LEFT(K81, 10)), "dd-mmm-yyyy")) -> 27-Jun-2025 | M81: Task | N81: None | P81: 5 | Q81: https://github.com/cloudwarriors-ai/zoom_presales_django/issues/351 | R81: =IFERROR(__xludf.DUMMYFUNCTION("IF(REGEXMATCH(N81, ""PRIORITY: Low""), ""Low"", IF(REGEXMATCH(N81, ""PRIORITY: Medium""), ""Medium"", IF(REGEXMATCH(N81, ""PRIORITY: High""), ""High"", """"))) "),"") | S81: =IFERROR(__xludf.DUMMYFUNCTION("IF(REGEXMATCH(N81, ""SKILL: Low""), ""Low"", IF(REGEXMATCH(N81, ""SKILL: Medium""), ""Medium"", IF(REGEXMATCH(N81, ""SKILL: High""), ""High"", """")))"),"") | T81: =IFERROR(__xludf.DUMMYFUNCTION("IF(REGEXMATCH(N81, ""STATUS: Dev Complete - Awaiting QA""), ""Dev Complete - Awaiting QA"", IF(REGEXMATCH(N81, ""STATUS: Follow-Up Required""), ""Follow-Up Required"", IF(REGEXMATCH(N81, ""STATUS: In Progress""), ""In Progress"", IF(REGEXMATCH(N81, ""STAT"&"US: In QA""), ""In QA"", IF(REGEXMATCH(N81, ""STATUS: Needs Customer Feedback""), ""Needs Customer Feedback"", IF(REGEXMATCH(N81, ""STATUS: QA Passed - Awaiting Release""), ""QA Passed - Awaiting Release"", IF(REGEXMATCH(N81, ""STATUS: Release to Prod""),"&" ""Release to Prod"", """")))))))"),"")
A82: cloudwarriors-ai/zoom_presales_django | B82: ZoomWarriors v1 | C82: 350 | D82: ZCC Page - Form Validation for Instances & Agent/Supervisors | E82: closed | F82: 2025-06-18T19:58:27Z | G82: =IF(I82="", "", TEXT(DATEVALUE(LEFT(F82, 10)), "dd-mmm-yyyy")) -> 18-Jun-2025 | H82: rebecca-cichy | I82: 2025-07-31T22:39:05Z | J82: =IF(I82="", "", TEXT(DATEVALUE(LEFT(I82, 10)), "dd-mmm-yyyy")) -> 31-Jul-2025 | K82: 2025-07-11T17:02:21Z | L82: =IF(K82="", "", TEXT(DATEVALUE(LEFT(K82, 10)), "dd-mmm-yyyy")) -> 11-Jul-2025 | M82: Bug | N82: None | O82: rebecca-cichy | P82: 4 | Q82: https://github.com/cloudwarriors-ai/zoom_presales_django/issues/350 | R82: =IFERROR(__xludf.DUMMYFUNCTION("IF(REGEXMATCH(N82, ""PRIORITY: Low""), ""Low"", IF(REGEXMATCH(N82, ""PRIORITY: Medium""), ""Medium"", IF(REGEXMATCH(N82, ""PRIORITY: High""), ""High"", """"))) "),"") | S82: =IFERROR(__xludf.DUMMYFUNCTION("IF(REGEXMATCH(N82, ""SKILL: Low""), ""Low"", IF(REGEXMATCH(N82, ""SKILL: Medium""), ""Medium"", IF(REGEXMATCH(N82, ""SKILL: High""), ""High"", """")))"),"") | T82: =IFERROR(__xludf.DUMMYFUNCTION("IF(REGEXMATCH(N82, ""STATUS: Dev Complete - Awaiting QA""), ""Dev Complete - Awaiting QA"", IF(REGEXMATCH(N82, ""STATUS: Follow-Up Required""), ""Follow-Up Required"", IF(REGEXMATCH(N82, ""STATUS: In Progress""), ""In Progress"", IF(REGEXMATCH(N82, ""STAT"&"US: In QA""), ""In QA"", IF(REGEXMATCH(N82, ""STATUS: Needs Customer Feedback""), ""Needs Customer Feedback"", IF(REGEXMATCH(N82, ""STATUS: QA Passed - Awaiting Release""), ""QA Passed - Awaiting Release"", IF(REGEXMATCH(N82, ""STATUS: Release to Prod""),"&" ""Release to Prod"", """")))))))"),"")
A83: cloudwarriors-ai/zoom_presales_django | B83: ZoomWarriors v1 | C83: 349 | D83: ZP Location Page - Form Validation, Must include at least one Site | E83: closed | F83: 2025-06-18T19:56:58Z | G83: =IF(I83="", "", TEXT(DATEVALUE(LEFT(F83, 10)), "dd-mmm-yyyy")) -> 18-Jun-2025 | H83: rebecca-cichy | I83: 2025-07-31T22:39:05Z | J83: =IF(I83="", "", TEXT(DATEVALUE(LEFT(I83, 10)), "dd-mmm-yyyy")) -> 31-Jul-2025 | K83: 2025-07-11T17:04:42Z | L83: =IF(K83="", "", TEXT(DATEVALUE(LEFT(K83, 10)), "dd-mmm-yyyy")) -> 11-Jul-2025 | M83: Bug | N83: None | O83: rebecca-cichy | P83: 3 | Q83: https://github.com/cloudwarriors-ai/zoom_presales_django/issues/349 | R83: =IFERROR(__xludf.DUMMYFUNCTION("IF(REGEXMATCH(N83, ""PRIORITY: Low""), ""Low"", IF(REGEXMATCH(N83, ""PRIORITY: Medium""), ""Medium"", IF(REGEXMATCH(N83, ""PRIORITY: High""), ""High"", """"))) "),"") | S83: =IFERROR(__xludf.DUMMYFUNCTION("IF(REGEXMATCH(N83, ""SKILL: Low""), ""Low"", IF(REGEXMATCH(N83, ""SKILL: Medium""), ""Medium"", IF(REGEXMATCH(N83, ""SKILL: High""), ""High"", """")))"),"") | T83: =IFERROR(__xludf.DUMMYFUNCTION("IF(REGEXMATCH(N83, ""STATUS: Dev Complete - Awaiting QA""), ""Dev Complete - Awaiting QA"", IF(REGEXMATCH(N83, ""STATUS: Follow-Up Required""), ""Follow-Up Required"", IF(REGEXMATCH(N83, ""STATUS: In Progress""), ""In Progress"", IF(REGEXMATCH(N83, ""STAT"&"US: In QA""), ""In QA"", IF(REGEXMATCH(N83, ""STATUS: Needs Customer Feedback""), ""Needs Customer Feedback"", IF(REGEXMATCH(N83, ""STATUS: QA Passed - Awaiting Release""), ""QA Passed - Awaiting Release"", IF(REGEXMATCH(N83, ""STATUS: Release to Prod""),"&" ""Release to Prod"", """")))))))"),"")
A84: cloudwarriors-ai/zoom_presales_django | B84: ZoomWarriors v1 | C84: 348 | D84: Implement backend pricing breakdown | E84: closed | F84: 2025-06-18T17:24:34Z | G84: =IF(I84="", "", TEXT(DATEVALUE(LEFT(F84, 10)), "dd-mmm-yyyy")) -> 18-Jun-2025 | H84: Waterboy-TH | I84: 2025-07-31T22:39:04Z | J84: =IF(I84="", "", TEXT(DATEVALUE(LEFT(I84, 10)), "dd-mmm-yyyy")) -> 31-Jul-2025 | K84: 2025-06-24T15:25:26Z | L84: =IF(K84="", "", TEXT(DATEVALUE(LEFT(K84, 10)), "dd-mmm-yyyy")) -> 24-Jun-2025 | M84: Feature | N84: None | O84: rebecca-cichy, jvitato1 | P84: 3 | Q84: https://github.com/cloudwarriors-ai/zoom_presales_django/issues/348 | R84: =IFERROR(__xludf.DUMMYFUNCTION("IF(REGEXMATCH(N84, ""PRIORITY: Low""), ""Low"", IF(REGEXMATCH(N84, ""PRIORITY: Medium""), ""Medium"", IF(REGEXMATCH(N84, ""PRIORITY: High""), ""High"", """"))) "),"") | S84: =IFERROR(__xludf.DUMMYFUNCTION("IF(REGEXMATCH(N84, ""SKILL: Low""), ""Low"", IF(REGEXMATCH(N84, ""SKILL: Medium""), ""Medium"", IF(REGEXMATCH(N84, ""SKILL: High""), ""High"", """")))"),"") | T84: =IFERROR(__xludf.DUMMYFUNCTION("IF(REGEXMATCH(N84, ""STATUS: Dev Complete - Awaiting QA""), ""Dev Complete - Awaiting QA"", IF(REGEXMATCH(N84, ""STATUS: Follow-Up Required""), ""Follow-Up Required"", IF(REGEXMATCH(N84, ""STATUS: In Progress""), ""In Progress"", IF(REGEXMATCH(N84, ""STAT"&"US: In QA""), ""In QA"", IF(REGEXMATCH(N84, ""STATUS: Needs Customer Feedback""), ""Needs Customer Feedback"", IF(REGEXMATCH(N84, ""STATUS: QA Passed - Awaiting Release""), ""QA Passed - Awaiting Release"", IF(REGEXMATCH(N84, ""STATUS: Release to Prod""),"&" ""Release to Prod"", """")))))))"),"")
A85: cloudwarriors-ai/zoom_presales_django | B85: ZoomWarriors v1 | C85: 346 | D85: Remove Preview Quote Function | E85: closed | F85: 2025-06-13T21:48:37Z | G85: =IF(I85="", "", TEXT(DATEVALUE(LEFT(F85, 10)), "dd-mmm-yyyy")) -> 13-Jun-2025 | H85: rebecca-cichy | I85: 2025-07-31T22:39:04Z | J85: =IF(I85="", "", TEXT(DATEVALUE(LEFT(I85, 10)), "dd-mmm-yyyy")) -> 31-Jul-2025 | K85: 2025-06-24T15:28:08Z | L85: =IF(K85="", "", TEXT(DATEVALUE(LEFT(K85, 10)), "dd-mmm-yyyy")) -> 24-Jun-2025 | M85: Bug | N85: None | O85: rebecca-cichy | P85: 4 | Q85: https://github.com/cloudwarriors-ai/zoom_presales_django/issues/346 | R85: =IFERROR(__xludf.DUMMYFUNCTION("IF(REGEXMATCH(N85, ""PRIORITY: Low""), ""Low"", IF(REGEXMATCH(N85, ""PRIORITY: Medium""), ""Medium"", IF(REGEXMATCH(N85, ""PRIORITY: High""), ""High"", """"))) "),"") | S85: =IFERROR(__xludf.DUMMYFUNCTION("IF(REGEXMATCH(N85, ""SKILL: Low""), ""Low"", IF(REGEXMATCH(N85, ""SKILL: Medium""), ""Medium"", IF(REGEXMATCH(N85, ""SKILL: High""), ""High"", """")))"),"") | T85: =IFERROR(__xludf.DUMMYFUNCTION("IF(REGEXMATCH(N85, ""STATUS: Dev Complete - Awaiting QA""), ""Dev Complete - Awaiting QA"", IF(REGEXMATCH(N85, ""STATUS: Follow-Up Required""), ""Follow-Up Required"", IF(REGEXMATCH(N85, ""STATUS: In Progress""), ""In Progress"", IF(REGEXMATCH(N85, ""STAT"&"US: In QA""), ""In QA"", IF(REGEXMATCH(N85, ""STATUS: Needs Customer Feedback""), ""Needs Customer Feedback"", IF(REGEXMATCH(N85, ""STATUS: QA Passed - Awaiting Release""), ""QA Passed - Awaiting Release"", IF(REGEXMATCH(N85, ""STATUS: Release to Prod""),"&" ""Release to Prod"", """")))))))"),"")
A86: cloudwarriors-ai/zoom_presales_django | B86: ZoomWarriors v1 | C86: 345 | D86: SOW Issue - ZP Locations Page - Extra E911 Zones Not Included in SOW | E86: closed | F86: 2025-06-13T17:57:54Z | G86: =IF(I86="", "", TEXT(DATEVALUE(LEFT(F86, 10)), "dd-mmm-yyyy")) -> 13-Jun-2025 | H86: rebecca-cichy | I86: 2025-07-31T22:39:04Z | J86: =IF(I86="", "", TEXT(DATEVALUE(LEFT(I86, 10)), "dd-mmm-yyyy")) -> 31-Jul-2025 | K86: 2025-07-11T17:10:51Z | L86: =IF(K86="", "", TEXT(DATEVALUE(LEFT(K86, 10)), "dd-mmm-yyyy")) -> 11-Jul-2025 | M86: Bug | N86: None | P86: 6 | Q86: https://github.com/cloudwarriors-ai/zoom_presales_django/issues/345 | R86: =IFERROR(__xludf.DUMMYFUNCTION("IF(REGEXMATCH(N86, ""PRIORITY: Low""), ""Low"", IF(REGEXMATCH(N86, ""PRIORITY: Medium""), ""Medium"", IF(REGEXMATCH(N86, ""PRIORITY: High""), ""High"", """"))) "),"") | S86: =IFERROR(__xludf.DUMMYFUNCTION("IF(REGEXMATCH(N86, ""SKILL: Low""), ""Low"", IF(REGEXMATCH(N86, ""SKILL: Medium""), ""Medium"", IF(REGEXMATCH(N86, ""SKILL: High""), ""High"", """")))"),"") | T86: =IFERROR(__xludf.DUMMYFUNCTION("IF(REGEXMATCH(N86, ""STATUS: Dev Complete - Awaiting QA""), ""Dev Complete - Awaiting QA"", IF(REGEXMATCH(N86, ""STATUS: Follow-Up Required""), ""Follow-Up Required"", IF(REGEXMATCH(N86, ""STATUS: In Progress""), ""In Progress"", IF(REGEXMATCH(N86, ""STAT"&"US: In QA""), ""In QA"", IF(REGEXMATCH(N86, ""STATUS: Needs Customer Feedback""), ""Needs Customer Feedback"", IF(REGEXMATCH(N86, ""STATUS: QA Passed - Awaiting Release""), ""QA Passed - Awaiting Release"", IF(REGEXMATCH(N86, ""STATUS: Release to Prod""),"&" ""Release to Prod"", """")))))))"),"")
A87: cloudwarriors-ai/zoom_presales_django | B87: ZoomWarriors v1 | C87: 344 | D87: Add Preview Page Button | E87: closed | F87: 2025-06-13T16:47:54Z | G87: =IF(I87="", "", TEXT(DATEVALUE(LEFT(F87, 10)), "dd-mmm-yyyy")) -> 13-Jun-2025 | H87: rebecca-cichy | I87: 2025-09-26T14:48:08Z | J87: =IF(I87="", "", TEXT(DATEVALUE(LEFT(I87, 10)), "dd-mmm-yyyy")) -> 26-Sep-2025 | K87: 2025-06-18T21:15:46Z | L87: =IF(K87="", "", TEXT(DATEVALUE(LEFT(K87, 10)), "dd-mmm-yyyy")) -> 18-Jun-2025 | M87: Feature | N87: None | P87: 1 | Q87: https://github.com/cloudwarriors-ai/zoom_presales_django/issues/344 | R87: =IFERROR(__xludf.DUMMYFUNCTION("IF(REGEXMATCH(N87, ""PRIORITY: Low""), ""Low"", IF(REGEXMATCH(N87, ""PRIORITY: Medium""), ""Medium"", IF(REGEXMATCH(N87, ""PRIORITY: High""), ""High"", """"))) "),"") | S87: =IFERROR(__xludf.DUMMYFUNCTION("IF(REGEXMATCH(N87, ""SKILL: Low""), ""Low"", IF(REGEXMATCH(N87, ""SKILL: Medium""), ""Medium"", IF(REGEXMATCH(N87, ""SKILL: High""), ""High"", """")))"),"") | T87: =IFERROR(__xludf.DUMMYFUNCTION("IF(REGEXMATCH(N87, ""STATUS: Dev Complete - Awaiting QA""), ""Dev Complete - Awaiting QA"", IF(REGEXMATCH(N87, ""STATUS: Follow-Up Required""), ""Follow-Up Required"", IF(REGEXMATCH(N87, ""STATUS: In Progress""), ""In Progress"", IF(REGEXMATCH(N87, ""STAT"&"US: In QA""), ""In QA"", IF(REGEXMATCH(N87, ""STATUS: Needs Customer Feedback""), ""Needs Customer Feedback"", IF(REGEXMATCH(N87, ""STATUS: QA Passed - Awaiting Release""), ""QA Passed - Awaiting Release"", IF(REGEXMATCH(N87, ""STATUS: Release to Prod""),"&" ""Release to Prod"", """")))))))"),"")
A88: cloudwarriors-ai/zoom_presales_django | B88: ZoomWarriors v1 | C88: 342 | D88: Pricing - ZCC Logic Impacted when changing the # of Agents & Supervisors | E88: closed | F88: 2025-06-12T21:15:08Z | G88: =IF(I88="", "", TEXT(DATEVALUE(LEFT(F88, 10)), "dd-mmm-yyyy")) -> 12-Jun-2025 | H88: rebecca-cichy | I88: 2025-09-26T14:48:07Z | J88: =IF(I88="", "", TEXT(DATEVALUE(LEFT(I88, 10)), "dd-mmm-yyyy")) -> 26-Sep-2025 | K88: 2025-06-30T16:29:27Z | L88: =IF(K88="", "", TEXT(DATEVALUE(LEFT(K88, 10)), "dd-mmm-yyyy")) -> 30-Jun-2025 | M88: Bug | N88: None | P88: 5 | Q88: https://github.com/cloudwarriors-ai/zoom_presales_django/issues/342 | R88: =IFERROR(__xludf.DUMMYFUNCTION("IF(REGEXMATCH(N88, ""PRIORITY: Low""), ""Low"", IF(REGEXMATCH(N88, ""PRIORITY: Medium""), ""Medium"", IF(REGEXMATCH(N88, ""PRIORITY: High""), ""High"", """"))) "),"") | S88: =IFERROR(__xludf.DUMMYFUNCTION("IF(REGEXMATCH(N88, ""SKILL: Low""), ""Low"", IF(REGEXMATCH(N88, ""SKILL: Medium""), ""Medium"", IF(REGEXMATCH(N88, ""SKILL: High""), ""High"", """")))"),"") | T88: =IFERROR(__xludf.DUMMYFUNCTION("IF(REGEXMATCH(N88, ""STATUS: Dev Complete - Awaiting QA""), ""Dev Complete - Awaiting QA"", IF(REGEXMATCH(N88, ""STATUS: Follow-Up Required""), ""Follow-Up Required"", IF(REGEXMATCH(N88, ""STATUS: In Progress""), ""In Progress"", IF(REGEXMATCH(N88, ""STAT"&"US: In QA""), ""In QA"", IF(REGEXMATCH(N88, ""STATUS: Needs Customer Feedback""), ""Needs Customer Feedback"", IF(REGEXMATCH(N88, ""STATUS: QA Passed - Awaiting Release""), ""QA Passed - Awaiting Release"", IF(REGEXMATCH(N88, ""STATUS: Release to Prod""),"&" ""Release to Prod"", """")))))))"),"")
A89: cloudwarriors-ai/zoom_presales_django | B89: ZoomWarriors v1 | C89: 341 | D89: Create QA Account for Testing | E89: closed | F89: 2025-06-11T19:27:16Z | G89: =IF(I89="", "", TEXT(DATEVALUE(LEFT(F89, 10)), "dd-mmm-yyyy")) -> 11-Jun-2025 | H89: rebecca-cichy | I89: 2025-09-26T14:48:07Z | J89: =IF(I89="", "", TEXT(DATEVALUE(LEFT(I89, 10)), "dd-mmm-yyyy")) -> 26-Sep-2025 | K89: 2025-06-11T20:17:29Z | L89: =IF(K89="", "", TEXT(DATEVALUE(LEFT(K89, 10)), "dd-mmm-yyyy")) -> 11-Jun-2025 | M89: Feature | N89: None | P89: 1 | Q89: https://github.com/cloudwarriors-ai/zoom_presales_django/issues/341 | R89: =IFERROR(__xludf.DUMMYFUNCTION("IF(REGEXMATCH(N89, ""PRIORITY: Low""), ""Low"", IF(REGEXMATCH(N89, ""PRIORITY: Medium""), ""Medium"", IF(REGEXMATCH(N89, ""PRIORITY: High""), ""High"", """"))) "),"") | S89: =IFERROR(__xludf.DUMMYFUNCTION("IF(REGEXMATCH(N89, ""SKILL: Low""), ""Low"", IF(REGEXMATCH(N89, ""SKILL: Medium""), ""Medium"", IF(REGEXMATCH(N89, ""SKILL: High""), ""High"", """")))"),"") | T89: =IFERROR(__xludf.DUMMYFUNCTION("IF(REGEXMATCH(N89, ""STATUS: Dev Complete - Awaiting QA""), ""Dev Complete - Awaiting QA"", IF(REGEXMATCH(N89, ""STATUS: Follow-Up Required""), ""Follow-Up Required"", IF(REGEXMATCH(N89, ""STATUS: In Progress""), ""In Progress"", IF(REGEXMATCH(N89, ""STAT"&"US: In QA""), ""In QA"", IF(REGEXMATCH(N89, ""STATUS: Needs Customer Feedback""), ""Needs Customer Feedback"", IF(REGEXMATCH(N89, ""STATUS: QA Passed - Awaiting Release""), ""QA Passed - Awaiting Release"", IF(REGEXMATCH(N89, ""STATUS: Release to Prod""),"&" ""Release to Prod"", """")))))))"),"")
A90: cloudwarriors-ai/zoom_presales_django | B90: ZoomWarriors v1 | C90: 340 | D90: ZP License Type Page - Ability to Add Negative License Qty | E90: closed | F90: 2025-06-10T21:19:05Z | G90: =IF(I90="", "", TEXT(DATEVALUE(LEFT(F90, 10)), "dd-mmm-yyyy")) -> 10-Jun-2025 | H90: jvitato1 | I90: 2025-09-26T14:48:07Z | J90: =IF(I90="", "", TEXT(DATEVALUE(LEFT(I90, 10)), "dd-mmm-yyyy")) -> 26-Sep-2025 | K90: 2025-06-30T07:29:59Z | L90: =IF(K90="", "", TEXT(DATEVALUE(LEFT(K90, 10)), "dd-mmm-yyyy")) -> 30-Jun-2025 | M90: Bug | N90: None | P90: 4 | Q90: https://github.com/cloudwarriors-ai/zoom_presales_django/issues/340 | R90: =IFERROR(__xludf.DUMMYFUNCTION("IF(REGEXMATCH(N90, ""PRIORITY: Low""), ""Low"", IF(REGEXMATCH(N90, ""PRIORITY: Medium""), ""Medium"", IF(REGEXMATCH(N90, ""PRIORITY: High""), ""High"", """"))) "),"") | S90: =IFERROR(__xludf.DUMMYFUNCTION("IF(REGEXMATCH(N90, ""SKILL: Low""), ""Low"", IF(REGEXMATCH(N90, ""SKILL: Medium""), ""Medium"", IF(REGEXMATCH(N90, ""SKILL: High""), ""High"", """")))"),"") | T90: =IFERROR(__xludf.DUMMYFUNCTION("IF(REGEXMATCH(N90, ""STATUS: Dev Complete - Awaiting QA""), ""Dev Complete - Awaiting QA"", IF(REGEXMATCH(N90, ""STATUS: Follow-Up Required""), ""Follow-Up Required"", IF(REGEXMATCH(N90, ""STATUS: In Progress""), ""In Progress"", IF(REGEXMATCH(N90, ""STAT"&"US: In QA""), ""In QA"", IF(REGEXMATCH(N90, ""STATUS: Needs Customer Feedback""), ""Needs Customer Feedback"", IF(REGEXMATCH(N90, ""STATUS: QA Passed - Awaiting Release""), ""QA Passed - Awaiting Release"", IF(REGEXMATCH(N90, ""STATUS: Release to Prod""),"&" ""Release to Prod"", """")))))))"),"")
A91: cloudwarriors-ai/zoom_presales_django | B91: ZoomWarriors v1 | C91: 339 | D91: Pricing - ZP Quote Minimum Cost Logic | E91: closed | F91: 2025-06-10T20:33:01Z | G91: =IF(I91="", "", TEXT(DATEVALUE(LEFT(F91, 10)), "dd-mmm-yyyy")) -> 10-Jun-2025 | H91: rebecca-cichy | I91: 2025-09-26T14:48:06Z | J91: =IF(I91="", "", TEXT(DATEVALUE(LEFT(I91, 10)), "dd-mmm-yyyy")) -> 26-Sep-2025 | K91: 2025-06-30T07:31:02Z | L91: =IF(K91="", "", TEXT(DATEVALUE(LEFT(K91, 10)), "dd-mmm-yyyy")) -> 30-Jun-2025 | M91: Bug | N91: None | P91: 6 | Q91: https://github.com/cloudwarriors-ai/zoom_presales_django/issues/339 | R91: =IFERROR(__xludf.DUMMYFUNCTION("IF(REGEXMATCH(N91, ""PRIORITY: Low""), ""Low"", IF(REGEXMATCH(N91, ""PRIORITY: Medium""), ""Medium"", IF(REGEXMATCH(N91, ""PRIORITY: High""), ""High"", """"))) "),"") | S91: =IFERROR(__xludf.DUMMYFUNCTION("IF(REGEXMATCH(N91, ""SKILL: Low""), ""Low"", IF(REGEXMATCH(N91, ""SKILL: Medium""), ""Medium"", IF(REGEXMATCH(N91, ""SKILL: High""), ""High"", """")))"),"") | T91: =IFERROR(__xludf.DUMMYFUNCTION("IF(REGEXMATCH(N91, ""STATUS: Dev Complete - Awaiting QA""), ""Dev Complete - Awaiting QA"", IF(REGEXMATCH(N91, ""STATUS: Follow-Up Required""), ""Follow-Up Required"", IF(REGEXMATCH(N91, ""STATUS: In Progress""), ""In Progress"", IF(REGEXMATCH(N91, ""STAT"&"US: In QA""), ""In QA"", IF(REGEXMATCH(N91, ""STATUS: Needs Customer Feedback""), ""Needs Customer Feedback"", IF(REGEXMATCH(N91, ""STATUS: QA Passed - Awaiting Release""), ""QA Passed - Awaiting Release"", IF(REGEXMATCH(N91, ""STATUS: Release to Prod""),"&" ""Release to Prod"", """")))))))"),"")
A92: cloudwarriors-ai/zoom_presales_django | B92: ZoomWarriors v1 | C92: 338 | D92: SOW/Quote Changes & Updates - Not Displaying new message in ZW_SOW Chat | E92: closed | F92: 2025-06-10T20:03:22Z | G92: =IF(I92="", "", TEXT(DATEVALUE(LEFT(F92, 10)), "dd-mmm-yyyy")) -> 10-Jun-2025 | H92: rebecca-cichy | I92: 2025-07-31T22:39:03Z | J92: =IF(I92="", "", TEXT(DATEVALUE(LEFT(I92, 10)), "dd-mmm-yyyy")) -> 31-Jul-2025 | K92: 2025-06-24T19:33:29Z | L92: =IF(K92="", "", TEXT(DATEVALUE(LEFT(K92, 10)), "dd-mmm-yyyy")) -> 24-Jun-2025 | M92: Bug | N92: None | O92: Jeffrey-Searcy, rebecca-cichy | P92: 2 | Q92: https://github.com/cloudwarriors-ai/zoom_presales_django/issues/338 | R92: =IFERROR(__xludf.DUMMYFUNCTION("IF(REGEXMATCH(N92, ""PRIORITY: Low""), ""Low"", IF(REGEXMATCH(N92, ""PRIORITY: Medium""), ""Medium"", IF(REGEXMATCH(N92, ""PRIORITY: High""), ""High"", """"))) "),"") | S92: =IFERROR(__xludf.DUMMYFUNCTION("IF(REGEXMATCH(N92, ""SKILL: Low""), ""Low"", IF(REGEXMATCH(N92, ""SKILL: Medium""), ""Medium"", IF(REGEXMATCH(N92, ""SKILL: High""), ""High"", """")))"),"") | T92: =IFERROR(__xludf.DUMMYFUNCTION("IF(REGEXMATCH(N92, ""STATUS: Dev Complete - Awaiting QA""), ""Dev Complete - Awaiting QA"", IF(REGEXMATCH(N92, ""STATUS: Follow-Up Required""), ""Follow-Up Required"", IF(REGEXMATCH(N92, ""STATUS: In Progress""), ""In Progress"", IF(REGEXMATCH(N92, ""STAT"&"US: In QA""), ""In QA"", IF(REGEXMATCH(N92, ""STATUS: Needs Customer Feedback""), ""Needs Customer Feedback"", IF(REGEXMATCH(N92, ""STATUS: QA Passed - Awaiting Release""), ""QA Passed - Awaiting Release"", IF(REGEXMATCH(N92, ""STATUS: Release to Prod""),"&" ""Release to Prod"", """")))))))"),"")
A93: cloudwarriors-ai/zoom_presales_django | B93: ZoomWarriors v1 | C93: 337 | D93: ZP Locations Page - Change North America to United States | E93: closed | F93: 2025-06-10T19:43:01Z | G93: =IF(I93="", "", TEXT(DATEVALUE(LEFT(F93, 10)), "dd-mmm-yyyy")) -> 10-Jun-2025 | H93: rebecca-cichy | I93: 2025-09-26T14:48:05Z | J93: =IF(I93="", "", TEXT(DATEVALUE(LEFT(I93, 10)), "dd-mmm-yyyy")) -> 26-Sep-2025 | K93: 2025-06-27T00:58:11Z | L93: =IF(K93="", "", TEXT(DATEVALUE(LEFT(K93, 10)), "dd-mmm-yyyy")) -> 27-Jun-2025 | M93: Bug | N93: None | P93: 4 | Q93: https://github.com/cloudwarriors-ai/zoom_presales_django/issues/337 | R93: =IFERROR(__xludf.DUMMYFUNCTION("IF(REGEXMATCH(N93, ""PRIORITY: Low""), ""Low"", IF(REGEXMATCH(N93, ""PRIORITY: Medium""), ""Medium"", IF(REGEXMATCH(N93, ""PRIORITY: High""), ""High"", """"))) "),"") | S93: =IFERROR(__xludf.DUMMYFUNCTION("IF(REGEXMATCH(N93, ""SKILL: Low""), ""Low"", IF(REGEXMATCH(N93, ""SKILL: Medium""), ""Medium"", IF(REGEXMATCH(N93, ""SKILL: High""), ""High"", """")))"),"") | T93: =IFERROR(__xludf.DUMMYFUNCTION("IF(REGEXMATCH(N93, ""STATUS: Dev Complete - Awaiting QA""), ""Dev Complete - Awaiting QA"", IF(REGEXMATCH(N93, ""STATUS: Follow-Up Required""), ""Follow-Up Required"", IF(REGEXMATCH(N93, ""STATUS: In Progress""), ""In Progress"", IF(REGEXMATCH(N93, ""STAT"&"US: In QA""), ""In QA"", IF(REGEXMATCH(N93, ""STATUS: Needs Customer Feedback""), ""Needs Customer Feedback"", IF(REGEXMATCH(N93, ""STATUS: QA Passed - Awaiting Release""), ""QA Passed - Awaiting Release"", IF(REGEXMATCH(N93, ""STATUS: Release to Prod""),"&" ""Release to Prod"", """")))))))"),"")
A94: cloudwarriors-ai/zoom_presales_django | B94: ZoomWarriors v1 | C94: 336 | D94: ZW Login Page - Add Ability to See/Unhide Password | E94: closed | F94: 2025-06-10T15:10:26Z | G94: =IF(I94="", "", TEXT(DATEVALUE(LEFT(F94, 10)), "dd-mmm-yyyy")) -> 10-Jun-2025 | H94: rebecca-cichy | I94: 2025-09-26T14:48:05Z | J94: =IF(I94="", "", TEXT(DATEVALUE(LEFT(I94, 10)), "dd-mmm-yyyy")) -> 26-Sep-2025 | K94: 2025-06-27T02:18:06Z | L94: =IF(K94="", "", TEXT(DATEVALUE(LEFT(K94, 10)), "dd-mmm-yyyy")) -> 27-Jun-2025 | M94: Feature | N94: None | P94: 5 | Q94: https://github.com/cloudwarriors-ai/zoom_presales_django/issues/336 | R94: =IFERROR(__xludf.DUMMYFUNCTION("IF(REGEXMATCH(N94, ""PRIORITY: Low""), ""Low"", IF(REGEXMATCH(N94, ""PRIORITY: Medium""), ""Medium"", IF(REGEXMATCH(N94, ""PRIORITY: High""), ""High"", """"))) "),"") | S94: =IFERROR(__xludf.DUMMYFUNCTION("IF(REGEXMATCH(N94, ""SKILL: Low""), ""Low"", IF(REGEXMATCH(N94, ""SKILL: Medium""), ""Medium"", IF(REGEXMATCH(N94, ""SKILL: High""), ""High"", """")))"),"") | T94: =IFERROR(__xludf.DUMMYFUNCTION("IF(REGEXMATCH(N94, ""STATUS: Dev Complete - Awaiting QA""), ""Dev Complete - Awaiting QA"", IF(REGEXMATCH(N94, ""STATUS: Follow-Up Required""), ""Follow-Up Required"", IF(REGEXMATCH(N94, ""STATUS: In Progress""), ""In Progress"", IF(REGEXMATCH(N94, ""STAT"&"US: In QA""), ""In QA"", IF(REGEXMATCH(N94, ""STATUS: Needs Customer Feedback""), ""Needs Customer Feedback"", IF(REGEXMATCH(N94, ""STATUS: QA Passed - Awaiting Release""), ""QA Passed - Awaiting Release"", IF(REGEXMATCH(N94, ""STATUS: Release to Prod""),"&" ""Release to Prod"", """")))))))"),"")
A95: cloudwarriors-ai/zoom_presales_django | B95: ZoomWarriors v1 | C95: 334 | D95: ZP & ZCC Additions Page - Remove Selection Buttons | E95: closed | F95: 2025-06-07T12:36:14Z | G95: =IF(I95="", "", TEXT(DATEVALUE(LEFT(F95, 10)), "dd-mmm-yyyy")) -> 07-Jun-2025 | H95: rebecca-cichy | I95: 2025-08-06T19:10:29Z | J95: =IF(I95="", "", TEXT(DATEVALUE(LEFT(I95, 10)), "dd-mmm-yyyy")) -> 06-Aug-2025 | K95: 2025-08-06T19:10:29Z | L95: =IF(K95="", "", TEXT(DATEVALUE(LEFT(K95, 10)), "dd-mmm-yyyy")) -> 06-Aug-2025 | M95: Bug | N95: PRIORITY: Low, SKILL: Low, STATUS: Follow-Up Required | O95: rebecca-cichy | P95: 6 | Q95: https://github.com/cloudwarriors-ai/zoom_presales_django/issues/334 | R95: =IFERROR(__xludf.DUMMYFUNCTION("IF(REGEXMATCH(N95, ""PRIORITY: Low""), ""Low"", IF(REGEXMATCH(N95, ""PRIORITY: Medium""), ""Medium"", IF(REGEXMATCH(N95, ""PRIORITY: High""), ""High"", """"))) "),"Low") -> Low | S95: =IFERROR(__xludf.DUMMYFUNCTION("IF(REGEXMATCH(N95, ""SKILL: Low""), ""Low"", IF(REGEXMATCH(N95, ""SKILL: Medium""), ""Medium"", IF(REGEXMATCH(N95, ""SKILL: High""), ""High"", """")))"),"Low") -> Low | T95: =IFERROR(__xludf.DUMMYFUNCTION("IF(REGEXMATCH(N95, ""STATUS: Dev Complete - Awaiting QA""), ""Dev Complete - Awaiting QA"", IF(REGEXMATCH(N95, ""STATUS: Follow-Up Required""), ""Follow-Up Required"", IF(REGEXMATCH(N95, ""STATUS: In Progress""), ""In Progress"", IF(REGEXMATCH(N95, ""STAT"&"US: In QA""), ""In QA"", IF(REGEXMATCH(N95, ""STATUS: Needs Customer Feedback""), ""Needs Customer Feedback"", IF(REGEXMATCH(N95, ""STATUS: QA Passed - Awaiting Release""), ""QA Passed - Awaiting Release"", IF(REGEXMATCH(N95, ""STATUS: Release to Prod""),"&" ""Release to Prod"", """")))))))"),"Follow-Up Required") -> Follow-Up Required
A96: cloudwarriors-ai/zoom_presales_django | B96: ZoomWarriors v1 | C96: 333 | D96: Final Submission Page - Remove Partner Reference | E96: closed | F96: 2025-06-07T12:32:38Z | G96: =IF(I96="", "", TEXT(DATEVALUE(LEFT(F96, 10)), "dd-mmm-yyyy")) -> 07-Jun-2025 | H96: rebecca-cichy | I96: 2025-09-26T14:48:05Z | J96: =IF(I96="", "", TEXT(DATEVALUE(LEFT(I96, 10)), "dd-mmm-yyyy")) -> 26-Sep-2025 | K96: 2025-06-27T01:05:40Z | L96: =IF(K96="", "", TEXT(DATEVALUE(LEFT(K96, 10)), "dd-mmm-yyyy")) -> 27-Jun-2025 | M96: Bug | N96: None | P96: 4 | Q96: https://github.com/cloudwarriors-ai/zoom_presales_django/issues/333 | R96: =IFERROR(__xludf.DUMMYFUNCTION("IF(REGEXMATCH(N96, ""PRIORITY: Low""), ""Low"", IF(REGEXMATCH(N96, ""PRIORITY: Medium""), ""Medium"", IF(REGEXMATCH(N96, ""PRIORITY: High""), ""High"", """"))) "),"") | S96: =IFERROR(__xludf.DUMMYFUNCTION("IF(REGEXMATCH(N96, ""SKILL: Low""), ""Low"", IF(REGEXMATCH(N96, ""SKILL: Medium""), ""Medium"", IF(REGEXMATCH(N96, ""SKILL: High""), ""High"", """")))"),"") | T96: =IFERROR(__xludf.DUMMYFUNCTION("IF(REGEXMATCH(N96, ""STATUS: Dev Complete - Awaiting QA""), ""Dev Complete - Awaiting QA"", IF(REGEXMATCH(N96, ""STATUS: Follow-Up Required""), ""Follow-Up Required"", IF(REGEXMATCH(N96, ""STATUS: In Progress""), ""In Progress"", IF(REGEXMATCH(N96, ""STAT"&"US: In QA""), ""In QA"", IF(REGEXMATCH(N96, ""STATUS: Needs Customer Feedback""), ""Needs Customer Feedback"", IF(REGEXMATCH(N96, ""STATUS: QA Passed - Awaiting Release""), ""QA Passed - Awaiting Release"", IF(REGEXMATCH(N96, ""STATUS: Release to Prod""),"&" ""Release to Prod"", """")))))))"),"")
A97: cloudwarriors-ai/zoom_presales_django | B97: ZoomWarriors v1 | C97: 332 | D97: Excessive SOW Email Communication | E97: closed | F97: 2025-06-07T12:28:20Z | G97: =IF(I97="", "", TEXT(DATEVALUE(LEFT(F97, 10)), "dd-mmm-yyyy")) -> 07-Jun-2025 | H97: rebecca-cichy | I97: 2025-09-26T14:48:04Z | J97: =IF(I97="", "", TEXT(DATEVALUE(LEFT(I97, 10)), "dd-mmm-yyyy")) -> 26-Sep-2025 | K97: 2025-06-24T17:07:16Z | L97: =IF(K97="", "", TEXT(DATEVALUE(LEFT(K97, 10)), "dd-mmm-yyyy")) -> 24-Jun-2025 | M97: Bug | N97: None | O97: Jeffrey-Searcy, rebecca-cichy | P97: 5 | Q97: https://github.com/cloudwarriors-ai/zoom_presales_django/issues/332 | R97: =IFERROR(__xludf.DUMMYFUNCTION("IF(REGEXMATCH(N97, ""PRIORITY: Low""), ""Low"", IF(REGEXMATCH(N97, ""PRIORITY: Medium""), ""Medium"", IF(REGEXMATCH(N97, ""PRIORITY: High""), ""High"", """"))) "),"") | S97: =IFERROR(__xludf.DUMMYFUNCTION("IF(REGEXMATCH(N97, ""SKILL: Low""), ""Low"", IF(REGEXMATCH(N97, ""SKILL: Medium""), ""Medium"", IF(REGEXMATCH(N97, ""SKILL: High""), ""High"", """")))"),"") | T97: =IFERROR(__xludf.DUMMYFUNCTION("IF(REGEXMATCH(N97, ""STATUS: Dev Complete - Awaiting QA""), ""Dev Complete - Awaiting QA"", IF(REGEXMATCH(N97, ""STATUS: Follow-Up Required""), ""Follow-Up Required"", IF(REGEXMATCH(N97, ""STATUS: In Progress""), ""In Progress"", IF(REGEXMATCH(N97, ""STAT"&"US: In QA""), ""In QA"", IF(REGEXMATCH(N97, ""STATUS: Needs Customer Feedback""), ""Needs Customer Feedback"", IF(REGEXMATCH(N97, ""STATUS: QA Passed - Awaiting Release""), ""QA Passed - Awaiting Release"", IF(REGEXMATCH(N97, ""STATUS: Release to Prod""),"&" ""Release to Prod"", """")))))))"),"")
A98: cloudwarriors-ai/zoom_presales_django | B98: ZoomWarriors v1 | C98: 330 | D98: SOW Issue - ARs & Queues not matching | E98: closed | F98: 2025-06-05T21:18:48Z | G98: =IF(I98="", "", TEXT(DATEVALUE(LEFT(F98, 10)), "dd-mmm-yyyy")) -> 05-Jun-2025 | H98: Jeffrey-Searcy | I98: 2025-07-31T22:39:01Z | J98: =IF(I98="", "", TEXT(DATEVALUE(LEFT(I98, 10)), "dd-mmm-yyyy")) -> 31-Jul-2025 | K98: 2025-07-11T17:33:37Z | L98: =IF(K98="", "", TEXT(DATEVALUE(LEFT(K98, 10)), "dd-mmm-yyyy")) -> 11-Jul-2025 | M98: Bug | N98: None | P98: 8 | Q98: https://github.com/cloudwarriors-ai/zoom_presales_django/issues/330 | R98: =IFERROR(__xludf.DUMMYFUNCTION("IF(REGEXMATCH(N98, ""PRIORITY: Low""), ""Low"", IF(REGEXMATCH(N98, ""PRIORITY: Medium""), ""Medium"", IF(REGEXMATCH(N98, ""PRIORITY: High""), ""High"", """"))) "),"") | S98: =IFERROR(__xludf.DUMMYFUNCTION("IF(REGEXMATCH(N98, ""SKILL: Low""), ""Low"", IF(REGEXMATCH(N98, ""SKILL: Medium""), ""Medium"", IF(REGEXMATCH(N98, ""SKILL: High""), ""High"", """")))"),"") | T98: =IFERROR(__xludf.DUMMYFUNCTION("IF(REGEXMATCH(N98, ""STATUS: Dev Complete - Awaiting QA""), ""Dev Complete - Awaiting QA"", IF(REGEXMATCH(N98, ""STATUS: Follow-Up Required""), ""Follow-Up Required"", IF(REGEXMATCH(N98, ""STATUS: In Progress""), ""In Progress"", IF(REGEXMATCH(N98, ""STAT"&"US: In QA""), ""In QA"", IF(REGEXMATCH(N98, ""STATUS: Needs Customer Feedback""), ""Needs Customer Feedback"", IF(REGEXMATCH(N98, ""STATUS: QA Passed - Awaiting Release""), ""QA Passed - Awaiting Release"", IF(REGEXMATCH(N98, ""STATUS: Release to Prod""),"&" ""Release to Prod"", """")))))))"),"")
A99: cloudwarriors-ai/zoom_presales_django | B99: ZoomWarriors v1 | C99: 328 | D99: Update Final Submission Statement | E99: closed | F99: 2025-06-04T19:35:38Z | G99: =IF(I99="", "", TEXT(DATEVALUE(LEFT(F99, 10)), "dd-mmm-yyyy")) -> 04-Jun-2025 | H99: rebecca-cichy | I99: 2025-07-31T22:39:01Z | J99: =IF(I99="", "", TEXT(DATEVALUE(LEFT(I99, 10)), "dd-mmm-yyyy")) -> 31-Jul-2025 | K99: 2025-06-06T20:55:46Z | L99: =IF(K99="", "", TEXT(DATEVALUE(LEFT(K99, 10)), "dd-mmm-yyyy")) -> 06-Jun-2025 | M99: Bug | N99: None | O99: Jeffrey-Searcy | P99: 2 | Q99: https://github.com/cloudwarriors-ai/zoom_presales_django/issues/328 | R99: =IFERROR(__xludf.DUMMYFUNCTION("IF(REGEXMATCH(N99, ""PRIORITY: Low""), ""Low"", IF(REGEXMATCH(N99, ""PRIORITY: Medium""), ""Medium"", IF(REGEXMATCH(N99, ""PRIORITY: High""), ""High"", """"))) "),"") | S99: =IFERROR(__xludf.DUMMYFUNCTION("IF(REGEXMATCH(N99, ""SKILL: Low""), ""Low"", IF(REGEXMATCH(N99, ""SKILL: Medium""), ""Medium"", IF(REGEXMATCH(N99, ""SKILL: High""), ""High"", """")))"),"") | T99: =IFERROR(__xludf.DUMMYFUNCTION("IF(REGEXMATCH(N99, ""STATUS: Dev Complete - Awaiting QA""), ""Dev Complete - Awaiting QA"", IF(REGEXMATCH(N99, ""STATUS: Follow-Up Required""), ""Follow-Up Required"", IF(REGEXMATCH(N99, ""STATUS: In Progress""), ""In Progress"", IF(REGEXMATCH(N99, ""STAT"&"US: In QA""), ""In QA"", IF(REGEXMATCH(N99, ""STATUS: Needs Customer Feedback""), ""Needs Customer Feedback"", IF(REGEXMATCH(N99, ""STATUS: QA Passed - Awaiting Release""), ""QA Passed - Awaiting Release"", IF(REGEXMATCH(N99, ""STATUS: Release to Prod""),"&" ""Release to Prod"", """")))))))"),"")
A100: cloudwarriors-ai/zoom_presales_django | B100: ZoomWarriors v1 | C100: 327 | D100: Cloud Warrirors Cost w/o Margin Page - Add & Italicize Clause at the bottom of Page | E100: closed | F100: 2025-06-04T19:23:44Z | G100: =IF(I100="", "", TEXT(DATEVALUE(LEFT(F100, 10)), "dd-mmm-yyyy")) -> 04-Jun-2025 | H100: rebecca-cichy | I100: 2025-07-11T21:00:38Z | J100: =IF(I100="", "", TEXT(DATEVALUE(LEFT(I100, 10)), "dd-mmm-yyyy")) -> 11-Jul-2025 | K100: 2025-06-06T20:57:28Z | L100: =IF(K100="", "", TEXT(DATEVALUE(LEFT(K100, 10)), "dd-mmm-yyyy")) -> 06-Jun-2025 | M100: Feature | N100: None | O100: Jeffrey-Searcy | P100: 1 | Q100: https://github.com/cloudwarriors-ai/zoom_presales_django/issues/327 | R100: =IFERROR(__xludf.DUMMYFUNCTION("IF(REGEXMATCH(N100, ""PRIORITY: Low""), ""Low"", IF(REGEXMATCH(N100, ""PRIORITY: Medium""), ""Medium"", IF(REGEXMATCH(N100, ""PRIORITY: High""), ""High"", """"))) "),"") | S100: =IFERROR(__xludf.DUMMYFUNCTION("IF(REGEXMATCH(N100, ""SKILL: Low""), ""Low"", IF(REGEXMATCH(N100, ""SKILL: Medium""), ""Medium"", IF(REGEXMATCH(N100, ""SKILL: High""), ""High"", """")))"),"") | T100: =IFERROR(__xludf.DUMMYFUNCTION("IF(REGEXMATCH(N100, ""STATUS: Dev Complete - Awaiting QA""), ""Dev Complete - Awaiting QA"", IF(REGEXMATCH(N100, ""STATUS: Follow-Up Required""), ""Follow-Up Required"", IF(REGEXMATCH(N100, ""STATUS: In Progress""), ""In Progress"", IF(REGEXMATCH(N100, """&"STATUS: In QA""), ""In QA"", IF(REGEXMATCH(N100, ""STATUS: Needs Customer Feedback""), ""Needs Customer Feedback"", IF(REGEXMATCH(N100, ""STATUS: QA Passed - Awaiting Release""), ""QA Passed - Awaiting Release"", IF(REGEXMATCH(N100, ""STATUS: Release to P"&"rod""), ""Release to Prod"", """")))))))"),"")
...
